Workbook
Name Клиенты: [1]!ТабКлиенты[name]
Name Клиенты: [1]!ТабКлиенты[name]
Name Клиенты: ТабКлиенты[name]

Sheet Маршрут
B1: 47.1193, 37.5172 | C1: =IFERROR(REPLACE(B1,SEARCH(",",B1),2,"%2C"),"") -> 47.1193%2C37.5172
B2: 47.1281, 37.5732 | C2: =IFERROR(REPLACE(B2,SEARCH(",",B2),2,"%2C"),"") -> 47.1281%2C37.5732
B3: 47.1149, 37.5127 | C3: =IFERROR(REPLACE(B3,SEARCH(",",B3),2,"%2C"),"") -> 47.1149%2C37.5127
B4: 47.0898, 37.5062 | C4: =IFERROR(REPLACE(B4,SEARCH(",",B4),2,"%2C"),"") -> 47.0898%2C37.5062
B5: 47.087079, 37.519275 | C5: =IFERROR(REPLACE(B5,SEARCH(",",B5),2,"%2C"),"") -> 47.087079%2C37.519275
C6: =IFERROR(REPLACE(B6,SEARCH(",",B6),2,"%2C"),"")
C7: =IFERROR(REPLACE(B7,SEARCH(",",B7),2,"%2C"),"")
C8: =IFERROR(REPLACE(B8,SEARCH(",",B8),2,"%2C"),"")
C9: =IFERROR(REPLACE(B9,SEARCH(",",B9),2,"%2C"),"")
C10: =IFERROR(REPLACE(B10,SEARCH(",",B10),2,"%2C"),"")
C11: =IFERROR(REPLACE(B11,SEARCH(",",B11),2,"%2C"),"")
C12: =IFERROR(REPLACE(B12,SEARCH(",",B12),2,"%2C"),"")
C13: =IFERROR(REPLACE(B13,SEARCH(",",B13),2,"%2C"),"")
C14: =IFERROR(REPLACE(B14,SEARCH(",",B14),2,"%2C"),"")
C15: =IFERROR(REPLACE(B15,SEARCH(",",B15),2,"%2C"),"") | D15: ="https://yandex.ru/maps/?mode=routes&rtext="&C1&"~"&C2&"~"&C3&"~"&C4&"~"&C5&"~"&C6&"~"&C7&"~"&C8&"~"&C9&"~"&C10&"~"&C11&"~"&C12&"~"&C13&"~"&C14&"~"&C15&"~"&C16&"~"&C17&"~"&C18&"~"&C19&"~"&C20&"~"&C21 -> https://yandex.ru/maps/?mode=routes&rtext=47.1193%2C37.5172~47.1281%2C37.5732~47.1149%2C37.5127~47.0898%2C37.5062~47.087079%2C37.519275~~~~~~~~~~~~~~~~
C16: =IFERROR(REPLACE(B16,SEARCH(",",B16),2,"%2C"),"")
C17: =IFERROR(REPLACE(B17,SEARCH(",",B17),2,"%2C"),"")
C18: =IFERROR(REPLACE(B18,SEARCH(",",B18),2,"%2C"),"")
C19: =IFERROR(REPLACE(B19,SEARCH(",",B19),2,"%2C"),"")
C20: =IFERROR(REPLACE(B20,SEARCH(",",B20),2,"%2C"),"")
C21: =IFERROR(REPLACE(B21,SEARCH(",",B21),2,"%2C"),"")

Sheet Доставка
B1: Дата | C1: name | D1: phone | E1: address | F1: GPS | G1: Время | H1: Summ | I1: № Заказов | J1: Мест | K1: Шаблон
A2: 1 | B2: 45391 | C2: Елена пер. Фруктовый | D2: =VLOOKUP($C2,ТабКлиенты[[#All],[name]:[phone]],MATCH(D$1,ТабКлиенты[#Headers],0)-1,0) -> +79497190408 | E2: =VLOOKUP($C2,ТабАдрес[[#All],[Клиент]:[gps]],MATCH(E$1,ТабКлиенты[#Headers],0)-4,0) -> Проектная 10 | F2: =VLOOKUP($C2,ТабАдрес[[#All],[Клиент]:[gps]],MATCH(F$1,ТабКлиенты[#Headers],0)-4,0) -> 47.1281, 37.5732 | H2: 3400 | K2: =A2&". "&C2&CHAR(10)&"Тел.: "&D2&CHAR(10)&"Адрес: "&E2&" ("&I2&")"&CHAR(10)&"https://yandex.ru/maps/?text="&REPLACE(F2,SEARCH(",",F2),2,"%2C")&CHAR(10)&"https://maps.google.com/?daddr="&REPLACE(F2,SEARCH(",",F2),2,"%2C")&CHAR(10)&"К оплате: "&H2&CHAR(10)&"----------------------------------------------------------" -> 1. Елена пер. Фруктовый Тел.: +79497190408 Адрес: Проектная 10 () https://yandex.ru/maps/?text=47.1281%2C37.5732 https://maps.google.com/?daddr=47.1281%2C37.5732 К оплате: 3400 ----------------------------------------------------------
A3: 2 | B3: 45391 | C3: Лариса Кирова | D3: =VLOOKUP($C3,ТабКлиенты[[#All],[name]:[phone]],MATCH(D$1,ТабКлиенты[#Headers],0)-1,0) -> #N/A | E3: =VLOOKUP($C3,ТабАдрес[[#All],[Клиент]:[gps]],MATCH(E$1,ТабКлиенты[#Headers],0)-4,0) -> #N/A | F3: =VLOOKUP($C3,ТабАдрес[[#All],[Клиент]:[gps]],MATCH(F$1,ТабКлиенты[#Headers],0)-4,0) -> #N/A | H3: 0 | K3: =A3&". "&C3&CHAR(10)&"Тел.: "&D3&CHAR(10)&"Адрес: "&E3&" ("&I3&")"&CHAR(10)&"https://yandex.ru/maps/?text="&REPLACE(F3,SEARCH(",",F3),2,"%2C")&CHAR(10)&"https://maps.google.com/?daddr="&REPLACE(F3,SEARCH(",",F3),2,"%2C")&CHAR(10)&"К оплате: "&H3&CHAR(10)&"----------------------------------------------------------" -> #N/A
A4: 3 | B4: 45391 | C4: Галина Агабекова(церковь) | D4: =VLOOKUP($C4,ТабКлиенты[[#All],[name]:[phone]],MATCH(D$1,ТабКлиенты[#Headers],0)-1,0) -> #N/A | E4: =VLOOKUP($C4,ТабАдрес[[#All],[Клиент]:[gps]],MATCH(E$1,ТабКлиенты[#Headers],0)-4,0) -> #N/A | F4: =VLOOKUP($C4,ТабАдрес[[#All],[Клиент]:[gps]],MATCH(F$1,ТабКлиенты[#Headers],0)-4,0) -> #N/A | H4: 6196 | K4: =A4&". "&C4&CHAR(10)&"Тел.: "&D4&CHAR(10)&"Адрес: "&E4&" ("&I4&")"&CHAR(10)&"https://yandex.ru/maps/?text="&REPLACE(F4,SEARCH(",",F4),2,"%2C")&CHAR(10)&"https://maps.google.com/?daddr="&REPLACE(F4,SEARCH(",",F4),2,"%2C")&CHAR(10)&"К оплате: "&H4&CHAR(10)&"----------------------------------------------------------" -> #N/A
A5: 4 | B5: 45391 | C5: Алексей перфоратор | D5: =VLOOKUP($C5,ТабКлиенты[[#All],[name]:[phone]],MATCH(D$1,ТабКлиенты[#Headers],0)-1,0) -> #N/A | E5: =VLOOKUP($C5,ТабАдрес[[#All],[Клиент]:[gps]],MATCH(E$1,ТабКлиенты[#Headers],0)-4,0) -> #N/A | F5: =VLOOKUP($C5,ТабАдрес[[#All],[Клиент]:[gps]],MATCH(F$1,ТабКлиенты[#Headers],0)-4,0) -> #N/A | H5: 0 | K5: =A5&". "&C5&CHAR(10)&"Тел.: "&D5&CHAR(10)&"Адрес: "&E5&" ("&I5&")"&CHAR(10)&"https://yandex.ru/maps/?text="&REPLACE(F5,SEARCH(",",F5),2,"%2C")&CHAR(10)&"https://maps.google.com/?daddr="&REPLACE(F5,SEARCH(",",F5),2,"%2C")&CHAR(10)&"К оплате: "&H5&CHAR(10)&"----------------------------------------------------------" -> #N/A
A6: 5 | B6: 45391 | C6: Кирилл Урицкого 104 | D6: =VLOOKUP($C6,ТабКлиенты[[#All],[name]:[phone]],MATCH(D$1,ТабКлиенты[#Headers],0)-1,0) -> #N/A | E6: =VLOOKUP($C6,ТабАдрес[[#All],[Клиент]:[gps]],MATCH(E$1,ТабКлиенты[#Headers],0)-4,0) -> #N/A | F6: =VLOOKUP($C6,ТабАдрес[[#All],[Клиент]:[gps]],MATCH(F$1,ТабКлиенты[#Headers],0)-4,0) -> #N/A | H6: 3000 | K6: =A6&". "&C6&CHAR(10)&"Тел.: "&D6&CHAR(10)&"Адрес: "&E6&" ("&I6&")"&CHAR(10)&"https://yandex.ru/maps/?text="&REPLACE(F6,SEARCH(",",F6),2,"%2C")&CHAR(10)&"https://maps.google.com/?daddr="&REPLACE(F6,SEARCH(",",F6),2,"%2C")&CHAR(10)&"К оплате: "&H6&CHAR(10)&"----------------------------------------------------------" -> #N/A
A7: 6 | B7: 45391 | C7: Александр 3 База | D7: =VLOOKUP($C7,ТабКлиенты[[#All],[name]:[phone]],MATCH(D$1,ТабКлиенты[#Headers],0)-1,0) -> #N/A | E7: =VLOOKUP($C7,ТабАдрес[[#All],[Клиент]:[gps]],MATCH(E$1,ТабКлиенты[#Headers],0)-4,0) -> #N/A | F7: =VLOOKUP($C7,ТабАдрес[[#All],[Клиент]:[gps]],MATCH(F$1,ТабКлиенты[#Headers],0)-4,0) -> #N/A | H7: 2260 | K7: =A7&". "&C7&CHAR(10)&"Тел.: "&D7&CHAR(10)&"Адрес: "&E7&" ("&I7&")"&CHAR(10)&"https://yandex.ru/maps/?text="&REPLACE(F7,SEARCH(",",F7),2,"%2C")&CHAR(10)&"https://maps.google.com/?daddr="&REPLACE(F7,SEARCH(",",F7),2,"%2C")&CHAR(10)&"К оплате: "&H7&CHAR(10)&"----------------------------------------------------------" -> #N/A
A8: 7 | B8: 45391 | C8: Наталья Вельвет | D8: =VLOOKUP($C8,ТабКлиенты[[#All],[name]:[phone]],MATCH(D$1,ТабКлиенты[#Headers],0)-1,0) -> +79497385016 | E8: =VLOOKUP($C8,ТабАдрес[[#All],[Клиент]:[gps]],MATCH(E$1,ТабКлиенты[#Headers],0)-4,0) -> Шевченко 285А | F8: =VLOOKUP($C8,ТабАдрес[[#All],[Клиент]:[gps]],MATCH(F$1,ТабКлиенты[#Headers],0)-4,0) -> 47.1169, 37.5258 | H8: 1800 | K8: =A8&". "&C8&CHAR(10)&"Тел.: "&D8&CHAR(10)&"Адрес: "&E8&" ("&I8&")"&CHAR(10)&"https://yandex.ru/maps/?text="&REPLACE(F8,SEARCH(",",F8),2,"%2C")&CHAR(10)&"https://maps.google.com/?daddr="&REPLACE(F8,SEARCH(",",F8),2,"%2C")&CHAR(10)&"К оплате: "&H8&CHAR(10)&"----------------------------------------------------------" -> 7. Наталья Вельвет Тел.: +79497385016 Адрес: Шевченко 285А () https://yandex.ru/maps/?text=47.1169%2C37.5258 https://maps.google.com/?daddr=47.1169%2C37.5258 К оплате: 1800 ----------------------------------------------------------
A9: 1 | B9: 45402 | C9: Митрофанов Евгений | D9: =VLOOKUP($C9,ТабКлиенты[[#All],[name]:[phone]],MATCH(D$1,ТабКлиенты[#Headers],0)-1,0) -> #N/A | E9: =VLOOKUP($C9,ТабАдрес[[#All],[Клиент]:[gps]],MATCH(E$1,ТабКлиенты[#Headers],0)-4,0) -> #N/A | F9: =VLOOKUP($C9,ТабАдрес[[#All],[Клиент]:[gps]],MATCH(F$1,ТабКлиенты[#Headers],0)-4,0) -> #N/A | H9: 6067 | I9: 50 | K9: =A9&". "&C9&CHAR(10)&"Тел.: "&D9&CHAR(10)&"Адрес: "&E9&" ("&I9&")"&CHAR(10)&"https://yandex.ru/maps/?text="&REPLACE(F9,SEARCH(",",F9),2,"%2C")&CHAR(10)&"https://maps.google.com/?daddr="&REPLACE(F9,SEARCH(",",F9),2,"%2C")&CHAR(10)&"К оплате: "&H9&CHAR(10)&"----------------------------------------------------------" -> #N/A
A10: 2 | B10: 45402 | C10: Александр 3 Металлургов | D10: =VLOOKUP($C10,ТабКлиенты[[#All],[name]:[phone]],MATCH(D$1,ТабКлиенты[#Headers],0)-1,0) -> #N/A | E10: =VLOOKUP($C10,ТабАдрес[[#All],[Клиент]:[gps]],MATCH(E$1,ТабКлиенты[#Headers],0)-4,0) -> #N/A | F10: =VLOOKUP($C10,ТабАдрес[[#All],[Клиент]:[gps]],MATCH(F$1,ТабКлиенты[#Headers],0)-4,0) -> #N/A | H10: 0 | I10: 52 | K10: =A10&". "&C10&CHAR(10)&"Тел.: "&D10&CHAR(10)&"Адрес: "&E10&" ("&I10&")"&CHAR(10)&"https://yandex.ru/maps/?text="&REPLACE(F10,SEARCH(",",F10),2,"%2C")&CHAR(10)&"https://maps.google.com/?daddr="&REPLACE(F10,SEARCH(",",F10),2,"%2C")&CHAR(10)&"К оплате: "&H10&CHAR(10)&"----------------------------------------------------------" -> #N/A
A11: 3 | B11: 45402 | C11: Юля Нептун | D11: =VLOOKUP($C11,ТабКлиенты[[#All],[name]:[phone]],MATCH(D$1,ТабКлиенты[#Headers],0)-1,0) -> #N/A | E11: =VLOOKUP($C11,ТабАдрес[[#All],[Клиент]:[gps]],MATCH(E$1,ТабКлиенты[#Headers],0)-4,0) -> #N/A | F11: =VLOOKUP($C11,ТабАдрес[[#All],[Клиент]:[gps]],MATCH(F$1,ТабКлиенты[#Headers],0)-4,0) -> #N/A | H11: 3000 | I11: Витамины | K11: =A11&". "&C11&CHAR(10)&"Тел.: "&D11&CHAR(10)&"Адрес: "&E11&" ("&I11&")"&CHAR(10)&"https://yandex.ru/maps/?text="&REPLACE(F11,SEARCH(",",F11),2,"%2C")&CHAR(10)&"https://maps.google.com/?daddr="&REPLACE(F11,SEARCH(",",F11),2,"%2C")&CHAR(10)&"К оплате: "&H11&CHAR(10)&"----------------------------------------------------------" -> #N/A
A12: 4 | B12: 45402 | C12: Галина Агабекова(церковь) | D12: =VLOOKUP($C12,ТабКлиенты[[#All],[name]:[phone]],MATCH(D$1,ТабКлиенты[#Headers],0)-1,0) -> #N/A | E12: =VLOOKUP($C12,ТабАдрес[[#All],[Клиент]:[gps]],MATCH(E$1,ТабКлиенты[#Headers],0)-4,0) -> #N/A | F12: =VLOOKUP($C12,ТабАдрес[[#All],[Клиент]:[gps]],MATCH(F$1,ТабКлиенты[#Headers],0)-4,0) -> #N/A | H12: 5887 | I12: 53.56 | K12: =A12&". "&C12&CHAR(10)&"Тел.: "&D12&CHAR(10)&"Адрес: "&E12&" ("&I12&")"&CHAR(10)&"https://yandex.ru/maps/?text="&REPLACE(F12,SEARCH(",",F12),2,"%2C")&CHAR(10)&"https://maps.google.com/?daddr="&REPLACE(F12,SEARCH(",",F12),2,"%2C")&CHAR(10)&"К оплате: "&H12&CHAR(10)&"----------------------------------------------------------" -> #N/A
A13: 5 | B13: 45402 | C13: Галина Шевченко 248 | D13: =VLOOKUP($C13,ТабКлиенты[[#All],[name]:[phone]],MATCH(D$1,ТабКлиенты[#Headers],0)-1,0) -> #N/A | E13: =VLOOKUP($C13,ТабАдрес[[#All],[Клиент]:[gps]],MATCH(E$1,ТабКлиенты[#Headers],0)-4,0) -> #N/A | F13: =VLOOKUP($C13,ТабАдрес[[#All],[Клиент]:[gps]],MATCH(F$1,ТабКлиенты[#Headers],0)-4,0) -> #N/A | H13: 0 | I13: 64 | K13: =A13&". "&C13&CHAR(10)&"Тел.: "&D13&CHAR(10)&"Адрес: "&E13&" ("&I13&")"&CHAR(10)&"https://yandex.ru/maps/?text="&REPLACE(F13,SEARCH(",",F13),2,"%2C")&CHAR(10)&"https://maps.google.com/?daddr="&REPLACE(F13,SEARCH(",",F13),2,"%2C")&CHAR(10)&"К оплате: "&H13&CHAR(10)&"----------------------------------------------------------" -> #N/A
A14: 6 | B14: 45402 | C14: ОТ Порт сити | D14: =VLOOKUP($C14,ТабКлиенты[[#All],[name]:[phone]],MATCH(D$1,ТабКлиенты[#Headers],0)-1,0) -> #N/A | E14: =VLOOKUP($C14,ТабАдрес[[#All],[Клиент]:[gps]],MATCH(E$1,ТабКлиенты[#Headers],0)-4,0) -> #N/A | F14: =VLOOKUP($C14,ТабАдрес[[#All],[Клиент]:[gps]],MATCH(F$1,ТабКлиенты[#Headers],0)-4,0) -> #N/A | H14: 2600 | I14: Витамины | K14: =A14&". "&C14&CHAR(10)&"Тел.: "&D14&CHAR(10)&"Адрес: "&E14&" ("&I14&")"&CHAR(10)&"https://yandex.ru/maps/?text="&REPLACE(F14,SEARCH(",",F14),2,"%2C")&CHAR(10)&"https://maps.google.com/?daddr="&REPLACE(F14,SEARCH(",",F14),2,"%2C")&CHAR(10)&"К оплате: "&H14&CHAR(10)&"----------------------------------------------------------" -> #N/A
A15: 7 | B15: 45402 | C15: Оксана 17 цветы | D15: =VLOOKUP($C15,ТабКлиенты[[#All],[name]:[phone]],MATCH(D$1,ТабКлиенты[#Headers],0)-1,0) -> 0 | E15: =VLOOKUP($C15,ТабАдрес[[#All],[Клиент]:[gps]],MATCH(E$1,ТабКлиенты[#Headers],0)-4,0) -> Троицкая 46 | F15: =VLOOKUP($C15,ТабАдрес[[#All],[Клиент]:[gps]],MATCH(F$1,ТабКлиенты[#Headers],0)-4,0) -> 47.1119, 37.5147 | H15: 4100 | I15: Витамины | K15: =A15&". "&C15&CHAR(10)&"Тел.: "&D15&CHAR(10)&"Адрес: "&E15&" ("&I15&")"&CHAR(10)&"https://yandex.ru/maps/?text="&REPLACE(F15,SEARCH(",",F15),2,"%2C")&CHAR(10)&"https://maps.google.com/?daddr="&REPLACE(F15,SEARCH(",",F15),2,"%2C")&CHAR(10)&"К оплате: "&H15&CHAR(10)&"----------------------------------------------------------" -> 7. Оксана 17 цветы Тел.: 0 Адрес: Троицкая 46 (Витамины) https://yandex.ru/maps/?text=47.1119%2C37.5147 https://maps.google.com/?daddr=47.1119%2C37.5147 К оплате: 4100 ----------------------------------------------------------
A16: 8 | B16: 45402 | C16: Елена 17 рынок | D16: =VLOOKUP($C16,ТабКлиенты[[#All],[name]:[phone]],MATCH(D$1,ТабКлиенты[#Headers],0)-1,0) -> #N/A | E16: =VLOOKUP($C16,ТабАдрес[[#All],[Клиент]:[gps]],MATCH(E$1,ТабКлиенты[#Headers],0)-4,0) -> #N/A | F16: =VLOOKUP($C16,ТабАдрес[[#All],[Клиент]:[gps]],MATCH(F$1,ТабКлиенты[#Headers],0)-4,0) -> #N/A | H16: 2400 | I16: Витамины | K16: =A16&". "&C16&CHAR(10)&"Тел.: "&D16&CHAR(10)&"Адрес: "&E16&" ("&I16&")"&CHAR(10)&"https://yandex.ru/maps/?text="&REPLACE(F16,SEARCH(",",F16),2,"%2C")&CHAR(10)&"https://maps.google.com/?daddr="&REPLACE(F16,SEARCH(",",F16),2,"%2C")&CHAR(10)&"К оплате: "&H16&CHAR(10)&"----------------------------------------------------------" -> #N/A
A17: 9 | B17: 45402 | C17: Валера Фагот | D17: =VLOOKUP($C17,ТабКлиенты[[#All],[name]:[phone]],MATCH(D$1,ТабКлиенты[#Headers],0)-1,0) -> #N/A | E17: =VLOOKUP($C17,ТабАдрес[[#All],[Клиент]:[gps]],MATCH(E$1,ТабКлиенты[#Headers],0)-4,0) -> #N/A | F17: =VLOOKUP($C17,ТабАдрес[[#All],[Клиент]:[gps]],MATCH(F$1,ТабКлиенты[#Headers],0)-4,0) -> #N/A | H17: 8700 | I17: Витамины | K17: =A17&". "&C17&CHAR(10)&"Тел.: "&D17&CHAR(10)&"Адрес: "&E17&" ("&I17&")"&CHAR(10)&"https://yandex.ru/maps/?text="&REPLACE(F17,SEARCH(",",F17),2,"%2C")&CHAR(10)&"https://maps.google.com/?daddr="&REPLACE(F17,SEARCH(",",F17),2,"%2C")&CHAR(10)&"К оплате: "&H17&CHAR(10)&"----------------------------------------------------------" -> #N/A
A18: 10 | B18: 45402 | C18: Наталья | D18: =VLOOKUP($C18,ТабКлиенты[[#All],[name]:[phone]],MATCH(D$1,ТабКлиенты[#Headers],0)-1,0) -> #N/A | E18: =VLOOKUP($C18,ТабАдрес[[#All],[Клиент]:[gps]],MATCH(E$1,ТабКлиенты[#Headers],0)-4,0) -> #N/A | F18: =VLOOKUP($C18,ТабАдрес[[#All],[Клиент]:[gps]],MATCH(F$1,ТабКлиенты[#Headers],0)-4,0) -> #N/A | H18: 6300 | I18: Витамины | K18: =A18&". "&C18&CHAR(10)&"Тел.: "&D18&CHAR(10)&"Адрес: "&E18&" ("&I18&")"&CHAR(10)&"https://yandex.ru/maps/?text="&REPLACE(F18,SEARCH(",",F18),2,"%2C")&CHAR(10)&"https://maps.google.com/?daddr="&REPLACE(F18,SEARCH(",",F18),2,"%2C")&CHAR(10)&"К оплате: "&H18&CHAR(10)&"----------------------------------------------------------" -> #N/A
A19: 11 | B19: 45402 | C19: Елена Ларисына | D19: =VLOOKUP($C19,ТабКлиенты[[#All],[name]:[phone]],MATCH(D$1,ТабКлиенты[#Headers],0)-1,0) -> #N/A | E19: =VLOOKUP($C19,ТабАдрес[[#All],[Клиент]:[gps]],MATCH(E$1,ТабКлиенты[#Headers],0)-4,0) -> #N/A | F19: =VLOOKUP($C19,ТабАдрес[[#All],[Клиент]:[gps]],MATCH(F$1,ТабКлиенты[#Headers],0)-4,0) -> #N/A | H19: 0 | I19: 54, 58, 59 | K19: =A19&". "&C19&CHAR(10)&"Тел.: "&D19&CHAR(10)&"Адрес: "&E19&" ("&I19&")"&CHAR(10)&"https://yandex.ru/maps/?text="&REPLACE(F19,SEARCH(",",F19),2,"%2C")&CHAR(10)&"https://maps.google.com/?daddr="&REPLACE(F19,SEARCH(",",F19),2,"%2C")&CHAR(10)&"К оплате: "&H19&CHAR(10)&"----------------------------------------------------------" -> #N/A
A20: 12 | B20: 45402 | C20: Лариса Кирова | D20: =VLOOKUP($C20,ТабКлиенты[[#All],[name]:[phone]],MATCH(D$1,ТабКлиенты[#Headers],0)-1,0) -> #N/A | E20: =VLOOKUP($C20,ТабАдрес[[#All],[Клиент]:[gps]],MATCH(E$1,ТабКлиенты[#Headers],0)-4,0) -> #N/A | F20: =VLOOKUP($C20,ТабАдрес[[#All],[Клиент]:[gps]],MATCH(F$1,ТабКлиенты[#Headers],0)-4,0) -> #N/A | H20: 803 | I20: 49.59 | K20: =A20&". "&C20&CHAR(10)&"Тел.: "&D20&CHAR(10)&"Адрес: "&E20&" ("&I20&")"&CHAR(10)&"https://yandex.ru/maps/?text="&REPLACE(F20,SEARCH(",",F20),2,"%2C")&CHAR(10)&"https://maps.google.com/?daddr="&REPLACE(F20,SEARCH(",",F20),2,"%2C")&CHAR(10)&"К оплате: "&H20&CHAR(10)&"----------------------------------------------------------" -> #N/A
A21: 13 | B21: 45402 | C21: Елена от Ани | D21: =VLOOKUP($C21,ТабКлиенты[[#All],[name]:[phone]],MATCH(D$1,ТабКлиенты[#Headers],0)-1,0) -> #N/A | E21: =VLOOKUP($C21,ТабАдрес[[#All],[Клиент]:[gps]],MATCH(E$1,ТабКлиенты[#Headers],0)-4,0) -> #N/A | F21: =VLOOKUP($C21,ТабАдрес[[#All],[Клиент]:[gps]],MATCH(F$1,ТабКлиенты[#Headers],0)-4,0) -> #N/A | H21: 4600 | I21: Витамины | K21: =A21&". "&C21&CHAR(10)&"Тел.: "&D21&CHAR(10)&"Адрес: "&E21&" ("&I21&")"&CHAR(10)&"https://yandex.ru/maps/?text="&REPLACE(F21,SEARCH(",",F21),2,"%2C")&CHAR(10)&"https://maps.google.com/?daddr="&REPLACE(F21,SEARCH(",",F21),2,"%2C")&CHAR(10)&"К оплате: "&H21&CHAR(10)&"----------------------------------------------------------" -> #N/A
A22: 1 | B22: 45409 | C22: Максим рюкзак | D22: =VLOOKUP($C22,ТабКлиенты[[#All],[name]:[phone]],MATCH(D$1,ТабКлиенты[#Headers],0)-1,0) -> #N/A | E22: =VLOOKUP($C22,ТабАдрес[[#All],[Клиент]:[gps]],MATCH(E$1,ТабКлиенты[#Headers],0)-4,0) -> #N/A | F22: =VLOOKUP($C22,ТабАдрес[[#All],[Клиент]:[gps]],MATCH(F$1,ТабКлиенты[#Headers],0)-4,0) -> #N/A | H22: 1528 | I22: 71 | K22: =A22&". "&C22&CHAR(10)&"Тел.: "&D22&CHAR(10)&"Адрес: "&E22&" ("&I22&")"&CHAR(10)&"https://yandex.ru/maps/?text="&REPLACE(F22,SEARCH(",",F22),2,"%2C")&CHAR(10)&"https://maps.google.com/?daddr="&REPLACE(F22,SEARCH(",",F22),2,"%2C")&CHAR(10)&"К оплате: "&H22&CHAR(10)&"----------------------------------------------------------" -> #N/A
A23: 2 | B23: 45409 | C23: Макс Куприна | D23: =VLOOKUP($C23,ТабКлиенты[[#All],[name]:[phone]],MATCH(D$1,ТабКлиенты[#Headers],0)-1,0) -> #N/A | E23: =VLOOKUP($C23,ТабАдрес[[#All],[Клиент]:[gps]],MATCH(E$1,ТабКлиенты[#Headers],0)-4,0) -> #N/A | F23: =VLOOKUP($C23,ТабАдрес[[#All],[Клиент]:[gps]],MATCH(F$1,ТабКлиенты[#Headers],0)-4,0) -> #N/A | H23: 0 | I23: 67 | K23: =A23&". "&C23&CHAR(10)&"Тел.: "&D23&CHAR(10)&"Адрес: "&E23&" ("&I23&")"&CHAR(10)&"https://yandex.ru/maps/?text="&REPLACE(F23,SEARCH(",",F23),2,"%2C")&CHAR(10)&"https://maps.google.com/?daddr="&REPLACE(F23,SEARCH(",",F23),2,"%2C")&CHAR(10)&"К оплате: "&H23&CHAR(10)&"----------------------------------------------------------" -> #N/A
A24: 3 | B24: 45409 | C24: Константин Маркет | D24: =VLOOKUP($C24,ТабКлиенты[[#All],[name]:[phone]],MATCH(D$1,ТабКлиенты[#Headers],0)-1,0) -> #N/A | E24: =VLOOKUP($C24,ТабАдрес[[#All],[Клиент]:[gps]],MATCH(E$1,ТабКлиенты[#Headers],0)-4,0) -> #N/A | F24: =VLOOKUP($C24,ТабАдрес[[#All],[Клиент]:[gps]],MATCH(F$1,ТабКлиенты[#Headers],0)-4,0) -> #N/A | H24: 0 | I24: 60 | K24: =A24&". "&C24&CHAR(10)&"Тел.: "&D24&CHAR(10)&"Адрес: "&E24&" ("&I24&")"&CHAR(10)&"https://yandex.ru/maps/?text="&REPLACE(F24,SEARCH(",",F24),2,"%2C")&CHAR(10)&"https://maps.google.com/?daddr="&REPLACE(F24,SEARCH(",",F24),2,"%2C")&CHAR(10)&"К оплате: "&H24&CHAR(10)&"----------------------------------------------------------" -> #N/A
A25: 4 | B25: 45409 | C25: Галина Шевченко 248 | D25: =VLOOKUP($C25,ТабКлиенты[[#All],[name]:[phone]],MATCH(D$1,ТабКлиенты[#Headers],0)-1,0) -> #N/A | E25: =VLOOKUP($C25,ТабАдрес[[#All],[Клиент]:[gps]],MATCH(E$1,ТабКлиенты[#Headers],0)-4,0) -> #N/A | F25: =VLOOKUP($C25,ТабАдрес[[#All],[Клиент]:[gps]],MATCH(F$1,ТабКлиенты[#Headers],0)-4,0) -> #N/A | H25: 0 | I25: 64, 75 | K25: =A25&". "&C25&CHAR(10)&"Тел.: "&D25&CHAR(10)&"Адрес: "&E25&" ("&I25&")"&CHAR(10)&"https://yandex.ru/maps/?text="&REPLACE(F25,SEARCH(",",F25),2,"%2C")&CHAR(10)&"https://maps.google.com/?daddr="&REPLACE(F25,SEARCH(",",F25),2,"%2C")&CHAR(10)&"К оплате: "&H25&CHAR(10)&"----------------------------------------------------------" -> #N/A
A26: 5 | B26: 45409 | C26: Галина Агабекова(церковь) | D26: =VLOOKUP($C26,ТабКлиенты[[#All],[name]:[phone]],MATCH(D$1,ТабКлиенты[#Headers],0)-1,0) -> #N/A | E26: =VLOOKUP($C26,ТабАдрес[[#All],[Клиент]:[gps]],MATCH(E$1,ТабКлиенты[#Headers],0)-4,0) -> #N/A | F26: =VLOOKUP($C26,ТабАдрес[[#All],[Клиент]:[gps]],MATCH(F$1,ТабКлиенты[#Headers],0)-4,0) -> #N/A | H26: 0 | I26: 66 | K26: =A26&". "&C26&CHAR(10)&"Тел.: "&D26&CHAR(10)&"Адрес: "&E26&" ("&I26&")"&CHAR(10)&"https://yandex.ru/maps/?text="&REPLACE(F26,SEARCH(",",F26),2,"%2C")&CHAR(10)&"https://maps.google.com/?daddr="&REPLACE(F26,SEARCH(",",F26),2,"%2C")&CHAR(10)&"К оплате: "&H26&CHAR(10)&"----------------------------------------------------------" -> #N/A
A27: 6 | B27: 45409 | C27: Лариса Кирова | D27: =VLOOKUP($C27,ТабКлиенты[[#All],[name]:[phone]],MATCH(D$1,ТабКлиенты[#Headers],0)-1,0) -> #N/A | E27: =VLOOKUP($C27,ТабАдрес[[#All],[Клиент]:[gps]],MATCH(E$1,ТабКлиенты[#Headers],0)-4,0) -> #N/A | F27: =VLOOKUP($C27,ТабАдрес[[#All],[Клиент]:[gps]],MATCH(F$1,ТабКлиенты[#Headers],0)-4,0) -> #N/A | H27: =2556+472 -> 3028 | I27: 59, 69 | K27: =A27&". "&C27&CHAR(10)&"Тел.: "&D27&CHAR(10)&"Адрес: "&E27&" ("&I27&")"&CHAR(10)&"https://yandex.ru/maps/?text="&REPLACE(F27,SEARCH(",",F27),2,"%2C")&CHAR(10)&"https://maps.google.com/?daddr="&REPLACE(F27,SEARCH(",",F27),2,"%2C")&CHAR(10)&"К оплате: "&H27&CHAR(10)&"----------------------------------------------------------" -> #N/A
A28: 7 | B28: 45409 | C28: Наталья 12 | D28: =VLOOKUP($C28,ТабКлиенты[[#All],[name]:[phone]],MATCH(D$1,ТабКлиенты[#Headers],0)-1,0) -> #N/A | E28: =VLOOKUP($C28,ТабАдрес[[#All],[Клиент]:[gps]],MATCH(E$1,ТабКлиенты[#Headers],0)-4,0) -> #N/A | F28: =VLOOKUP($C28,ТабАдрес[[#All],[Клиент]:[gps]],MATCH(F$1,ТабКлиенты[#Headers],0)-4,0) -> #N/A | H28: 0 | I28: 72 | K28: =A28&". "&C28&CHAR(10)&"Тел.: "&D28&CHAR(10)&"Адрес: "&E28&" ("&I28&")"&CHAR(10)&"https://yandex.ru/maps/?text="&REPLACE(F28,SEARCH(",",F28),2,"%2C")&CHAR(10)&"https://maps.google.com/?daddr="&REPLACE(F28,SEARCH(",",F28),2,"%2C")&CHAR(10)&"К оплате: "&H28&CHAR(10)&"----------------------------------------------------------" -> #N/A
A29: 8 | B29: 45409 | C29: Лена Ларисына | D29: =VLOOKUP($C29,ТабКлиенты[[#All],[name]:[phone]],MATCH(D$1,ТабКлиенты[#Headers],0)-1,0) -> #N/A | E29: =VLOOKUP($C29,ТабАдрес[[#All],[Клиент]:[gps]],MATCH(E$1,ТабКлиенты[#Headers],0)-4,0) -> #N/A | F29: =VLOOKUP($C29,ТабАдрес[[#All],[Клиент]:[gps]],MATCH(F$1,ТабКлиенты[#Headers],0)-4,0) -> #N/A | H29: 0 | I29: 69 | K29: =A29&". "&C29&CHAR(10)&"Тел.: "&D29&CHAR(10)&"Адрес: "&E29&" ("&I29&")"&CHAR(10)&"https://yandex.ru/maps/?text="&REPLACE(F29,SEARCH(",",F29),2,"%2C")&CHAR(10)&"https://maps.google.com/?daddr="&REPLACE(F29,SEARCH(",",F29),2,"%2C")&CHAR(10)&"К оплате: "&H29&CHAR(10)&"----------------------------------------------------------" -> #N/A
A30: 9 | B30: 45409 | C30: Татьяна Торговая 100 | D30: =VLOOKUP($C30,ТабКлиенты[[#All],[name]:[phone]],MATCH(D$1,ТабКлиенты[#Headers],0)-1,0) -> +79497267699 | E30: =VLOOKUP($C30,ТабАдрес[[#All],[Клиент]:[gps]],MATCH(E$1,ТабКлиенты[#Headers],0)-4,0) -> Торговая 100 | F30: =VLOOKUP($C30,ТабАдрес[[#All],[Клиент]:[gps]],MATCH(F$1,ТабКлиенты[#Headers],0)-4,0) -> 47.1034, 37.5633 | H30: 2200 | I30: Витамины | K30: =A30&". "&C30&CHAR(10)&"Тел.: "&D30&CHAR(10)&"Адрес: "&E30&" ("&I30&")"&CHAR(10)&"https://yandex.ru/maps/?text="&REPLACE(F30,SEARCH(",",F30),2,"%2C")&CHAR(10)&"https://maps.google.com/?daddr="&REPLACE(F30,SEARCH(",",F30),2,"%2C")&CHAR(10)&"К оплате: "&H30&CHAR(10)&"----------------------------------------------------------" -> 9. Татьяна Торговая 100 Тел.: +79497267699 Адрес: Торговая 100 (Витамины) https://yandex.ru/maps/?text=47.1034%2C37.5633 https://maps.google.com/?daddr=47.1034%2C37.5633 К оплате: 2200 ----------------------------------------------------------
A31: 10 | B31: 45409 | C31: Митрофанов Евгений | D31: =VLOOKUP($C31,ТабКлиенты[[#All],[name]:[phone]],MATCH(D$1,ТабКлиенты[#Headers],0)-1,0) -> #N/A | E31: =VLOOKUP($C31,ТабАдрес[[#All],[Клиент]:[gps]],MATCH(E$1,ТабКлиенты[#Headers],0)-4,0) -> #N/A | F31: =VLOOKUP($C31,ТабАдрес[[#All],[Клиент]:[gps]],MATCH(F$1,ТабКлиенты[#Headers],0)-4,0) -> #N/A | H31: 0 | I31: 65 | K31: =A31&". "&C31&CHAR(10)&"Тел.: "&D31&CHAR(10)&"Адрес: "&E31&" ("&I31&")"&CHAR(10)&"https://yandex.ru/maps/?text="&REPLACE(F31,SEARCH(",",F31),2,"%2C")&CHAR(10)&"https://maps.google.com/?daddr="&REPLACE(F31,SEARCH(",",F31),2,"%2C")&CHAR(10)&"К оплате: "&H31&CHAR(10)&"----------------------------------------------------------" -> #N/A
A32: 11 | B32: 45409 | C32: Карина Кравченко 17 | D32: =VLOOKUP($C32,ТабКлиенты[[#All],[name]:[phone]],MATCH(D$1,ТабКлиенты[#Headers],0)-1,0) -> #N/A | E32: =VLOOKUP($C32,ТабАдрес[[#All],[Клиент]:[gps]],MATCH(E$1,ТабКлиенты[#Headers],0)-4,0) -> #N/A | F32: =VLOOKUP($C32,ТабАдрес[[#All],[Клиент]:[gps]],MATCH(F$1,ТабКлиенты[#Headers],0)-4,0) -> #N/A | H32: 200 | I32: 61 | K32: =A32&". "&C32&CHAR(10)&"Тел.: "&D32&CHAR(10)&"Адрес: "&E32&" ("&I32&")"&CHAR(10)&"https://yandex.ru/maps/?text="&REPLACE(F32,SEARCH(",",F32),2,"%2C")&CHAR(10)&"https://maps.google.com/?daddr="&REPLACE(F32,SEARCH(",",F32),2,"%2C")&CHAR(10)&"К оплате: "&H32&CHAR(10)&"----------------------------------------------------------" -> #N/A
A33: 1 | B33: 45416 | C33: григорий(танковый ) | D33: =VLOOKUP($C33,ТабКлиенты[[#All],[name]:[phone]],MATCH(D$1,ТабКлиенты[#Headers],0)-1,0) -> #N/A | E33: =VLOOKUP($C33,ТабАдрес[[#All],[Клиент]:[gps]],MATCH(E$1,ТабКлиенты[#Headers],0)-4,0) -> #N/A | F33: =VLOOKUP($C33,ТабАдрес[[#All],[Клиент]:[gps]],MATCH(F$1,ТабКлиенты[#Headers],0)-4,0) -> #N/A | H33: 0 | I33: 79 | K33: =A33&". "&C33&CHAR(10)&"Тел.: "&D33&CHAR(10)&"Адрес: "&E33&" ("&I33&")"&CHAR(10)&"https://yandex.ru/maps/?text="&REPLACE(F33,SEARCH(",",F33),2,"%2C")&CHAR(10)&"https://maps.google.com/?daddr="&REPLACE(F33,SEARCH(",",F33),2,"%2C")&CHAR(10)&"К оплате: "&H33&CHAR(10)&"----------------------------------------------------------" -> #N/A
A34: 2 | B34: 45416 | C34: Наталья 12 | D34: =VLOOKUP($C34,ТабКлиенты[[#All],[name]:[phone]],MATCH(D$1,ТабКлиенты[#Headers],0)-1,0) -> #N/A | E34: =VLOOKUP($C34,ТабАдрес[[#All],[Клиент]:[gps]],MATCH(E$1,ТабКлиенты[#Headers],0)-4,0) -> #N/A | F34: =VLOOKUP($C34,ТабАдрес[[#All],[Клиент]:[gps]],MATCH(F$1,ТабКлиенты[#Headers],0)-4,0) -> #N/A | H34: 0 | I34: 72 | K34: =A34&". "&C34&CHAR(10)&"Тел.: "&D34&CHAR(10)&"Адрес: "&E34&" ("&I34&")"&CHAR(10)&"https://yandex.ru/maps/?text="&REPLACE(F34,SEARCH(",",F34),2,"%2C")&CHAR(10)&"https://maps.google.com/?daddr="&REPLACE(F34,SEARCH(",",F34),2,"%2C")&CHAR(10)&"К оплате: "&H34&CHAR(10)&"----------------------------------------------------------" -> #N/A
A35: 3 | B35: 45416 | C35: Максим рюкзак | D35: =VLOOKUP($C35,ТабКлиенты[[#All],[name]:[phone]],MATCH(D$1,ТабКлиенты[#Headers],0)-1,0) -> #N/A | E35: =VLOOKUP($C35,ТабАдрес[[#All],[Клиент]:[gps]],MATCH(E$1,ТабКлиенты[#Headers],0)-4,0) -> #N/A | F35: =VLOOKUP($C35,ТабАдрес[[#All],[Клиент]:[gps]],MATCH(F$1,ТабКлиенты[#Headers],0)-4,0) -> #N/A | H35: 0 | I35: 71 | K35: =A35&". "&C35&CHAR(10)&"Тел.: "&D35&CHAR(10)&"Адрес: "&E35&" ("&I35&")"&CHAR(10)&"https://yandex.ru/maps/?text="&REPLACE(F35,SEARCH(",",F35),2,"%2C")&CHAR(10)&"https://maps.google.com/?daddr="&REPLACE(F35,SEARCH(",",F35),2,"%2C")&CHAR(10)&"К оплате: "&H35&CHAR(10)&"----------------------------------------------------------" -> #N/A
A36: 4 | B36: 45416 | C36: Галина Шевченко 248 | D36: =VLOOKUP($C36,ТабКлиенты[[#All],[name]:[phone]],MATCH(D$1,ТабКлиенты[#Headers],0)-1,0) -> #N/A | E36: =VLOOKUP($C36,ТабАдрес[[#All],[Клиент]:[gps]],MATCH(E$1,ТабКлиенты[#Headers],0)-4,0) -> #N/A | F36: =VLOOKUP($C36,ТабАдрес[[#All],[Клиент]:[gps]],MATCH(F$1,ТабКлиенты[#Headers],0)-4,0) -> #N/A | H36: 0 | I36: 75 | K36: =A36&". "&C36&CHAR(10)&"Тел.: "&D36&CHAR(10)&"Адрес: "&E36&" ("&I36&")"&CHAR(10)&"https://yandex.ru/maps/?text="&REPLACE(F36,SEARCH(",",F36),2,"%2C")&CHAR(10)&"https://maps.google.com/?daddr="&REPLACE(F36,SEARCH(",",F36),2,"%2C")&CHAR(10)&"К оплате: "&H36&CHAR(10)&"----------------------------------------------------------" -> #N/A
A37: 5 | B37: 45416 | C37: Лариса Кирова | D37: =VLOOKUP($C37,ТабКлиенты[[#All],[name]:[phone]],MATCH(D$1,ТабКлиенты[#Headers],0)-1,0) -> #N/A | E37: =VLOOKUP($C37,ТабАдрес[[#All],[Клиент]:[gps]],MATCH(E$1,ТабКлиенты[#Headers],0)-4,0) -> #N/A | F37: =VLOOKUP($C37,ТабАдрес[[#All],[Клиент]:[gps]],MATCH(F$1,ТабКлиенты[#Headers],0)-4,0) -> #N/A | H37: 0 | I37: 76 | K37: =A37&". "&C37&CHAR(10)&"Тел.: "&D37&CHAR(10)&"Адрес: "&E37&" ("&I37&")"&CHAR(10)&"https://yandex.ru/maps/?text="&REPLACE(F37,SEARCH(",",F37),2,"%2C")&CHAR(10)&"https://maps.google.com/?daddr="&REPLACE(F37,SEARCH(",",F37),2,"%2C")&CHAR(10)&"К оплате: "&H37&CHAR(10)&"----------------------------------------------------------" -> #N/A
A38: 6 | B38: 45416 | C38: Елена Ларисына | D38: =VLOOKUP($C38,ТабКлиенты[[#All],[name]:[phone]],MATCH(D$1,ТабКлиенты[#Headers],0)-1,0) -> #N/A | E38: =VLOOKUP($C38,ТабАдрес[[#All],[Клиент]:[gps]],MATCH(E$1,ТабКлиенты[#Headers],0)-4,0) -> #N/A | F38: =VLOOKUP($C38,ТабАдрес[[#All],[Клиент]:[gps]],MATCH(F$1,ТабКлиенты[#Headers],0)-4,0) -> #N/A | H38: 1187 | I38: 78 | K38: =A38&". "&C38&CHAR(10)&"Тел.: "&D38&CHAR(10)&"Адрес: "&E38&" ("&I38&")"&CHAR(10)&"https://yandex.ru/maps/?text="&REPLACE(F38,SEARCH(",",F38),2,"%2C")&CHAR(10)&"https://maps.google.com/?daddr="&REPLACE(F38,SEARCH(",",F38),2,"%2C")&CHAR(10)&"К оплате: "&H38&CHAR(10)&"----------------------------------------------------------" -> #N/A
A39: 7 | B39: 45416 | C39: Митрофанов Евгений | D39: =VLOOKUP($C39,ТабКлиенты[[#All],[name]:[phone]],MATCH(D$1,ТабКлиенты[#Headers],0)-1,0) -> #N/A | E39: =VLOOKUP($C39,ТабАдрес[[#All],[Клиент]:[gps]],MATCH(E$1,ТабКлиенты[#Headers],0)-4,0) -> #N/A | F39: =VLOOKUP($C39,ТабАдрес[[#All],[Клиент]:[gps]],MATCH(F$1,ТабКлиенты[#Headers],0)-4,0) -> #N/A | H39: 0 | I39: 80 | K39: =A39&". "&C39&CHAR(10)&"Тел.: "&D39&CHAR(10)&"Адрес: "&E39&" ("&I39&")"&CHAR(10)&"https://yandex.ru/maps/?text="&REPLACE(F39,SEARCH(",",F39),2,"%2C")&CHAR(10)&"https://maps.google.com/?daddr="&REPLACE(F39,SEARCH(",",F39),2,"%2C")&CHAR(10)&"К оплате: "&H39&CHAR(10)&"----------------------------------------------------------" -> #N/A
A40: 8 | B40: 45416 | C40: Полинка | D40: =VLOOKUP($C40,ТабКлиенты[[#All],[name]:[phone]],MATCH(D$1,ТабКлиенты[#Headers],0)-1,0) -> #N/A | E40: =VLOOKUP($C40,ТабАдрес[[#All],[Клиент]:[gps]],MATCH(E$1,ТабКлиенты[#Headers],0)-4,0) -> #N/A | F40: =VLOOKUP($C40,ТабАдрес[[#All],[Клиент]:[gps]],MATCH(F$1,ТабКлиенты[#Headers],0)-4,0) -> #N/A | H40: -265 | I40: 1, 68 | K40: =A40&". "&C40&CHAR(10)&"Тел.: "&D40&CHAR(10)&"Адрес: "&E40&" ("&I40&")"&CHAR(10)&"https://yandex.ru/maps/?text="&REPLACE(F40,SEARCH(",",F40),2,"%2C")&CHAR(10)&"https://maps.google.com/?daddr="&REPLACE(F40,SEARCH(",",F40),2,"%2C")&CHAR(10)&"К оплате: "&H40&CHAR(10)&"----------------------------------------------------------" -> #N/A
A41: 9 | B41: 45416 | C41: Александр Каскад | D41: =VLOOKUP($C41,ТабКлиенты[[#All],[name]:[phone]],MATCH(D$1,ТабКлиенты[#Headers],0)-1,0) -> #N/A | E41: =VLOOKUP($C41,ТабАдрес[[#All],[Клиент]:[gps]],MATCH(E$1,ТабКлиенты[#Headers],0)-4,0) -> #N/A | F41: =VLOOKUP($C41,ТабАдрес[[#All],[Клиент]:[gps]],MATCH(F$1,ТабКлиенты[#Headers],0)-4,0) -> #N/A | H41: 0 | I41: 77 | K41: =A41&". "&C41&CHAR(10)&"Тел.: "&D41&CHAR(10)&"Адрес: "&E41&" ("&I41&")"&CHAR(10)&"https://yandex.ru/maps/?text="&REPLACE(F41,SEARCH(",",F41),2,"%2C")&CHAR(10)&"https://maps.google.com/?daddr="&REPLACE(F41,SEARCH(",",F41),2,"%2C")&CHAR(10)&"К оплате: "&H41&CHAR(10)&"----------------------------------------------------------" -> #N/A
A42: 1 | B42: 45423 | C42: григорий(танковый ) | D42: =VLOOKUP($C42,ТабКлиенты[[#All],[name]:[phone]],MATCH(D$1,ТабКлиенты[#Headers],0)-1,0) -> #N/A | E42: =VLOOKUP($C42,ТабАдрес[[#All],[Клиент]:[gps]],MATCH(E$1,ТабКлиенты[#Headers],0)-4,0) -> #N/A | F42: =VLOOKUP($C42,ТабАдрес[[#All],[Клиент]:[gps]],MATCH(F$1,ТабКлиенты[#Headers],0)-4,0) -> #N/A | H42: 0 | I42: 79, 86 | K42: =A42&". "&C42&CHAR(10)&"Тел.: "&D42&CHAR(10)&"Адрес: "&E42&CHAR(10)&"№ заказа: "&I42&CHAR(10)&"https://yandex.ru/maps/?text="&REPLACE(F42,SEARCH(",",F42),2,"%2C")&CHAR(10)&"https://maps.google.com/?daddr="&REPLACE(F42,SEARCH(",",F42),2,"%2C")&CHAR(10)&"К оплате: "&"**"&H42&CHAR(10)&"**"&"----------------------------------------------------------" -> #N/A
A43: 2 | B43: 45423 | C43: Людмила Эдельвейс | D43: =VLOOKUP($C43,ТабКлиенты[[#All],[name]:[phone]],MATCH(D$1,ТабКлиенты[#Headers],0)-1,0) -> +79496019237 | E43: =VLOOKUP($C43,ТабАдрес[[#All],[Клиент]:[gps]],MATCH(E$1,ТабКлиенты[#Headers],0)-4,0) -> Металлургов 92 | F43: =VLOOKUP($C43,ТабАдрес[[#All],[Клиент]:[gps]],MATCH(F$1,ТабКлиенты[#Headers],0)-4,0) -> 47.1053, 37.5483 | H43: 0 | I43: 87 | K43: =A43&". "&C43&CHAR(10)&"Тел.: "&D43&CHAR(10)&"Адрес: "&E43&CHAR(10)&"№ заказа: "&I43&CHAR(10)&"https://yandex.ru/maps/?text="&REPLACE(F43,SEARCH(",",F43),2,"%2C")&CHAR(10)&"https://maps.google.com/?daddr="&REPLACE(F43,SEARCH(",",F43),2,"%2C")&CHAR(10)&"К оплате: "&"**"&H43&CHAR(10)&"**"&"----------------------------------------------------------" -> 2. Людмила Эдельвейс Тел.: +79496019237 Адрес: Металлургов 92 № заказа: 87 https://yandex.ru/maps/?text=47.1053%2C37.5483 https://maps.google.com/?daddr=47.1053%2C37.5483 К оплате: **0 **----------------------------------------------------------
A44: 3 | B44: 45423 | C44: Лариса Кирова | D44: =VLOOKUP($C44,ТабКлиенты[[#All],[name]:[phone]],MATCH(D$1,ТабКлиенты[#Headers],0)-1,0) -> #N/A | E44: =VLOOKUP($C44,ТабАдрес[[#All],[Клиент]:[gps]],MATCH(E$1,ТабКлиенты[#Headers],0)-4,0) -> #N/A | F44: =VLOOKUP($C44,ТабАдрес[[#All],[Клиент]:[gps]],MATCH(F$1,ТабКлиенты[#Headers],0)-4,0) -> #N/A | H44: =734+4578 -> 5312 | I44: 82, 88, 78 | K44: =A44&". "&C44&CHAR(10)&"Тел.: "&D44&CHAR(10)&"Адрес: "&E44&CHAR(10)&"№ заказа: "&I44&CHAR(10)&"https://yandex.ru/maps/?text="&REPLACE(F44,SEARCH(",",F44),2,"%2C")&CHAR(10)&"https://maps.google.com/?daddr="&REPLACE(F44,SEARCH(",",F44),2,"%2C")&CHAR(10)&"К оплате: "&"**"&H44&CHAR(10)&"**"&"----------------------------------------------------------" -> #N/A
A45: 4 | B45: 45423 | C45: Александр Радин | D45: =VLOOKUP($C45,ТабКлиенты[[#All],[name]:[phone]],MATCH(D$1,ТабКлиенты[#Headers],0)-1,0) -> +79497277100 | E45: =VLOOKUP($C45,ТабАдрес[[#All],[Клиент]:[gps]],MATCH(E$1,ТабКлиенты[#Headers],0)-4,0) -> Артема 132 | F45: =VLOOKUP($C45,ТабАдрес[[#All],[Клиент]:[gps]],MATCH(F$1,ТабКлиенты[#Headers],0)-4,0) -> 47.1085, 37.5599 | H45: 28599 | I45: Витамины | K45: =A45&". "&C45&CHAR(10)&"Тел.: "&D45&CHAR(10)&"Адрес: "&E45&CHAR(10)&"№ заказа: "&I45&CHAR(10)&"https://yandex.ru/maps/?text="&REPLACE(F45,SEARCH(",",F45),2,"%2C")&CHAR(10)&"https://maps.google.com/?daddr="&REPLACE(F45,SEARCH(",",F45),2,"%2C")&CHAR(10)&"К оплате: "&"**"&H45&CHAR(10)&"**"&"----------------------------------------------------------" -> 4. Александр Радин Тел.: +79497277100 Адрес: Артема 132 № заказа: Витамины https://yandex.ru/maps/?text=47.1085%2C37.5599 https://maps.google.com/?daddr=47.1085%2C37.5599 К оплате: **28599 **----------------------------------------------------------
A46: 5 | B46: 45423 | C46: ПерксХеарт | D46: =VLOOKUP($C46,ТабКлиенты[[#All],[name]:[phone]],MATCH(D$1,ТабКлиенты[#Headers],0)-1,0) -> #N/A | E46: =VLOOKUP($C46,ТабАдрес[[#All],[Клиент]:[gps]],MATCH(E$1,ТабКлиенты[#Headers],0)-4,0) -> #N/A | F46: =VLOOKUP($C46,ТабАдрес[[#All],[Клиент]:[gps]],MATCH(F$1,ТабКлиенты[#Headers],0)-4,0) -> #N/A | H46: 3000 | I46: Витамины | K46: =A46&". "&C46&CHAR(10)&"Тел.: "&D46&CHAR(10)&"Адрес: "&E46&CHAR(10)&"№ заказа: "&I46&CHAR(10)&"https://yandex.ru/maps/?text="&REPLACE(F46,SEARCH(",",F46),2,"%2C")&CHAR(10)&"https://maps.google.com/?daddr="&REPLACE(F46,SEARCH(",",F46),2,"%2C")&CHAR(10)&"К оплате: "&"**"&H46&CHAR(10)&"**"&"----------------------------------------------------------" -> #N/A
A47: 6 | B47: 45423 | C47: Наталья Азовстальская | D47: =VLOOKUP($C47,ТабКлиенты[[#All],[name]:[phone]],MATCH(D$1,ТабКлиенты[#Headers],0)-1,0) -> +79497246366 | E47: =VLOOKUP($C47,ТабАдрес[[#All],[Клиент]:[gps]],MATCH(E$1,ТабКлиенты[#Headers],0)-4,0) -> Азовстальская 91 подъезд 1 | F47: =VLOOKUP($C47,ТабАдрес[[#All],[Клиент]:[gps]],MATCH(F$1,ТабКлиенты[#Headers],0)-4,0) -> 47.1008, 37.6529 | H47: 8200 | I47: Витамины | K47: =A47&". "&C47&CHAR(10)&"Тел.: "&D47&CHAR(10)&"Адрес: "&E47&CHAR(10)&"№ заказа: "&I47&CHAR(10)&"https://yandex.ru/maps/?text="&REPLACE(F47,SEARCH(",",F47),2,"%2C")&CHAR(10)&"https://maps.google.com/?daddr="&REPLACE(F47,SEARCH(",",F47),2,"%2C")&CHAR(10)&"К оплате: "&"**"&H47&CHAR(10)&"**"&"----------------------------------------------------------" -> 6. Наталья Азовстальская Тел.: +79497246366 Адрес: Азовстальская 91 подъезд 1 № заказа: Витамины https://yandex.ru/maps/?text=47.1008%2C37.6529 https://maps.google.com/?daddr=47.1008%2C37.6529 К оплате: **8200 **----------------------------------------------------------
A48: 1 | B48: 45430 | C48: григорий(танковый ) | D48: =VLOOKUP($C48,ТабКлиенты[[#All],[name]:[phone]],MATCH(D$1,ТабКлиенты[#Headers],0)-1,0) -> #N/A | E48: =VLOOKUP($C48,ТабАдрес[[#All],[Клиент]:[gps]],MATCH(E$1,ТабКлиенты[#Headers],0)-4,0) -> #N/A | F48: =VLOOKUP($C48,ТабАдрес[[#All],[Клиент]:[gps]],MATCH(F$1,ТабКлиенты[#Headers],0)-4,0) -> #N/A | H48: -2854 | I48: 86.98 | K48: =A48&". "&C48&CHAR(10)&"Тел.: "&D48&CHAR(10)&"Адрес: "&E48&CHAR(10)&"№ заказа: "&I48&CHAR(10)&"https://yandex.ru/maps/?text="&REPLACE(F48,SEARCH(",",F48),2,"%2C")&CHAR(10)&"https://maps.google.com/?daddr="&REPLACE(F48,SEARCH(",",F48),2,"%2C")&CHAR(10)&"К оплате: "&"**"&H48&CHAR(10)&"**"&"----------------------------------------------------------" -> #N/A
A49: 2 | B49: 45430 | C49: Олег Гагарина 6 | D49: =VLOOKUP($C49,ТабКлиенты[[#All],[name]:[phone]],MATCH(D$1,ТабКлиенты[#Headers],0)-1,0) -> #N/A | E49: =VLOOKUP($C49,ТабАдрес[[#All],[Клиент]:[gps]],MATCH(E$1,ТабКлиенты[#Headers],0)-4,0) -> #N/A | F49: =VLOOKUP($C49,ТабАдрес[[#All],[Клиент]:[gps]],MATCH(F$1,ТабКлиенты[#Headers],0)-4,0) -> #N/A | H49: 200 | I49: 107 | K49: =A49&". "&C49&CHAR(10)&"Тел.: "&D49&CHAR(10)&"Адрес: "&E49&CHAR(10)&"№ заказа: "&I49&CHAR(10)&"https://yandex.ru/maps/?text="&REPLACE(F49,SEARCH(",",F49),2,"%2C")&CHAR(10)&"https://maps.google.com/?daddr="&REPLACE(F49,SEARCH(",",F49),2,"%2C")&CHAR(10)&"К оплате: "&"**"&H49&CHAR(10)&"**"&"----------------------------------------------------------" -> #N/A
A50: 3 | B50: 45430 | C50: Наталья Зелинского | D50: =VLOOKUP($C50,ТабКлиенты[[#All],[name]:[phone]],MATCH(D$1,ТабКлиенты[#Headers],0)-1,0) -> +79497428404 | E50: =VLOOKUP($C50,ТабАдрес[[#All],[Клиент]:[gps]],MATCH(E$1,ТабКлиенты[#Headers],0)-4,0) -> Зелинского 94 | F50: =VLOOKUP($C50,ТабАдрес[[#All],[Клиент]:[gps]],MATCH(F$1,ТабКлиенты[#Headers],0)-4,0) -> 47.1008, 37.5167 | H50: 9000 | I50: Витамины | K50: =A50&". "&C50&CHAR(10)&"Тел.: "&D50&CHAR(10)&"Адрес: "&E50&CHAR(10)&"№ заказа: "&I50&CHAR(10)&"https://yandex.ru/maps/?text="&REPLACE(F50,SEARCH(",",F50),2,"%2C")&CHAR(10)&"https://maps.google.com/?daddr="&REPLACE(F50,SEARCH(",",F50),2,"%2C")&CHAR(10)&"К оплате: "&"**"&H50&CHAR(10)&"**"&"----------------------------------------------------------" -> 3. Наталья Зелинского Тел.: +79497428404 Адрес: Зелинского 94 № заказа: Витамины https://yandex.ru/maps/?text=47.1008%2C37.5167 https://maps.google.com/?daddr=47.1008%2C37.5167 К оплате: **9000 **----------------------------------------------------------
A51: 4 | B51: 45430 | C51: Наталья Урицкого | D51: =VLOOKUP($C51,ТабКлиенты[[#All],[name]:[phone]],MATCH(D$1,ТабКлиенты[#Headers],0)-1,0) -> #N/A | E51: =VLOOKUP($C51,ТабАдрес[[#All],[Клиент]:[gps]],MATCH(E$1,ТабКлиенты[#Headers],0)-4,0) -> #N/A | F51: =VLOOKUP($C51,ТабАдрес[[#All],[Клиент]:[gps]],MATCH(F$1,ТабКлиенты[#Headers],0)-4,0) -> #N/A | H51: 33400 | I51: Витамины | K51: =A51&". "&C51&CHAR(10)&"Тел.: "&D51&CHAR(10)&"Адрес: "&E51&CHAR(10)&"№ заказа: "&I51&CHAR(10)&"https://yandex.ru/maps/?text="&REPLACE(F51,SEARCH(",",F51),2,"%2C")&CHAR(10)&"https://maps.google.com/?daddr="&REPLACE(F51,SEARCH(",",F51),2,"%2C")&CHAR(10)&"К оплате: "&"**"&H51&CHAR(10)&"**"&"----------------------------------------------------------" -> #N/A
A52: 5 | B52: 45430 | C52: Максим телевизор | D52: =VLOOKUP($C52,ТабКлиенты[[#All],[name]:[phone]],MATCH(D$1,ТабКлиенты[#Headers],0)-1,0) -> #N/A | E52: =VLOOKUP($C52,ТабАдрес[[#All],[Клиент]:[gps]],MATCH(E$1,ТабКлиенты[#Headers],0)-4,0) -> #N/A | F52: =VLOOKUP($C52,ТабАдрес[[#All],[Клиент]:[gps]],MATCH(F$1,ТабКлиенты[#Headers],0)-4,0) -> #N/A | H52: 0 | I52: 89 | K52: =A52&". "&C52&CHAR(10)&"Тел.: "&D52&CHAR(10)&"Адрес: "&E52&CHAR(10)&"№ заказа: "&I52&CHAR(10)&"https://yandex.ru/maps/?text="&REPLACE(F52,SEARCH(",",F52),2,"%2C")&CHAR(10)&"https://maps.google.com/?daddr="&REPLACE(F52,SEARCH(",",F52),2,"%2C")&CHAR(10)&"К оплате: "&"**"&H52&CHAR(10)&"**"&"----------------------------------------------------------" -> #N/A
A53: 6 | B53: 45430 | C53: Галина Агабекова(церковь) | D53: =VLOOKUP($C53,ТабКлиенты[[#All],[name]:[phone]],MATCH(D$1,ТабКлиенты[#Headers],0)-1,0) -> #N/A | E53: =VLOOKUP($C53,ТабАдрес[[#All],[Клиент]:[gps]],MATCH(E$1,ТабКлиенты[#Headers],0)-4,0) -> #N/A | F53: =VLOOKUP($C53,ТабАдрес[[#All],[Клиент]:[gps]],MATCH(F$1,ТабКлиенты[#Headers],0)-4,0) -> #N/A | H53: 0 | I53: 97.105 | K53: =A53&". "&C53&CHAR(10)&"Тел.: "&D53&CHAR(10)&"Адрес: "&E53&CHAR(10)&"№ заказа: "&I53&CHAR(10)&"https://yandex.ru/maps/?text="&REPLACE(F53,SEARCH(",",F53),2,"%2C")&CHAR(10)&"https://maps.google.com/?daddr="&REPLACE(F53,SEARCH(",",F53),2,"%2C")&CHAR(10)&"К оплате: "&"**"&H53&CHAR(10)&"**"&"----------------------------------------------------------" -> #N/A
A54: 7 | B54: 45430 | C54: Лариса Кирова | D54: =VLOOKUP($C54,ТабКлиенты[[#All],[name]:[phone]],MATCH(D$1,ТабКлиенты[#Headers],0)-1,0) -> #N/A | E54: =VLOOKUP($C54,ТабАдрес[[#All],[Клиент]:[gps]],MATCH(E$1,ТабКлиенты[#Headers],0)-4,0) -> #N/A | F54: =VLOOKUP($C54,ТабАдрес[[#All],[Клиент]:[gps]],MATCH(F$1,ТабКлиенты[#Headers],0)-4,0) -> #N/A | H54: 0 | I54: 82.95 | K54: =A54&". "&C54&CHAR(10)&"Тел.: "&D54&CHAR(10)&"Адрес: "&E54&CHAR(10)&"№ заказа: "&I54&CHAR(10)&"https://yandex.ru/maps/?text="&REPLACE(F54,SEARCH(",",F54),2,"%2C")&CHAR(10)&"https://maps.google.com/?daddr="&REPLACE(F54,SEARCH(",",F54),2,"%2C")&CHAR(10)&"К оплате: "&"**"&H54&CHAR(10)&"**"&"----------------------------------------------------------" -> #N/A
A55: 8 | B55: 45430 | C55: Елена Ларисына | D55: =VLOOKUP($C55,ТабКлиенты[[#All],[name]:[phone]],MATCH(D$1,ТабКлиенты[#Headers],0)-1,0) -> #N/A | E55: =VLOOKUP($C55,ТабАдрес[[#All],[Клиент]:[gps]],MATCH(E$1,ТабКлиенты[#Headers],0)-4,0) -> #N/A | F55: =VLOOKUP($C55,ТабАдрес[[#All],[Клиент]:[gps]],MATCH(F$1,ТабКлиенты[#Headers],0)-4,0) -> #N/A | H55: 0 | I55: 92 | K55: =A55&". "&C55&CHAR(10)&"Тел.: "&D55&CHAR(10)&"Адрес: "&E55&CHAR(10)&"№ заказа: "&I55&CHAR(10)&"https://yandex.ru/maps/?text="&REPLACE(F55,SEARCH(",",F55),2,"%2C")&CHAR(10)&"https://maps.google.com/?daddr="&REPLACE(F55,SEARCH(",",F55),2,"%2C")&CHAR(10)&"К оплате: "&"**"&H55&CHAR(10)&"**"&"----------------------------------------------------------" -> #N/A
A56: 9 | B56: 45430 | C56: Митрофанов Евгений | D56: =VLOOKUP($C56,ТабКлиенты[[#All],[name]:[phone]],MATCH(D$1,ТабКлиенты[#Headers],0)-1,0) -> #N/A | E56: =VLOOKUP($C56,ТабАдрес[[#All],[Клиент]:[gps]],MATCH(E$1,ТабКлиенты[#Headers],0)-4,0) -> #N/A | F56: =VLOOKUP($C56,ТабАдрес[[#All],[Клиент]:[gps]],MATCH(F$1,ТабКлиенты[#Headers],0)-4,0) -> #N/A | H56: 0 | I56: 80.91 | K56: =A56&". "&C56&CHAR(10)&"Тел.: "&D56&CHAR(10)&"Адрес: "&E56&CHAR(10)&"№ заказа: "&I56&CHAR(10)&"https://yandex.ru/maps/?text="&REPLACE(F56,SEARCH(",",F56),2,"%2C")&CHAR(10)&"https://maps.google.com/?daddr="&REPLACE(F56,SEARCH(",",F56),2,"%2C")&CHAR(10)&"К оплате: "&"**"&H56&CHAR(10)&"**"&"----------------------------------------------------------" -> #N/A
A57: 10 | B57: 45430 | C57: Полинка | D57: =VLOOKUP($C57,ТабКлиенты[[#All],[name]:[phone]],MATCH(D$1,ТабКлиенты[#Headers],0)-1,0) -> #N/A | E57: =VLOOKUP($C57,ТабАдрес[[#All],[Клиент]:[gps]],MATCH(E$1,ТабКлиенты[#Headers],0)-4,0) -> #N/A | F57: =VLOOKUP($C57,ТабАдрес[[#All],[Клиент]:[gps]],MATCH(F$1,ТабКлиенты[#Headers],0)-4,0) -> #N/A | H57: 0 | I57: 96.99 | K57: =A57&". "&C57&CHAR(10)&"Тел.: "&D57&CHAR(10)&"Адрес: "&E57&CHAR(10)&"№ заказа: "&I57&CHAR(10)&"https://yandex.ru/maps/?text="&REPLACE(F57,SEARCH(",",F57),2,"%2C")&CHAR(10)&"https://maps.google.com/?daddr="&REPLACE(F57,SEARCH(",",F57),2,"%2C")&CHAR(10)&"К оплате: "&"**"&H57&CHAR(10)&"**"&"----------------------------------------------------------" -> #N/A
A58: 11 | B58: 45430 | C58: Маричка | D58: =VLOOKUP($C58,ТабКлиенты[[#All],[name]:[phone]],MATCH(D$1,ТабКлиенты[#Headers],0)-1,0) -> #N/A | E58: =VLOOKUP($C58,ТабАдрес[[#All],[Клиент]:[gps]],MATCH(E$1,ТабКлиенты[#Headers],0)-4,0) -> #N/A | F58: =VLOOKUP($C58,ТабАдрес[[#All],[Клиент]:[gps]],MATCH(F$1,ТабКлиенты[#Headers],0)-4,0) -> #N/A | H58: 0 | I58: 102 | K58: =A58&". "&C58&CHAR(10)&"Тел.: "&D58&CHAR(10)&"Адрес: "&E58&CHAR(10)&"№ заказа: "&I58&CHAR(10)&"https://yandex.ru/maps/?text="&REPLACE(F58,SEARCH(",",F58),2,"%2C")&CHAR(10)&"https://maps.google.com/?daddr="&REPLACE(F58,SEARCH(",",F58),2,"%2C")&CHAR(10)&"К оплате: "&"**"&H58&CHAR(10)&"**"&"----------------------------------------------------------" -> #N/A
A59: 12 | B59: 45430 | C59: Александр Каскад | D59: =VLOOKUP($C59,ТабКлиенты[[#All],[name]:[phone]],MATCH(D$1,ТабКлиенты[#Headers],0)-1,0) -> #N/A | E59: =VLOOKUP($C59,ТабАдрес[[#All],[Клиент]:[gps]],MATCH(E$1,ТабКлиенты[#Headers],0)-4,0) -> #N/A | F59: =VLOOKUP($C59,ТабАдрес[[#All],[Клиент]:[gps]],MATCH(F$1,ТабКлиенты[#Headers],0)-4,0) -> #N/A | H59: 0 | I59: 77 | K59: =A59&". "&C59&CHAR(10)&"Тел.: "&D59&CHAR(10)&"Адрес: "&E59&CHAR(10)&"№ заказа: "&I59&CHAR(10)&"https://yandex.ru/maps/?text="&REPLACE(F59,SEARCH(",",F59),2,"%2C")&CHAR(10)&"https://maps.google.com/?daddr="&REPLACE(F59,SEARCH(",",F59),2,"%2C")&CHAR(10)&"К оплате: "&"**"&H59&CHAR(10)&"**"&"----------------------------------------------------------" -> #N/A
A60: 13 | B60: 45430 | C60: Александр Радин | D60: =VLOOKUP($C60,ТабКлиенты[[#All],[name]:[phone]],MATCH(D$1,ТабКлиенты[#Headers],0)-1,0) -> +79497277100 | E60: =VLOOKUP($C60,ТабАдрес[[#All],[Клиент]:[gps]],MATCH(E$1,ТабКлиенты[#Headers],0)-4,0) -> Артема 132 | F60: =VLOOKUP($C60,ТабАдрес[[#All],[Клиент]:[gps]],MATCH(F$1,ТабКлиенты[#Headers],0)-4,0) -> 47.1085, 37.5599 | H60: 5200 | I60: 90 | K60: =A60&". "&C60&CHAR(10)&"Тел.: "&D60&CHAR(10)&"Адрес: "&E60&CHAR(10)&"№ заказа: "&I60&CHAR(10)&"https://yandex.ru/maps/?text="&REPLACE(F60,SEARCH(",",F60),2,"%2C")&CHAR(10)&"https://maps.google.com/?daddr="&REPLACE(F60,SEARCH(",",F60),2,"%2C")&CHAR(10)&"К оплате: "&"**"&H60&CHAR(10)&"**"&"----------------------------------------------------------" -> 13. Александр Радин Тел.: +79497277100 Адрес: Артема 132 № заказа: 90 https://yandex.ru/maps/?text=47.1085%2C37.5599 https://maps.google.com/?daddr=47.1085%2C37.5599 К оплате: **5200 **----------------------------------------------------------
A61: 1 | B61: 45437 | C61: Александр 3 Металлургов | D61: =VLOOKUP($C61,ТабКлиенты[[#All],[name]:[phone]],MATCH(D$1,ТабКлиенты[#Headers],0)-1,0) -> #N/A | E61: =VLOOKUP($C61,ТабАдрес[[#All],[Клиент]:[gps]],MATCH(E$1,ТабКлиенты[#Headers],0)-4,0) -> #N/A | F61: =VLOOKUP($C61,ТабАдрес[[#All],[Клиент]:[gps]],MATCH(F$1,ТабКлиенты[#Headers],0)-4,0) -> #N/A | H61: 2539 | I61: 103 | K61: =A61&". "&C61&CHAR(10)&"Тел.: "&D61&CHAR(10)&"Адрес: "&E61&CHAR(10)&"№ заказа: "&I61&CHAR(10)&"https://yandex.ru/maps/?text="&REPLACE(F61,SEARCH(",",F61),2,"%2C")&CHAR(10)&"https://maps.google.com/?daddr="&REPLACE(F61,SEARCH(",",F61),2,"%2C")&CHAR(10)&"К оплате: "&"**"&H61&CHAR(10)&"**"&"----------------------------------------------------------" -> #N/A
A62: 2 | B62: 45437 | C62: Полинка | D62: =VLOOKUP($C62,ТабКлиенты[[#All],[name]:[phone]],MATCH(D$1,ТабКлиенты[#Headers],0)-1,0) -> #N/A | E62: =VLOOKUP($C62,ТабАдрес[[#All],[Клиент]:[gps]],MATCH(E$1,ТабКлиенты[#Headers],0)-4,0) -> #N/A | F62: =VLOOKUP($C62,ТабАдрес[[#All],[Клиент]:[gps]],MATCH(F$1,ТабКлиенты[#Headers],0)-4,0) -> #N/A | H62: 0 | I62: 99, 110 | K62: =A62&". "&C62&CHAR(10)&"Тел.: "&D62&CHAR(10)&"Адрес: "&E62&CHAR(10)&"№ заказа: "&I62&CHAR(10)&"https://yandex.ru/maps/?text="&REPLACE(F62,SEARCH(",",F62),2,"%2C")&CHAR(10)&"https://maps.google.com/?daddr="&REPLACE(F62,SEARCH(",",F62),2,"%2C")&CHAR(10)&"К оплате: "&"**"&H62&CHAR(10)&"**"&"----------------------------------------------------------" -> #N/A
A63: 3 | B63: 45437 | C63: Кристина дет.мир | D63: =VLOOKUP($C63,ТабКлиенты[[#All],[name]:[phone]],MATCH(D$1,ТабКлиенты[#Headers],0)-1,0) -> #N/A | E63: =VLOOKUP($C63,ТабАдрес[[#All],[Клиент]:[gps]],MATCH(E$1,ТабКлиенты[#Headers],0)-4,0) -> #N/A | F63: =VLOOKUP($C63,ТабАдрес[[#All],[Клиент]:[gps]],MATCH(F$1,ТабКлиенты[#Headers],0)-4,0) -> #N/A | H63: 0 | K63: =A63&". "&C63&CHAR(10)&"Тел.: "&D63&CHAR(10)&"Адрес: "&E63&CHAR(10)&"№ заказа: "&I63&CHAR(10)&"https://yandex.ru/maps/?text="&REPLACE(F63,SEARCH(",",F63),2,"%2C")&CHAR(10)&"https://maps.google.com/?daddr="&REPLACE(F63,SEARCH(",",F63),2,"%2C")&CHAR(10)&"К оплате: "&"**"&H63&CHAR(10)&"**"&"----------------------------------------------------------" -> #N/A
A64: 4 | B64: 45437 | C64: Лариса Кирова | D64: =VLOOKUP($C64,ТабКлиенты[[#All],[name]:[phone]],MATCH(D$1,ТабКлиенты[#Headers],0)-1,0) -> #N/A | E64: =VLOOKUP($C64,ТабАдрес[[#All],[Клиент]:[gps]],MATCH(E$1,ТабКлиенты[#Headers],0)-4,0) -> #N/A | F64: =VLOOKUP($C64,ТабАдрес[[#All],[Клиент]:[gps]],MATCH(F$1,ТабКлиенты[#Headers],0)-4,0) -> #N/A | H64: 0 | I64: 109 | K64: =A64&". "&C64&CHAR(10)&"Тел.: "&D64&CHAR(10)&"Адрес: "&E64&CHAR(10)&"№ заказа: "&I64&CHAR(10)&"https://yandex.ru/maps/?text="&REPLACE(F64,SEARCH(",",F64),2,"%2C")&CHAR(10)&"https://maps.google.com/?daddr="&REPLACE(F64,SEARCH(",",F64),2,"%2C")&CHAR(10)&"К оплате: "&"**"&H64&CHAR(10)&"**"&"----------------------------------------------------------" -> #N/A
A65: 5 | B65: 45437 | C65: Галина Агабекова(церковь) | D65: =VLOOKUP($C65,ТабКлиенты[[#All],[name]:[phone]],MATCH(D$1,ТабКлиенты[#Headers],0)-1,0) -> #N/A | E65: =VLOOKUP($C65,ТабАдрес[[#All],[Клиент]:[gps]],MATCH(E$1,ТабКлиенты[#Headers],0)-4,0) -> #N/A | F65: =VLOOKUP($C65,ТабАдрес[[#All],[Клиент]:[gps]],MATCH(F$1,ТабКлиенты[#Headers],0)-4,0) -> #N/A | H65: 0 | I65: 97, 105 | K65: =A65&". "&C65&CHAR(10)&"Тел.: "&D65&CHAR(10)&"Адрес: "&E65&CHAR(10)&"№ заказа: "&I65&CHAR(10)&"https://yandex.ru/maps/?text="&REPLACE(F65,SEARCH(",",F65),2,"%2C")&CHAR(10)&"https://maps.google.com/?daddr="&REPLACE(F65,SEARCH(",",F65),2,"%2C")&CHAR(10)&"К оплате: "&"**"&H65&CHAR(10)&"**"&"----------------------------------------------------------" -> #N/A
A66: 6 | B66: 45437 | C66: Вадим | D66: =VLOOKUP($C66,ТабКлиенты[[#All],[name]:[phone]],MATCH(D$1,ТабКлиенты[#Headers],0)-1,0) -> #N/A | E66: =VLOOKUP($C66,ТабАдрес[[#All],[Клиент]:[gps]],MATCH(E$1,ТабКлиенты[#Headers],0)-4,0) -> #N/A | F66: =VLOOKUP($C66,ТабАдрес[[#All],[Клиент]:[gps]],MATCH(F$1,ТабКлиенты[#Headers],0)-4,0) -> #N/A | H66: 0 | I66: 104 | K66: =A66&". "&C66&CHAR(10)&"Тел.: "&D66&CHAR(10)&"Адрес: "&E66&CHAR(10)&"№ заказа: "&I66&CHAR(10)&"https://yandex.ru/maps/?text="&REPLACE(F66,SEARCH(",",F66),2,"%2C")&CHAR(10)&"https://maps.google.com/?daddr="&REPLACE(F66,SEARCH(",",F66),2,"%2C")&CHAR(10)&"К оплате: "&"**"&H66&CHAR(10)&"**"&"----------------------------------------------------------" -> #N/A
A67: 7 | B67: 45437 | C67: Максим телевизор | D67: =VLOOKUP($C67,ТабКлиенты[[#All],[name]:[phone]],MATCH(D$1,ТабКлиенты[#Headers],0)-1,0) -> #N/A | E67: =VLOOKUP($C67,ТабАдрес[[#All],[Клиент]:[gps]],MATCH(E$1,ТабКлиенты[#Headers],0)-4,0) -> #N/A | F67: =VLOOKUP($C67,ТабАдрес[[#All],[Клиент]:[gps]],MATCH(F$1,ТабКлиенты[#Headers],0)-4,0) -> #N/A | H67: 2163 | I67: 111 | K67: =A67&". "&C67&CHAR(10)&"Тел.: "&D67&CHAR(10)&"Адрес: "&E67&CHAR(10)&"№ заказа: "&I67&CHAR(10)&"https://yandex.ru/maps/?text="&REPLACE(F67,SEARCH(",",F67),2,"%2C")&CHAR(10)&"https://maps.google.com/?daddr="&REPLACE(F67,SEARCH(",",F67),2,"%2C")&CHAR(10)&"К оплате: "&"**"&H67&CHAR(10)&"**"&"----------------------------------------------------------" -> #N/A
A68: 8 | B68: 45437 | C68: Наталья 60 лет СССР | D68: =VLOOKUP($C68,ТабКлиенты[[#All],[name]:[phone]],MATCH(D$1,ТабКлиенты[#Headers],0)-1,0) -> +79497094719 | E68: =VLOOKUP($C68,ТабАдрес[[#All],[Клиент]:[gps]],MATCH(E$1,ТабКлиенты[#Headers],0)-4,0) -> 60 лет СССР 2Б | F68: =VLOOKUP($C68,ТабАдрес[[#All],[Клиент]:[gps]],MATCH(F$1,ТабКлиенты[#Headers],0)-4,0) -> 47.1178, 37.5121 | H68: 2600 | I68: Витамины | K68: =A68&". "&C68&CHAR(10)&"Тел.: "&D68&CHAR(10)&"Адрес: "&E68&CHAR(10)&"№ заказа: "&I68&CHAR(10)&"https://yandex.ru/maps/?text="&REPLACE(F68,SEARCH(",",F68),2,"%2C")&CHAR(10)&"https://maps.google.com/?daddr="&REPLACE(F68,SEARCH(",",F68),2,"%2C")&CHAR(10)&"К оплате: "&"**"&H68&CHAR(10)&"**"&"----------------------------------------------------------" -> 8. Наталья 60 лет СССР Тел.: +79497094719 Адрес: 60 лет СССР 2Б № заказа: Витамины https://yandex.ru/maps/?text=47.1178%2C37.5121 https://maps.google.com/?daddr=47.1178%2C37.5121 К оплате: **2600 **----------------------------------------------------------
A69: 9 | B69: 45437 | C69: Лариса Лавицкого 16 | D69: =VLOOKUP($C69,ТабКлиенты[[#All],[name]:[phone]],MATCH(D$1,ТабКлиенты[#Headers],0)-1,0) -> #N/A | E69: =VLOOKUP($C69,ТабАдрес[[#All],[Клиент]:[gps]],MATCH(E$1,ТабКлиенты[#Headers],0)-4,0) -> #N/A | F69: =VLOOKUP($C69,ТабАдрес[[#All],[Клиент]:[gps]],MATCH(F$1,ТабКлиенты[#Headers],0)-4,0) -> #N/A | H69: 2504 | I69: 112 | K69: =A69&". "&C69&CHAR(10)&"Тел.: "&D69&CHAR(10)&"Адрес: "&E69&CHAR(10)&"№ заказа: "&I69&CHAR(10)&"https://yandex.ru/maps/?text="&REPLACE(F69,SEARCH(",",F69),2,"%2C")&CHAR(10)&"https://maps.google.com/?daddr="&REPLACE(F69,SEARCH(",",F69),2,"%2C")&CHAR(10)&"К оплате: "&"**"&H69&CHAR(10)&"**"&"----------------------------------------------------------" -> #N/A
A70: 1 | B70: 45444 | C70: Александр Каскад | D70: =VLOOKUP($C70,ТабКлиенты[[#All],[name]:[phone]],MATCH(D$1,ТабКлиенты[#Headers],0)-1,0) -> #N/A | E70: =VLOOKUP($C70,ТабАдрес[[#All],[Клиент]:[gps]],MATCH(E$1,ТабКлиенты[#Headers],0)-4,0) -> #N/A | F70: =VLOOKUP($C70,ТабАдрес[[#All],[Клиент]:[gps]],MATCH(F$1,ТабКлиенты[#Headers],0)-4,0) -> #N/A | H70: 0 | I70: 43 | K70: =A70&". "&C70&CHAR(10)&"Тел.: "&D70&CHAR(10)&"Адрес: "&E70&CHAR(10)&"№ заказа: "&I70&CHAR(10)&"https://yandex.ru/maps/?text="&REPLACE(F70,SEARCH(",",F70),2,"%2C")&CHAR(10)&"https://maps.google.com/?daddr="&REPLACE(F70,SEARCH(",",F70),2,"%2C")&CHAR(10)&"К оплате: "&"**"&H70&CHAR(10)&"**"&"----------------------------------------------------------" -> #N/A
A71: 2 | B71: 45444 | C71: Валерий СТО ОРИОН | D71: =VLOOKUP($C71,ТабКлиенты[[#All],[name]:[phone]],MATCH(D$1,ТабКлиенты[#Headers],0)-1,0) -> +79497398357 | E71: =VLOOKUP($C71,ТабАдрес[[#All],[Клиент]:[gps]],MATCH(E$1,ТабКлиенты[#Headers],0)-4,0) -> Макара Мазая 41 | F71: =VLOOKUP($C71,ТабАдрес[[#All],[Клиент]:[gps]],MATCH(F$1,ТабКлиенты[#Headers],0)-4,0) -> 0 | H71: 0 | I71: Витамины | K71: =A71&". "&C71&CHAR(10)&"Тел.: "&D71&CHAR(10)&"Адрес: "&E71&CHAR(10)&"№ заказа: "&I71&CHAR(10)&"https://yandex.ru/maps/?text="&REPLACE(F71,SEARCH(",",F71),2,"%2C")&CHAR(10)&"https://maps.google.com/?daddr="&REPLACE(F71,SEARCH(",",F71),2,"%2C")&CHAR(10)&"К оплате: "&"**"&H71&CHAR(10)&"**"&"----------------------------------------------------------" -> #VALUE!
A72: 3 | B72: 45444 | C72: Митрофанов Евгений | D72: =VLOOKUP($C72,ТабКлиенты[[#All],[name]:[phone]],MATCH(D$1,ТабКлиенты[#Headers],0)-1,0) -> #N/A | E72: =VLOOKUP($C72,ТабАдрес[[#All],[Клиент]:[gps]],MATCH(E$1,ТабКлиенты[#Headers],0)-4,0) -> #N/A | F72: =VLOOKUP($C72,ТабАдрес[[#All],[Клиент]:[gps]],MATCH(F$1,ТабКлиенты[#Headers],0)-4,0) -> #N/A | H72: -89 | I72: 80, 17 | K72: =A72&". "&C72&CHAR(10)&"Тел.: "&D72&CHAR(10)&"Адрес: "&E72&CHAR(10)&"№ заказа: "&I72&CHAR(10)&"https://yandex.ru/maps/?text="&REPLACE(F72,SEARCH(",",F72),2,"%2C")&CHAR(10)&"https://maps.google.com/?daddr="&REPLACE(F72,SEARCH(",",F72),2,"%2C")&CHAR(10)&"К оплате: "&"**"&H72&CHAR(10)&"**"&"----------------------------------------------------------" -> #N/A
A73: 4 | B73: 45444 | C73: Лариса Кирова | D73: =VLOOKUP($C73,ТабКлиенты[[#All],[name]:[phone]],MATCH(D$1,ТабКлиенты[#Headers],0)-1,0) -> #N/A | E73: =VLOOKUP($C73,ТабАдрес[[#All],[Клиент]:[gps]],MATCH(E$1,ТабКлиенты[#Headers],0)-4,0) -> #N/A | F73: =VLOOKUP($C73,ТабАдрес[[#All],[Клиент]:[gps]],MATCH(F$1,ТабКлиенты[#Headers],0)-4,0) -> #N/A | H73: 0 | I73: 88, 109, 25 | K73: =A73&". "&C73&CHAR(10)&"Тел.: "&D73&CHAR(10)&"Адрес: "&E73&CHAR(10)&"№ заказа: "&I73&CHAR(10)&"https://yandex.ru/maps/?text="&REPLACE(F73,SEARCH(",",F73),2,"%2C")&CHAR(10)&"https://maps.google.com/?daddr="&REPLACE(F73,SEARCH(",",F73),2,"%2C")&CHAR(10)&"К оплате: "&"**"&H73&CHAR(10)&"**"&"----------------------------------------------------------" -> #N/A
A74: 5 | B74: 45444 | C74: Галина Агабекова(церковь) | D74: =VLOOKUP($C74,ТабКлиенты[[#All],[name]:[phone]],MATCH(D$1,ТабКлиенты[#Headers],0)-1,0) -> #N/A | E74: =VLOOKUP($C74,ТабАдрес[[#All],[Клиент]:[gps]],MATCH(E$1,ТабКлиенты[#Headers],0)-4,0) -> #N/A | F74: =VLOOKUP($C74,ТабАдрес[[#All],[Клиент]:[gps]],MATCH(F$1,ТабКлиенты[#Headers],0)-4,0) -> #N/A | H74: 7325 | I74: 97, 20 | K74: =A74&". "&C74&CHAR(10)&"Тел.: "&D74&CHAR(10)&"Адрес: "&E74&CHAR(10)&"№ заказа: "&I74&CHAR(10)&"https://yandex.ru/maps/?text="&REPLACE(F74,SEARCH(",",F74),2,"%2C")&CHAR(10)&"https://maps.google.com/?daddr="&REPLACE(F74,SEARCH(",",F74),2,"%2C")&CHAR(10)&"К оплате: "&"**"&H74&CHAR(10)&"**"&"----------------------------------------------------------" -> #N/A
A75: 6 | B75: 45444 | C75: Максим телевизор | D75: =VLOOKUP($C75,ТабКлиенты[[#All],[name]:[phone]],MATCH(D$1,ТабКлиенты[#Headers],0)-1,0) -> #N/A | E75: =VLOOKUP($C75,ТабАдрес[[#All],[Клиент]:[gps]],MATCH(E$1,ТабКлиенты[#Headers],0)-4,0) -> #N/A | F75: =VLOOKUP($C75,ТабАдрес[[#All],[Клиент]:[gps]],MATCH(F$1,ТабКлиенты[#Headers],0)-4,0) -> #N/A | H75: 303 | I75: 117 | K75: =A75&". "&C75&CHAR(10)&"Тел.: "&D75&CHAR(10)&"Адрес: "&E75&CHAR(10)&"№ заказа: "&I75&CHAR(10)&"https://yandex.ru/maps/?text="&REPLACE(F75,SEARCH(",",F75),2,"%2C")&CHAR(10)&"https://maps.google.com/?daddr="&REPLACE(F75,SEARCH(",",F75),2,"%2C")&CHAR(10)&"К оплате: "&"**"&H75&CHAR(10)&"**"&"----------------------------------------------------------" -> #N/A
A76: 7 | B76: 45444 | C76: Даша Калифорния | D76: =VLOOKUP($C76,ТабКлиенты[[#All],[name]:[phone]],MATCH(D$1,ТабКлиенты[#Headers],0)-1,0) -> +79496248226 | E76: =VLOOKUP($C76,ТабАдрес[[#All],[Клиент]:[gps]],MATCH(E$1,ТабКлиенты[#Headers],0)-4,0) -> Шевченко 274 | F76: =VLOOKUP($C76,ТабАдрес[[#All],[Клиент]:[gps]],MATCH(F$1,ТабКлиенты[#Headers],0)-4,0) -> 47.1149, 37.5127 | H76: 1200 | I76: Витамины | K76: =A76&". "&C76&CHAR(10)&"Тел.: "&D76&CHAR(10)&"Адрес: "&E76&CHAR(10)&"№ заказа: "&I76&CHAR(10)&"https://yandex.ru/maps/?text="&REPLACE(F76,SEARCH(",",F76),2,"%2C")&CHAR(10)&"https://maps.google.com/?daddr="&REPLACE(F76,SEARCH(",",F76),2,"%2C")&CHAR(10)&"К оплате: "&"**"&H76&CHAR(10)&"**"&"----------------------------------------------------------" -> 7. Даша Калифорния Тел.: +79496248226 Адрес: Шевченко 274 № заказа: Витамины https://yandex.ru/maps/?text=47.1149%2C37.5127 https://maps.google.com/?daddr=47.1149%2C37.5127 К оплате: **1200 **----------------------------------------------------------
A77: 8 | B77: 45444 | C77: григорий(танковый ) | D77: =VLOOKUP($C77,ТабКлиенты[[#All],[name]:[phone]],MATCH(D$1,ТабКлиенты[#Headers],0)-1,0) -> #N/A | E77: =VLOOKUP($C77,ТабАдрес[[#All],[Клиент]:[gps]],MATCH(E$1,ТабКлиенты[#Headers],0)-4,0) -> #N/A | F77: =VLOOKUP($C77,ТабАдрес[[#All],[Клиент]:[gps]],MATCH(F$1,ТабКлиенты[#Headers],0)-4,0) -> #N/A | H77: -2854 | I77: 79, 20 | K77: =A77&". "&C77&CHAR(10)&"Тел.: "&D77&CHAR(10)&"Адрес: "&E77&CHAR(10)&"№ заказа: "&I77&CHAR(10)&"https://yandex.ru/maps/?text="&REPLACE(F77,SEARCH(",",F77),2,"%2C")&CHAR(10)&"https://maps.google.com/?daddr="&REPLACE(F77,SEARCH(",",F77),2,"%2C")&CHAR(10)&"К оплате: "&"**"&H77&CHAR(10)&"**"&"----------------------------------------------------------" -> #N/A
A78: 1 | B78: 45451 | C78: Анна соседка | D78: =VLOOKUP($C78,ТабКлиенты[[#All],[name]:[phone]],MATCH(D$1,ТабКлиенты[#Headers],0)-1,0) -> +79497105263 | E78: =VLOOKUP($C78,ТабАдрес[[#All],[Клиент]:[gps]],MATCH(E$1,ТабКлиенты[#Headers],0)-4,0) -> Казанцева 31 | F78: =VLOOKUP($C78,ТабАдрес[[#All],[Клиент]:[gps]],MATCH(F$1,ТабКлиенты[#Headers],0)-4,0) -> 47.1070, 37.5475 | H78: 0 | I78: Витамины | K78: =A78&". "&C78&CHAR(10)&"Тел.: "&D78&CHAR(10)&"Адрес: "&E78&CHAR(10)&"№ заказа: "&I78&CHAR(10)&"https://yandex.ru/maps/?text="&REPLACE(F78,SEARCH(",",F78),2,"%2C")&CHAR(10)&"https://maps.google.com/?daddr="&REPLACE(F78,SEARCH(",",F78),2,"%2C")&CHAR(10)&"К оплате: "&"**"&H78&CHAR(10)&"**"&"----------------------------------------------------------" -> 1. Анна соседка Тел.: +79497105263 Адрес: Казанцева 31 № заказа: Витамины https://yandex.ru/maps/?text=47.1070%2C37.5475 https://maps.google.com/?daddr=47.1070%2C37.5475 К оплате: **0 **----------------------------------------------------------
A79: 2 | B79: 45451 | C79: Митрофанов Евгений | D79: =VLOOKUP($C79,ТабКлиенты[[#All],[name]:[phone]],MATCH(D$1,ТабКлиенты[#Headers],0)-1,0) -> #N/A | E79: =VLOOKUP($C79,ТабАдрес[[#All],[Клиент]:[gps]],MATCH(E$1,ТабКлиенты[#Headers],0)-4,0) -> #N/A | F79: =VLOOKUP($C79,ТабАдрес[[#All],[Клиент]:[gps]],MATCH(F$1,ТабКлиенты[#Headers],0)-4,0) -> #N/A | H79: 0 | I79: 120 | K79: =A79&". "&C79&CHAR(10)&"Тел.: "&D79&CHAR(10)&"Адрес: "&E79&CHAR(10)&"№ заказа: "&I79&CHAR(10)&"https://yandex.ru/maps/?text="&REPLACE(F79,SEARCH(",",F79),2,"%2C")&CHAR(10)&"https://maps.google.com/?daddr="&REPLACE(F79,SEARCH(",",F79),2,"%2C")&CHAR(10)&"К оплате: "&"**"&H79&CHAR(10)&"**"&"----------------------------------------------------------" -> #N/A
A80: 3 | B80: 45451 | C80: Юля Ларисына | D80: =VLOOKUP($C80,ТабКлиенты[[#All],[name]:[phone]],MATCH(D$1,ТабКлиенты[#Headers],0)-1,0) -> #N/A | E80: =VLOOKUP($C80,ТабАдрес[[#All],[Клиент]:[gps]],MATCH(E$1,ТабКлиенты[#Headers],0)-4,0) -> #N/A | F80: =VLOOKUP($C80,ТабАдрес[[#All],[Клиент]:[gps]],MATCH(F$1,ТабКлиенты[#Headers],0)-4,0) -> #N/A | H80: 0 | I80: 122 | K80: =A80&". "&C80&CHAR(10)&"Тел.: "&D80&CHAR(10)&"Адрес: "&E80&CHAR(10)&"№ заказа: "&I80&CHAR(10)&"https://yandex.ru/maps/?text="&REPLACE(F80,SEARCH(",",F80),2,"%2C")&CHAR(10)&"https://maps.google.com/?daddr="&REPLACE(F80,SEARCH(",",F80),2,"%2C")&CHAR(10)&"К оплате: "&"**"&H80&CHAR(10)&"**"&"----------------------------------------------------------" -> #N/A
A81: 4 | B81: 45451 | C81: Константин СТО Оптима | D81: =VLOOKUP($C81,ТабКлиенты[[#All],[name]:[phone]],MATCH(D$1,ТабКлиенты[#Headers],0)-1,0) -> +79496340956 | E81: =VLOOKUP($C81,ТабАдрес[[#All],[Клиент]:[gps]],MATCH(E$1,ТабКлиенты[#Headers],0)-4,0) -> Макара Мазая 41 | F81: =VLOOKUP($C81,ТабАдрес[[#All],[Клиент]:[gps]],MATCH(F$1,ТабКлиенты[#Headers],0)-4,0) -> 47.1361, 37.5817 | H81: 2500 | I81: Витамины | K81: =A81&". "&C81&CHAR(10)&"Тел.: "&D81&CHAR(10)&"Адрес: "&E81&CHAR(10)&"№ заказа: "&I81&CHAR(10)&"https://yandex.ru/maps/?text="&REPLACE(F81,SEARCH(",",F81),2,"%2C")&CHAR(10)&"https://maps.google.com/?daddr="&REPLACE(F81,SEARCH(",",F81),2,"%2C")&CHAR(10)&"К оплате: "&"**"&H81&CHAR(10)&"**"&"----------------------------------------------------------" -> 4. Константин СТО Оптима Тел.: +79496340956 Адрес: Макара Мазая 41 № заказа: Витамины https://yandex.ru/maps/?text=47.1361%2C37.5817 https://maps.google.com/?daddr=47.1361%2C37.5817 К оплате: **2500 **----------------------------------------------------------
A82: 5 | B82: 45451 | C82: Александр электростанция | D82: =VLOOKUP($C82,ТабКлиенты[[#All],[name]:[phone]],MATCH(D$1,ТабКлиенты[#Headers],0)-1,0) -> #N/A | E82: =VLOOKUP($C82,ТабАдрес[[#All],[Клиент]:[gps]],MATCH(E$1,ТабКлиенты[#Headers],0)-4,0) -> #N/A | F82: =VLOOKUP($C82,ТабАдрес[[#All],[Клиент]:[gps]],MATCH(F$1,ТабКлиенты[#Headers],0)-4,0) -> #N/A | H82: 13000 | I82: Витамины | K82: =A82&". "&C82&CHAR(10)&"Тел.: "&D82&CHAR(10)&"Адрес: "&E82&CHAR(10)&"№ заказа: "&I82&CHAR(10)&"https://yandex.ru/maps/?text="&REPLACE(F82,SEARCH(",",F82),2,"%2C")&CHAR(10)&"https://maps.google.com/?daddr="&REPLACE(F82,SEARCH(",",F82),2,"%2C")&CHAR(10)&"К оплате: "&"**"&H82&CHAR(10)&"**"&"----------------------------------------------------------" -> #N/A
A83: 6 | B83: 45451 | C83: Александр 3 База | D83: =VLOOKUP($C83,ТабКлиенты[[#All],[name]:[phone]],MATCH(D$1,ТабКлиенты[#Headers],0)-1,0) -> #N/A | E83: =VLOOKUP($C83,ТабАдрес[[#All],[Клиент]:[gps]],MATCH(E$1,ТабКлиенты[#Headers],0)-4,0) -> #N/A | F83: =VLOOKUP($C83,ТабАдрес[[#All],[Клиент]:[gps]],MATCH(F$1,ТабКлиенты[#Headers],0)-4,0) -> #N/A | H83: 1892 | I83: 100 | K83: =A83&". "&C83&CHAR(10)&"Тел.: "&D83&CHAR(10)&"Адрес: "&E83&CHAR(10)&"№ заказа: "&I83&CHAR(10)&"https://yandex.ru/maps/?text="&REPLACE(F83,SEARCH(",",F83),2,"%2C")&CHAR(10)&"https://maps.google.com/?daddr="&REPLACE(F83,SEARCH(",",F83),2,"%2C")&CHAR(10)&"К оплате: "&"**"&H83&CHAR(10)&"**"&"----------------------------------------------------------" -> #N/A
A84: 7 | B84: 45451 | C84: Галина Агабекова(церковь) | D84: =VLOOKUP($C84,ТабКлиенты[[#All],[name]:[phone]],MATCH(D$1,ТабКлиенты[#Headers],0)-1,0) -> #N/A | E84: =VLOOKUP($C84,ТабАдрес[[#All],[Клиент]:[gps]],MATCH(E$1,ТабКлиенты[#Headers],0)-4,0) -> #N/A | F84: =VLOOKUP($C84,ТабАдрес[[#All],[Клиент]:[gps]],MATCH(F$1,ТабКлиенты[#Headers],0)-4,0) -> #N/A | H84: 0 | I84: 114, 70 | K84: =A84&". "&C84&CHAR(10)&"Тел.: "&D84&CHAR(10)&"Адрес: "&E84&CHAR(10)&"№ заказа: "&I84&CHAR(10)&"https://yandex.ru/maps/?text="&REPLACE(F84,SEARCH(",",F84),2,"%2C")&CHAR(10)&"https://maps.google.com/?daddr="&REPLACE(F84,SEARCH(",",F84),2,"%2C")&CHAR(10)&"К оплате: "&"**"&H84&CHAR(10)&"**"&"----------------------------------------------------------" -> #N/A
A85: 8 | B85: 45451 | C85: Лариса Кирова | D85: =VLOOKUP($C85,ТабКлиенты[[#All],[name]:[phone]],MATCH(D$1,ТабКлиенты[#Headers],0)-1,0) -> #N/A | E85: =VLOOKUP($C85,ТабАдрес[[#All],[Клиент]:[gps]],MATCH(E$1,ТабКлиенты[#Headers],0)-4,0) -> #N/A | F85: =VLOOKUP($C85,ТабАдрес[[#All],[Клиент]:[gps]],MATCH(F$1,ТабКлиенты[#Headers],0)-4,0) -> #N/A | H85: 0 | I85: 25, 119 | K85: =A85&". "&C85&CHAR(10)&"Тел.: "&D85&CHAR(10)&"Адрес: "&E85&CHAR(10)&"№ заказа: "&I85&CHAR(10)&"https://yandex.ru/maps/?text="&REPLACE(F85,SEARCH(",",F85),2,"%2C")&CHAR(10)&"https://maps.google.com/?daddr="&REPLACE(F85,SEARCH(",",F85),2,"%2C")&CHAR(10)&"К оплате: "&"**"&H85&CHAR(10)&"**"&"----------------------------------------------------------" -> #N/A
A86: 1 | B86: 45458 | C86: Людмила Эдельвейс | D86: =VLOOKUP($C86,ТабКлиенты[[#All],[name]:[phone]],MATCH(D$1,ТабКлиенты[#Headers],0)-1,0) -> +79496019237 | E86: =VLOOKUP($C86,ТабАдрес[[#All],[Клиент]:[gps]],MATCH(E$1,ТабКлиенты[#Headers],0)-4,0) -> Металлургов 92 | F86: =VLOOKUP($C86,ТабАдрес[[#All],[Клиент]:[gps]],MATCH(F$1,ТабКлиенты[#Headers],0)-4,0) -> 47.1053, 37.5483 | H86: 0 | I86: 127 | K86: =A86&". "&C86&CHAR(10)&"Тел.: "&D86&CHAR(10)&"Адрес: "&E86&CHAR(10)&"№ заказа: "&I86&CHAR(10)&"https://yandex.ru/maps/?text="&REPLACE(F86,SEARCH(",",F86),2,"%2C")&CHAR(10)&"https://maps.google.com/?daddr="&REPLACE(F86,SEARCH(",",F86),2,"%2C")&CHAR(10)&"К оплате: "&"**"&H86&CHAR(10)&"**"&"----------------------------------------------------------" -> 1. Людмила Эдельвейс Тел.: +79496019237 Адрес: Металлургов 92 № заказа: 127 https://yandex.ru/maps/?text=47.1053%2C37.5483 https://maps.google.com/?daddr=47.1053%2C37.5483 К оплате: **0 **----------------------------------------------------------
A87: 2 | B87: 45458 | C87: Галина Агабекова(церковь) | D87: =VLOOKUP($C87,ТабКлиенты[[#All],[name]:[phone]],MATCH(D$1,ТабКлиенты[#Headers],0)-1,0) -> #N/A | E87: =VLOOKUP($C87,ТабАдрес[[#All],[Клиент]:[gps]],MATCH(E$1,ТабКлиенты[#Headers],0)-4,0) -> #N/A | F87: =VLOOKUP($C87,ТабАдрес[[#All],[Клиент]:[gps]],MATCH(F$1,ТабКлиенты[#Headers],0)-4,0) -> #N/A | H87: 0 | I87: 70 | K87: =A87&". "&C87&CHAR(10)&"Тел.: "&D87&CHAR(10)&"Адрес: "&E87&CHAR(10)&"№ заказа: "&I87&CHAR(10)&"https://yandex.ru/maps/?text="&REPLACE(F87,SEARCH(",",F87),2,"%2C")&CHAR(10)&"https://maps.google.com/?daddr="&REPLACE(F87,SEARCH(",",F87),2,"%2C")&CHAR(10)&"К оплате: "&"**"&H87&CHAR(10)&"**"&"----------------------------------------------------------" -> #N/A
A88: 3 | B88: 45458 | C88: Лариса Кирова | D88: =VLOOKUP($C88,ТабКлиенты[[#All],[name]:[phone]],MATCH(D$1,ТабКлиенты[#Headers],0)-1,0) -> #N/A | E88: =VLOOKUP($C88,ТабАдрес[[#All],[Клиент]:[gps]],MATCH(E$1,ТабКлиенты[#Headers],0)-4,0) -> #N/A | F88: =VLOOKUP($C88,ТабАдрес[[#All],[Клиент]:[gps]],MATCH(F$1,ТабКлиенты[#Headers],0)-4,0) -> #N/A | H88: 0 | I88: 123 | K88: =A88&". "&C88&CHAR(10)&"Тел.: "&D88&CHAR(10)&"Адрес: "&E88&CHAR(10)&"№ заказа: "&I88&CHAR(10)&"https://yandex.ru/maps/?text="&REPLACE(F88,SEARCH(",",F88),2,"%2C")&CHAR(10)&"https://maps.google.com/?daddr="&REPLACE(F88,SEARCH(",",F88),2,"%2C")&CHAR(10)&"К оплате: "&"**"&H88&CHAR(10)&"**"&"----------------------------------------------------------" -> #N/A
A89: 4 | B89: 45458 | C89: Алена шмалко | D89: =VLOOKUP($C89,ТабКлиенты[[#All],[name]:[phone]],MATCH(D$1,ТабКлиенты[#Headers],0)-1,0) -> #N/A | E89: =VLOOKUP($C89,ТабАдрес[[#All],[Клиент]:[gps]],MATCH(E$1,ТабКлиенты[#Headers],0)-4,0) -> #N/A | F89: =VLOOKUP($C89,ТабАдрес[[#All],[Клиент]:[gps]],MATCH(F$1,ТабКлиенты[#Headers],0)-4,0) -> #N/A | H89: 4000 | I89: 118 | K89: =A89&". "&C89&CHAR(10)&"Тел.: "&D89&CHAR(10)&"Адрес: "&E89&CHAR(10)&"№ заказа: "&I89&CHAR(10)&"https://yandex.ru/maps/?text="&REPLACE(F89,SEARCH(",",F89),2,"%2C")&CHAR(10)&"https://maps.google.com/?daddr="&REPLACE(F89,SEARCH(",",F89),2,"%2C")&CHAR(10)&"К оплате: "&"**"&H89&CHAR(10)&"**"&"----------------------------------------------------------" -> #N/A
A90: 5 | B90: 45458 | C90: Митрофанов Евгений | D90: =VLOOKUP($C90,ТабКлиенты[[#All],[name]:[phone]],MATCH(D$1,ТабКлиенты[#Headers],0)-1,0) -> #N/A | E90: =VLOOKUP($C90,ТабАдрес[[#All],[Клиент]:[gps]],MATCH(E$1,ТабКлиенты[#Headers],0)-4,0) -> #N/A | F90: =VLOOKUP($C90,ТабАдрес[[#All],[Клиент]:[gps]],MATCH(F$1,ТабКлиенты[#Headers],0)-4,0) -> #N/A | H90: 0 | I90: 120 | K90: =A90&". "&C90&CHAR(10)&"Тел.: "&D90&CHAR(10)&"Адрес: "&E90&CHAR(10)&"№ заказа: "&I90&CHAR(10)&"https://yandex.ru/maps/?text="&REPLACE(F90,SEARCH(",",F90),2,"%2C")&CHAR(10)&"https://maps.google.com/?daddr="&REPLACE(F90,SEARCH(",",F90),2,"%2C")&CHAR(10)&"К оплате: "&"**"&H90&CHAR(10)&"**"&"----------------------------------------------------------" -> #N/A
A91: 6 | B91: 45458 | C91: Юля Ларисына | D91: =VLOOKUP($C91,ТабКлиенты[[#All],[name]:[phone]],MATCH(D$1,ТабКлиенты[#Headers],0)-1,0) -> #N/A | E91: =VLOOKUP($C91,ТабАдрес[[#All],[Клиент]:[gps]],MATCH(E$1,ТабКлиенты[#Headers],0)-4,0) -> #N/A | F91: =VLOOKUP($C91,ТабАдрес[[#All],[Клиент]:[gps]],MATCH(F$1,ТабКлиенты[#Headers],0)-4,0) -> #N/A | H91: 0 | I91: 122 124 | K91: =A91&". "&C91&CHAR(10)&"Тел.: "&D91&CHAR(10)&"Адрес: "&E91&CHAR(10)&"№ заказа: "&I91&CHAR(10)&"https://yandex.ru/maps/?text="&REPLACE(F91,SEARCH(",",F91),2,"%2C")&CHAR(10)&"https://maps.google.com/?daddr="&REPLACE(F91,SEARCH(",",F91),2,"%2C")&CHAR(10)&"К оплате: "&"**"&H91&CHAR(10)&"**"&"----------------------------------------------------------" -> #N/A
A92: 7 | B92: 45458 | C92: Полинка | D92: =VLOOKUP($C92,ТабКлиенты[[#All],[name]:[phone]],MATCH(D$1,ТабКлиенты[#Headers],0)-1,0) -> #N/A | E92: =VLOOKUP($C92,ТабАдрес[[#All],[Клиент]:[gps]],MATCH(E$1,ТабКлиенты[#Headers],0)-4,0) -> #N/A | F92: =VLOOKUP($C92,ТабАдрес[[#All],[Клиент]:[gps]],MATCH(F$1,ТабКлиенты[#Headers],0)-4,0) -> #N/A | H92: 0 | I92: 96 110 | K92: =A92&". "&C92&CHAR(10)&"Тел.: "&D92&CHAR(10)&"Адрес: "&E92&CHAR(10)&"№ заказа: "&I92&CHAR(10)&"https://yandex.ru/maps/?text="&REPLACE(F92,SEARCH(",",F92),2,"%2C")&CHAR(10)&"https://maps.google.com/?daddr="&REPLACE(F92,SEARCH(",",F92),2,"%2C")&CHAR(10)&"К оплате: "&"**"&H92&CHAR(10)&"**"&"----------------------------------------------------------" -> #N/A
A93: 8 | B93: 45458 | C93: Вадим | D93: =VLOOKUP($C93,ТабКлиенты[[#All],[name]:[phone]],MATCH(D$1,ТабКлиенты[#Headers],0)-1,0) -> #N/A | E93: =VLOOKUP($C93,ТабАдрес[[#All],[Клиент]:[gps]],MATCH(E$1,ТабКлиенты[#Headers],0)-4,0) -> #N/A | F93: =VLOOKUP($C93,ТабАдрес[[#All],[Клиент]:[gps]],MATCH(F$1,ТабКлиенты[#Headers],0)-4,0) -> #N/A | H93: 852 | I93: 130 | K93: =A93&". "&C93&CHAR(10)&"Тел.: "&D93&CHAR(10)&"Адрес: "&E93&CHAR(10)&"№ заказа: "&I93&CHAR(10)&"https://yandex.ru/maps/?text="&REPLACE(F93,SEARCH(",",F93),2,"%2C")&CHAR(10)&"https://maps.google.com/?daddr="&REPLACE(F93,SEARCH(",",F93),2,"%2C")&CHAR(10)&"К оплате: "&"**"&H93&CHAR(10)&"**"&"----------------------------------------------------------" -> #N/A
A94: 9 | B94: 45458 | C94: Максим телевизор | D94: =VLOOKUP($C94,ТабКлиенты[[#All],[name]:[phone]],MATCH(D$1,ТабКлиенты[#Headers],0)-1,0) -> #N/A | E94: =VLOOKUP($C94,ТабАдрес[[#All],[Клиент]:[gps]],MATCH(E$1,ТабКлиенты[#Headers],0)-4,0) -> #N/A | F94: =VLOOKUP($C94,ТабАдрес[[#All],[Клиент]:[gps]],MATCH(F$1,ТабКлиенты[#Headers],0)-4,0) -> #N/A | H94: 0 | I94: 129 | K94: =A94&". "&C94&CHAR(10)&"Тел.: "&D94&CHAR(10)&"Адрес: "&E94&CHAR(10)&"№ заказа: "&I94&CHAR(10)&"https://yandex.ru/maps/?text="&REPLACE(F94,SEARCH(",",F94),2,"%2C")&CHAR(10)&"https://maps.google.com/?daddr="&REPLACE(F94,SEARCH(",",F94),2,"%2C")&CHAR(10)&"К оплате: "&"**"&H94&CHAR(10)&"**"&"----------------------------------------------------------" -> #N/A
A95: 10 | B95: 45458 | C95: Александр Каскад | D95: =VLOOKUP($C95,ТабКлиенты[[#All],[name]:[phone]],MATCH(D$1,ТабКлиенты[#Headers],0)-1,0) -> #N/A | E95: =VLOOKUP($C95,ТабАдрес[[#All],[Клиент]:[gps]],MATCH(E$1,ТабКлиенты[#Headers],0)-4,0) -> #N/A | F95: =VLOOKUP($C95,ТабАдрес[[#All],[Клиент]:[gps]],MATCH(F$1,ТабКлиенты[#Headers],0)-4,0) -> #N/A | H95: 2000 | I95: 43 121 128 | K95: =A95&". "&C95&CHAR(10)&"Тел.: "&D95&CHAR(10)&"Адрес: "&E95&CHAR(10)&"№ заказа: "&I95&CHAR(10)&"https://yandex.ru/maps/?text="&REPLACE(F95,SEARCH(",",F95),2,"%2C")&CHAR(10)&"https://maps.google.com/?daddr="&REPLACE(F95,SEARCH(",",F95),2,"%2C")&CHAR(10)&"К оплате: "&"**"&H95&CHAR(10)&"**"&"----------------------------------------------------------" -> #N/A
A96: 1 | B96: 45465 | C96: Юля Ларисына | D96: =VLOOKUP($C96,ТабКлиенты[[#All],[name]:[phone]],MATCH(D$1,ТабКлиенты[#Headers],0)-1,0) -> #N/A | E96: =VLOOKUP($C96,ТабАдрес[[#All],[Клиент]:[gps]],MATCH(E$1,ТабКлиенты[#Headers],0)-4,0) -> #N/A | F96: =VLOOKUP($C96,ТабАдрес[[#All],[Клиент]:[gps]],MATCH(F$1,ТабКлиенты[#Headers],0)-4,0) -> #N/A | H96: 0 | I96: 137 | K96: =A96&". "&C96&CHAR(10)&"Тел.: "&D96&CHAR(10)&"Адрес: "&E96&CHAR(10)&"№ заказа: "&I96&CHAR(10)&"https://yandex.ru/maps/?text="&REPLACE(F96,SEARCH(",",F96),2,"%2C")&CHAR(10)&"https://maps.google.com/?daddr="&REPLACE(F96,SEARCH(",",F96),2,"%2C")&CHAR(10)&"К оплате: "&"**"&H96&CHAR(10)&"**"&"----------------------------------------------------------" -> #N/A
A97: 2 | B97: 45465 | C97: Александр электростанция | D97: =VLOOKUP($C97,ТабКлиенты[[#All],[name]:[phone]],MATCH(D$1,ТабКлиенты[#Headers],0)-1,0) -> #N/A | E97: =VLOOKUP($C97,ТабАдрес[[#All],[Клиент]:[gps]],MATCH(E$1,ТабКлиенты[#Headers],0)-4,0) -> #N/A | F97: =VLOOKUP($C97,ТабАдрес[[#All],[Клиент]:[gps]],MATCH(F$1,ТабКлиенты[#Headers],0)-4,0) -> #N/A | H97: 29077 | I97: 115 136 | K97: =A97&". "&C97&CHAR(10)&"Тел.: "&D97&CHAR(10)&"Адрес: "&E97&CHAR(10)&"№ заказа: "&I97&CHAR(10)&"https://yandex.ru/maps/?text="&REPLACE(F97,SEARCH(",",F97),2,"%2C")&CHAR(10)&"https://maps.google.com/?daddr="&REPLACE(F97,SEARCH(",",F97),2,"%2C")&CHAR(10)&"К оплате: "&"**"&H97&CHAR(10)&"**"&"----------------------------------------------------------" -> #N/A
A98: 3 | B98: 45465 | C98: Игорь свалка | D98: =VLOOKUP($C98,ТабКлиенты[[#All],[name]:[phone]],MATCH(D$1,ТабКлиенты[#Headers],0)-1,0) -> #N/A | E98: =VLOOKUP($C98,ТабАдрес[[#All],[Клиент]:[gps]],MATCH(E$1,ТабКлиенты[#Headers],0)-4,0) -> #N/A | F98: =VLOOKUP($C98,ТабАдрес[[#All],[Клиент]:[gps]],MATCH(F$1,ТабКлиенты[#Headers],0)-4,0) -> #N/A | H98: 20600 | I98: Витамины | K98: =A98&". "&C98&CHAR(10)&"Тел.: "&D98&CHAR(10)&"Адрес: "&E98&CHAR(10)&"№ заказа: "&I98&CHAR(10)&"https://yandex.ru/maps/?text="&REPLACE(F98,SEARCH(",",F98),2,"%2C")&CHAR(10)&"https://maps.google.com/?daddr="&REPLACE(F98,SEARCH(",",F98),2,"%2C")&CHAR(10)&"К оплате: "&"**"&H98&CHAR(10)&"**"&"----------------------------------------------------------" -> #N/A
A99: 4 | B99: 45465 | C99: Геннадий Генерал | D99: =VLOOKUP($C99,ТабКлиенты[[#All],[name]:[phone]],MATCH(D$1,ТабКлиенты[#Headers],0)-1,0) -> #N/A | E99: =VLOOKUP($C99,ТабАдрес[[#All],[Клиент]:[gps]],MATCH(E$1,ТабКлиенты[#Headers],0)-4,0) -> #N/A | F99: =VLOOKUP($C99,ТабАдрес[[#All],[Клиент]:[gps]],MATCH(F$1,ТабКлиенты[#Headers],0)-4,0) -> #N/A | H99: 0 | I99: 141 | K99: =A99&". "&C99&CHAR(10)&"Тел.: "&D99&CHAR(10)&"Адрес: "&E99&CHAR(10)&"№ заказа: "&I99&CHAR(10)&"https://yandex.ru/maps/?text="&REPLACE(F99,SEARCH(",",F99),2,"%2C")&CHAR(10)&"https://maps.google.com/?daddr="&REPLACE(F99,SEARCH(",",F99),2,"%2C")&CHAR(10)&"К оплате: "&"**"&H99&CHAR(10)&"**"&"----------------------------------------------------------" -> #N/A
A100: 5 | B100: 45465 | C100: Дмитрий Виноградная 29 | D100: =VLOOKUP($C100,ТабКлиенты[[#All],[name]:[phone]],MATCH(D$1,ТабКлиенты[#Headers],0)-1,0) -> #N/A | E100: =VLOOKUP($C100,ТабАдрес[[#All],[Клиент]:[gps]],MATCH(E$1,ТабКлиенты[#Headers],0)-4,0) -> #N/A | F100: =VLOOKUP($C100,ТабАдрес[[#All],[Клиент]:[gps]],MATCH(F$1,ТабКлиенты[#Headers],0)-4,0) -> #N/A | H100: 0 | I100: 126 | K100: =A100&". "&C100&CHAR(10)&"Тел.: "&D100&CHAR(10)&"Адрес: "&E100&CHAR(10)&"№ заказа: "&I100&CHAR(10)&"https://yandex.ru/maps/?text="&REPLACE(F100,SEARCH(",",F100),2,"%2C")&CHAR(10)&"https://maps.google.com/?daddr="&REPLACE(F100,SEARCH(",",F100),2,"%2C")&CHAR(10)&"К оплате: "&"**"&H100&CHAR(10)&"**"&"----------------------------------------------------------" -> #N/A
...

Sheet Clients
A1: _id | B1: name | C1: percent | D1: accountManager | E1: __v | F1: createdAt | G1: updatedAt | H1: phone | I1: address | J1: gps | K1: contactPerson | L1: contactPersonPhone | M1: description | N1: email
A2: 68e24e5bb38906efee33845c | B2: Александр Космос | C2: 0 | D2: 68d297f82c15702607657e22 | E2: 0 | F2: 2025-10-05T10:54:19.203Z | G2: 2025-10-05T10:54:19.203Z | H2: +7 949 704-99-29 | I2: Б-р Шевченко 317 Грация | J2: 47.117993, 37.516302
A3: 68d297ff2c15702607657f13 | B3: Александр Радин | C3: 15 | D3: 68d297f82c15702607657e22 | E3: 0 | H3: +79497277100 | I3: Артема 132 | J3: 47.1085, 37.5599
A4: 68d297ff2c15702607657f2b | B4: Александра 50 лет СССР | C4: 15 | D4: 68d297f82c15702607657e22 | E4: 0 | H4: +79497167877 | I4: 50 лет СССР 20 кв 92 | J4: 47.1112, 37.5224
A5: 68f781c7adc63884d7a59e1c | B5: Алена Бахчик | C5: 0 | D5: 68d297f82c15702607657e22 | E5: 0 | F5: 2025-10-21T12:51:19.121Z | G5: 2025-10-21T12:51:19.121Z | H5: +79498485492 | M5: Бахчиванджи
A6: 68d298052c1570260765804f | B6: Алена Грация | C6: 15 | D6: 68d297f82c15702607657e22 | E6: 0 | H6: +79497049936 | I6: Шевченко 317 Грация | J6: 47.1179, 37.5163
A7: 68f783a8adc63884d7a59eb1 | B7: Алёна Чайка | C7: 0 | D7: 68d297f82c15702607657e22 | E7: 0 | F7: 2025-10-21T12:59:20.822Z | G7: 2025-10-21T12:59:20.823Z | H7: +79497200824
A8: 692ab7e17ab5058720faf6eb | B8: Алёна Шевченко, 295 | C8: 0 | D8: 68d297f82c15702607657e22 | E8: 0 | F8: 2025-11-29T09:07:45.082Z | G8: 2025-11-29T09:07:45.083Z | H8: +79498014741
A9: 6922f1c27ab5058720faed8a | B9: Алина стоматология Лекарь | C9: 0 | D9: 68d297f82c15702607657e22 | E9: 0 | F9: 2025-11-23T11:36:34.899Z | G9: 2025-11-23T11:36:34.900Z | H9: +79497141954
A10: 691c38ab7ab5058720fadf5a | B10: Анна Володарское шоссе | C10: 0 | D10: 68d297f82c15702607657e22 | E10: 0 | F10: 2025-11-18T09:13:15.507Z | G10: 2025-11-18T09:13:15.508Z | H10: +7 949 437 30 37
A11: 68d298002c15702607657f39 | B11: Анна соседка | C11: 15 | D11: 68d297f82c15702607657e22 | E11: 0 | H11: +79497105263 | I11: Казанцева 31 | J11: 47.1070, 37.5475
A12: 68f8bc256d77f5c8a72f9a14 | B12: Антонина Космос | C12: 0 | D12: 68d297f82c15702607657e22 | E12: 0 | F12: 2025-10-22T11:12:37.496Z | G12: 2025-10-22T11:12:37.496Z | H12: +7949
A13: 68d298012c15702607657f65 | B13: Аня Мирный | C13: 15 | D13: 68d297f82c15702607657e22 | E13: 0 | F13: 2025-10-22T10:55:32.942Z | G13: 2025-10-22T10:55:32.942Z | H13: +79497115237 | I13: пер Станционный 8 | J13: 47.1640, 37.5780
A14: 68d298012c15702607657f73 | B14: Валентина | C14: 15 | D14: 68d297f82c15702607657e22 | E14: 0 | H14: +79497095480 | I14: Трамвайный 10 | J14: 47.1044, 37.5233
A15: 68f8ba0d6d77f5c8a72f99d6 | B15: Валентина Кострова | C15: 0 | D15: 68d297f82c15702607657e22 | E15: 0 | F15: 2025-10-22T11:03:41.772Z | G15: 2025-10-22T11:03:41.772Z | H15: +79493008466
A16: 68d298032c15702607657fe1 | B16: Валентина Сычева | C16: 15 | D16: 68d297f82c15702607657e22 | E16: 0 | H16: +79497388231 | I16: Леваневского 58 | J16: 47.1007, 37.5310
A17: 68d298002c15702607657f33 | B17: Валерий СТО ОРИОН | C17: 15 | D17: 68d297f82c15702607657e22 | E17: 0 | H17: +79497398357 | I17: Макара Мазая 41
A18: 68d298022c15702607657fa3 | B18: Валерий Фагот | C18: 15 | D18: 68d297f82c15702607657e22 | E18: 0 | H18: +79497196221 | I18: Краснофлотская 132 | J18: 47.0917, 37.4968
A19: 68d298022c15702607657fb9 | B19: Вера Надеждына | C19: 15 | D19: 68d297f82c15702607657e22 | E19: 0 | H19: +79497169849 | I19: 17 рынок Грация | J19: 47.1122, 37.5146
A20: 68e253ebb38906efee338504 | B20: Вероника стоматолог | C20: 0 | D20: 68d297f82c15702607657e22 | E20: 0 | F20: 2025-10-05T11:18:03.087Z | G20: 2025-10-05T11:18:03.088Z | H20: +7 949 561-96-56 | I20: Пр. Ленина, 104 стоматология Лекарь | J20: 47.098132, 37.522480
A21: 68e649edd41346b9e28f3d38 | B21: Виктория | C21: 0 | D21: 68d297f82c15702607657e22 | E21: 0 | F21: 2025-10-08T11:24:29.036Z | G21: 2025-10-08T11:24:29.036Z | M21: Берберин, встречались на Башне
A22: 6904df630024359e23617ad7 | B22: Виктория Бахчиванджи | C22: 0 | D22: 68d297f82c15702607657e22 | E22: 0 | F22: 2025-10-31T16:10:11.618Z | G22: 2025-10-31T16:10:11.618Z | H22: +79490371889
A23: 691c42717ab5058720fadfc1 | B23: Виктория Башня/Энгельса | C23: 0 | D23: 68d297f82c15702607657e22 | E23: 0 | F23: 2025-11-18T09:54:57.525Z | G23: 2025-11-18T09:54:57.525Z | H23: +79497220585
A24: 68d298012c15702607657f89 | B24: Виктория БСМП | C24: 15 | D24: 68d297f82c15702607657e22 | E24: 0 | F24: 2025-10-22T11:13:49.727Z | G24: 2025-10-22T11:13:49.727Z | H24: +79497057045 | I24: Бахмутская 20 | J24: 47.1157, 37.5479
A25: 68d298032c15702607657fd3 | B25: Виктория Порт Сити | C25: 15 | D25: 68d297f82c15702607657e22 | E25: 0 | H25: +79497271852 | I25: Запорожское шоссе 2 | J25: 47.1176, 37.5083
A26: 68d298052c1570260765804d | B26: Виктория Страховка | C26: 15 | D26: 68d297f82c15702607657e22 | E26: 0 | H26: +79497163227 | I26: Артема 44 | J26: 47.0943, 37.5487
A27: 68d298032c15702607657fe3 | B27: Виктория Урицкого 93а | C27: 15 | D27: 68d297f82c15702607657e22 | E27: 0 | H27: +79497309448 | I27: Урицкого 93а | J27: 47.1238, 37.5116
A28: 68fca01e0024359e23617284 | B28: Виталий Тополиная, 12А | C28: 0 | D28: 68d297f82c15702607657e22 | E28: 0 | F28: 2025-10-25T10:02:06.347Z | G28: 2025-10-25T10:02:06.347Z | H28: +79494997775
A29: 68e5ff5fd41346b9e28f3d04 | B29: Виталий Черемушки | C29: 0 | D29: 68d297f82c15702607657e22 | E29: 0 | F29: 2025-10-08T06:06:23.114Z | G29: 2025-10-08T06:06:23.114Z | H29: +79498311537 | I29: Цибулько, 37 | K29: Виктория | L29: +7 949 831-15-38
A30: 68d298042c1570260765800b | B30: Власта консалтинг | C30: 15 | D30: 68d297f82c15702607657e22 | E30: 0 | H30: +79497377568 | I30: Металлургов 33 | J30: 47.0952, 37.5438
A31: 68d297fe2c15702607657ee9 | B31: Горжовская Ульяна NSP | C31: 15 | D31: 68d297f82c15702607657e22 | E31: 0
A32: 68d298002c15702607657f35 | B32: Даша Калифорния | C32: 15 | D32: 68d297f82c15702607657e22 | E32: 0 | H32: +79496248226 | I32: Шевченко 274 | J32: 47.1149, 37.5127
A33: 68ecf0d5a46150fa4106fcf4 | B33: Евгения | C33: 0 | D33: 68d297f82c15702607657e22 | E33: 0 | F33: 2025-10-13T12:30:13.302Z | G33: 2025-10-13T12:30:13.303Z | H33: +7 (949) 857-32-40 | I33: Металлургов 127 А | J33: 47.111534, 37.558841
A34: 68d298022c15702607657f93 | B34: Евгения Охотник | C34: 15 | D34: 68d297f82c15702607657e22 | E34: 0 | H34: +79497263506 | I34: Аэродромная 4 | J34: 47.1087, 37.5254
A35: 68d298052c15702607658033 | B35: Екатерина Металлургов 129 | C35: 15 | D35: 68d297f82c15702607657e22 | E35: 0 | H35: +79495256416 | I35: Металлургов 129 | J35: 47.1123, 37.5582
A36: 68d298022c15702607657fa5 | B36: Елена Индол | C36: 15 | D36: 68d297f82c15702607657e22 | E36: 0 | H36: +79497177018 | I36: Троицка 75, Рынок Юмовила | J36: 47.1121, 37.5156
A37: 692943757ab5058720faf3b2 | B37: Елена казначейство | C37: 0 | D37: 68d297f82c15702607657e22 | E37: 0 | F37: 2025-11-28T06:38:45.428Z | G37: 2025-11-28T06:38:45.429Z | H37: +79495149095
A38: 68d298062c15702607658057 | B38: Елена Ленина 87 | C38: 15 | D38: 68d297f82c15702607657e22 | E38: 0 | H38: +79495524078 | I38: Ленина 87 | J38: 47.0980, 37.5374
A39: 68d297fe2c15702607657ef3 | B39: Елена пер. Фруктовый | C39: 10 | D39: 68d297f82c15702607657e22 | E39: 0 | F39: 2025-10-13T13:03:52.574Z | G39: 2025-10-13T13:03:52.574Z | H39: +79497190408 | I39: Проектная 10 | J39: 47.1281, 37.5732
A40: 68d298032c15702607657fcf | B40: Елена сахарный диабет | C40: 15 | D40: 68d297f82c15702607657e22 | E40: 0 | F40: 2025-10-05T08:15:51.941Z | G40: 2025-10-05T08:15:51.941Z | H40: +79497183446 | I40: Металлургов 199 | J40: 47.1286, 37.5670
A41: 68d297fb2c15702607657e53 | B41: Елена Строителей, 35 | D41: 68d297f82c15702607657e22 | E41: 0 | F41: 2025-11-08T10:49:43.101Z | G41: 2025-11-08T10:49:43.101Z | K41: Ольга сестра | L41: +79497251168
A42: 68d298022c15702607657fa7 | B42: Елена Трансфер | C42: 15 | D42: 68d297f82c15702607657e22 | E42: 0 | H42: +79497288148 | I42: Шевченко 317 Грация | J42: 47.1179, 37.5163
A43: 68d298012c15702607657f77 | B43: Елена Шевченко 217 | C43: 15 | D43: 68d297f82c15702607657e22 | E43: 0 | H43: +79496334882 | I43: Шевченко 217 | J43: 47.1130, 37.5406
A44: 68d298042c15702607657ffd | B44: Елизавета Водоканал | C44: 15 | D44: 68d297f82c15702607657e22 | E44: 0 | I44: Варганова 7 | J44: 47.0989, 37.5429
A45: 68d298022c15702607657f9b | B45: Жанна Наташина | C45: 15 | D45: 68d297f82c15702607657e22 | E45: 0 | H45: +79495529124 | I45: Зелинского 98а | J45: 47.1022, 37.5165
A46: 68d298042c15702607658023 | B46: Ирина Зелинского 106а | C46: 15 | D46: 68d297f82c15702607657e22 | E46: 0 | H46: +79496433686 | I46: Зелинского 106а | J46: 47.1059, 37.5155
A47: 692dcde67ab5058720faf9aa | B47: Конечный потребитель | C47: 0 | D47: 68d297f82c15702607657e22 | E47: 0 | F47: 2025-12-01T17:18:30.259Z | G47: 2025-12-01T17:18:30.260Z
A48: 68d298002c15702607657f3b | B48: Константин СТО Оптима | C48: 15 | D48: 68d297f82c15702607657e22 | E48: 0 | H48: +79496340956 | I48: Макара Мазая 41 | J48: 47.1361, 37.5817
A49: 68d298042c15702607657ff5 | B49: Косарева Елена | C49: 15 | D49: 68d297f82c15702607657e22 | E49: 0
A50: 68d298052c15702607658039 | B50: Ксения Краснофлотская | C50: 15 | D50: 68d297f82c15702607657e22 | E50: 0 | H50: +79497183952 | I50: Краснофлотская 167 | J50: 47.0910, 37.4981
A51: 68d298002c15702607657f5d | B51: Лакарова Татьяна | C51: 15 | D51: 68d297f82c15702607657e22 | E51: 0 | H51: +79497089129 | I51: Энгельса 28А | J51: 47.0964, 37.5459
A52: 68d298052c15702607658027 | B52: Лариса Западный | C52: 15 | D52: 68d297f82c15702607657e22 | E52: 0 | F52: 2025-11-08T15:51:17.212Z | G52: 2025-11-08T15:51:17.212Z | H52: +79497185141 | I52: Урицкого, 118/16 | J52: 47.1223, 37.5125
A53: 68d298012c15702607657f87 | B53: Лариса Терраспорт | C53: 15 | D53: 68d297f82c15702607657e22 | E53: 0 | H53: +79497054056 | I53: пер. Новгородский 41 | J53: 47.1100, 37.5242
A54: 692981467ab5058720faf45c | B54: Лев | C54: 0 | D54: 68d297f82c15702607657e22 | E54: 0 | F54: 2025-11-28T11:02:30.544Z | G54: 2025-11-28T11:02:30.544Z | H54: +79495251620
A55: 68d298002c15702607657f41 | B55: Лида корма | C55: 15 | D55: 68d297f82c15702607657e22 | E55: 0 | H55: +79497081831 | I55: Шевченко 289А | J55: 47.1168, 37.5229
A56: 68d298012c15702607657f7b | B56: Лидия Живописная | C56: 15 | D56: 68d297f82c15702607657e22 | E56: 0 | F56: 2025-10-05T08:04:11.563Z | G56: 2025-10-05T08:04:11.563Z | H56: +79497097873 | I56: Живописная 7 зеленая крыша | J56: 47.1237, 37.5313
A57: 68d298052c15702607658051 | B57: Лилия Леси Украинки | C57: 15 | D57: 68d297f82c15702607657e22 | E57: 0 | H57: +79497108197 | I57: Леси Украинки 24 | J57: 47.1035, 37.5324
A58: 68d298042c1570260765800d | B58: Лиля Эдельвейс | C58: 15 | D58: 68d297f82c15702607657e22 | E58: 0 | H58: +79497248825 | I58: Писарева 28 | J58: 47.1067, 37.5486
A59: 68d298062c15702607658059 | B59: Любовь 17 | C59: 15 | D59: 68d297f82c15702607657e22 | E59: 0 | H59: +79493850065 | I59: Рынок Юмовила | J59: 47.1143, 37.5157
A60: 68d298002c15702607657f53 | B60: Любовь Виталий | C60: 15 | D60: 68d297f82c15702607657e22 | E60: 0 | H60: +79497386112 | I60: Шевченко 325 | J60: 47.1193, 37.5172
A61: 68d298052c15702607658049 | B61: Любовь Металлургов 158 | C61: 15 | D61: 68d297f82c15702607657e22 | E61: 0 | H61: +79497379017 | I61: Металлургов 158 | J61: 47.1266, 37.5631
A62: 68d298022c15702607657f9f | B62: Людмила Кордицепс | C62: 15 | D62: 68d297f82c15702607657e22 | E62: 0 | H62: +79497095528 | I62: 9 Авиадивизии 28 | J62: 47.1235, 37.5191
A63: 68d298052c1570260765802b | B63: Людмила Федоровна | C63: 15 | D63: 68d297f82c15702607657e22 | E63: 0 | H63: +79496243970 | I63: Урицкого 104 подъезд 2 кв. 43 | J63: 47.1212, 37.5174
A64: 68d297ff2c15702607657f11 | B64: Людмила Эдельвейс | C64: 15 | D64: 68d297f82c15702607657e22 | E64: 0 | H64: +79496019237 | I64: Металлургов 92 | J64: 47.1053, 37.5483
A65: 6914b18c7ab5058720fada79 | B65: Маргарита Мангуш | C65: 0 | D65: 68d297f82c15702607657e22 | E65: 0 | F65: 2025-11-12T16:10:52.019Z | G65: 2025-11-12T16:10:52.019Z | H65: +79497398225
A66: 68d298052c1570260765804b | B66: Марина 50 Лет СССР 16 | C66: 15 | D66: 68d297f82c15702607657e22 | E66: 0 | H66: +79495600470 | I66: 50 Лет СССР 16 | J66: 47.1106, 37.5233
A67: 68ebb3595c3f2e12447f6566 | B67: Михаил Икра Кофе | C67: 0 | D67: 68d297f82c15702607657e22 | E67: 0 | F67: 2025-10-12T13:55:37.595Z | G67: 2025-10-12T13:55:37.595Z | H67: +79497241385
A68: 691ef8c07ab5058720faea1f | B68: Надежда Sumbucol | C68: 0 | D68: 68d297f82c15702607657e22 | E68: 0 | F68: 2025-11-20T11:17:20.464Z | G68: 2025-11-20T11:17:20.464Z | H68: +79497068957
A69: 68d298002c15702607657f47 | B69: Надежда Витамины | C69: 15 | D69: 68d297f82c15702607657e22 | E69: 0 | F69: 2025-10-21T12:45:07.559Z | G69: 2025-10-21T12:45:07.559Z | H69: +79497169864 | I69: пер. Ейский 9 | J69: 47.0898, 37.5062
A70: 68d298002c15702607657f2d | B70: Наталья 60 лет СССР | C70: 15 | D70: 68d297f82c15702607657e22 | E70: 0 | H70: +79497094719 | I70: 60 лет СССР 2Б | J70: 47.1178, 37.5121
A71: 68d297ff2c15702607657f17 | B71: Наталья Азовстальская | C71: 15 | D71: 68d297f82c15702607657e22 | E71: 0 | H71: +79497246366 | I71: Азовстальская 91 подъезд 1 | J71: 47.1008, 37.6529
A72: 691847157ab5058720fadcc7 | B72: Наталья Балабан | C72: 0 | D72: 68d297f82c15702607657e22 | E72: 0 | F72: 2025-11-15T09:25:41.083Z | G72: 2025-11-15T09:25:41.083Z | K72: Муж | L72: +79497176052
A73: 68d297fe2c15702607657ef7 | B73: Наталья Вельвет | C73: 15 | D73: 68d297f82c15702607657e22 | E73: 0 | F73: 2025-10-14T14:20:24.188Z | G73: 2025-10-14T14:20:24.188Z | H73: +79497385016 | I73: Шевченко 285А | J73: 47.1169, 37.5258
A74: 68d298022c15702607657f91 | B74: Наталья Дерматология | C74: 15 | D74: 68d297f82c15702607657e22 | E74: 0 | F74: 2025-10-05T08:07:04.559Z | G74: 2025-10-05T08:07:04.559Z | H74: +79497083587 | I74: Свободы 7 | J74: 47.1184, 37.5442
A75: 68d297ff2c15702607657f23 | B75: Наталья Зелинского | C75: 15 | D75: 68d297f82c15702607657e22 | E75: 0 | H75: +79497428404 | I75: Зелинского 94 | J75: 47.1008, 37.5167
A76: 68ed1a0aa46150fa4106fd24 | B76: Наталья магазин | C76: 0 | D76: 68d297f82c15702607657e22 | E76: 0 | F76: 2025-10-13T15:26:02.461Z | G76: 2025-10-13T15:26:02.461Z | H76: +79497094719 | I76: Апатова, 125 | M76: Магазин чёрный
A77: 68d298012c15702607657f83 | B77: Наталья магазин (Удалить) | C77: 15 | D77: 68d297f82c15702607657e22 | E77: 0 | F77: 2025-10-21T17:11:22.021Z | G77: 2025-10-21T17:11:22.021Z | H77: 79497094719 | I77: Грушевского 2б | J77: 47.1178, 37.5121
A78: 68d298022c15702607657fa1 | B78: Наталья Сергеевна | C78: 15 | D78: 68d297f82c15702607657e22 | E78: 0 | H78: +79497369642 | I78: Ленина 63/2 | J78: 47.0971, 37.5481
A79: 68d298042c15702607658007 | B79: Наталья Шевченко | C79: 15 | D79: 68d297f82c15702607657e22 | E79: 0 | H79: +79497399662 | I79: Шевченко 295 подъезд 3 | J79: 47.1179, 37.5217
A80: 68d297ff2c15702607657f1b | B80: Наталья Школа 53 | C80: 15 | D80: 68d297f82c15702607657e22 | E80: 0 | H80: +79497106271 | I80: Урицкого 77 | J80: 47.1228, 37.5167
A81: 68d298012c15702607657f63 | B81: Оксана 17 Цветы | C81: 15 | D81: 68d297f82c15702607657e22 | E81: 0 | F81: 2025-10-05T08:04:36.584Z | G81: 2025-10-05T08:04:36.584Z | I81: Троицкая 46 | J81: 47.1119, 37.5147
A82: 68d298052c1570260765802d | B82: Оксана молокозавод | C82: 15 | D82: 68d297f82c15702607657e22 | E82: 0 | H82: +79497135589 | I82: Бахмутская 20 | J82: 47.1164, 37.5459
A83: 68d298042c15702607657ffb | B83: Оксана Моцная | C83: 15 | D83: 68d297f82c15702607657e22 | E83: 0 | H83: +79495872741 | I83: Гранитная 148 подъезд 2, кв. 68 | J83: 47.1253, 37.5129
A84: 68d298052c15702607658037 | B84: Оксана Черноморская | C84: 15 | D84: 68d297f82c15702607657e22 | E84: 0 | H84: +79497078921 | I84: Черноморская 17 | J84: 47.0767, 37.5101
A85: 68d298042c15702607658019 | B85: Оксана Шевченко 240 | C85: 15 | D85: 68d297f82c15702607657e22 | E85: 0 | H85: +79497168896 | I85: Шевченко 240 подъезд 3 | J85: 47.1153, 37.5222
A86: 68f8bab16d77f5c8a72f99f0 | B86: Олег Алешин | C86: 0 | D86: 68d297f82c15702607657e22 | E86: 0 | F86: 2025-10-22T11:06:25.630Z | G86: 2025-10-22T11:06:25.630Z | H86: +79497149436 | M86: Анестезиолог
A87: 68e25c3bb38906efee33859d | B87: Олеся | C87: 0 | D87: 68d297f82c15702607657e22 | E87: 0 | F87: 2025-10-05T11:53:31.918Z | G87: 2025-10-05T11:53:31.918Z | H87: +79497421716 | I87: Урицкого, 107, подъезд 2 | J87: 47.124663, 37.508768
A88: 68d298042c15702607657ff3 | B88: Олеся Пугачева 23 | C88: 15 | D88: 68d297f82c15702607657e22 | E88: 0 | H88: +79497195898 | I88: Пугачева 23 | J88: 47.1190, 37.5327
A89: 68d298032c15702607657fd7 | B89: Ольга ЖД больница | C89: 15 | D89: 68d297f82c15702607657e22 | E89: 0 | H89: +79497178192 | I89: Новороссийская 28, ЖД Больница | J89: 47.0718, 37.4881
A90: 691885527ab5058720fadd0d | B90: Ольга Лавицкого, 17 | C90: 0 | D90: 68d297f82c15702607657e22 | E90: 0 | F90: 2025-11-15T13:51:14.587Z | G90: 2025-11-15T13:51:14.587Z | H90: +79497320091
A91: 68d298032c15702607657fd1 | B91: Ольга Мелованова | C91: 15 | D91: 68d297f82c15702607657e22 | E91: 0 | H91: +79490023562 | I91: Ленина 46/54 | J91: 47.0947, 37.5488
A92: 68e7a7f684f8b0568963190a | B92: Ольга Электромех. Колледж | C92: 0 | D92: 68d297f82c15702607657e22 | E92: 0 | F92: 2025-10-09T12:17:58.353Z | G92: 2025-10-09T12:17:58.353Z | H92: +79497093373 | I92: Зелинского, 11 | J92: 47.089456, 37.516851
A93: 68f78107adc63884d7a59e06 | B93: Полина Цветы | C93: 0 | D93: 68d297f82c15702607657e22 | E93: 0 | F93: 2025-10-21T12:48:07.833Z | G93: 2025-10-21T12:48:07.834Z | H93: +79497113670 | M93: Рынок Космос Цветы
A94: 68f8b99a6d77f5c8a72f99b1 | B94: Римма Омск | C94: 0 | D94: 68d297f82c15702607657e22 | E94: 0 | F94: 2025-10-22T11:01:46.430Z | G94: 2025-10-22T11:01:46.430Z | H94: +79088017768
A95: 68d297fe2c15702607657edd | B95: Руденко Юля | C95: 10 | D95: 68d297f82c15702607657e22 | E95: 0 | F95: 2025-10-05T07:51:16.285Z | G95: 2025-10-05T07:51:16.285Z | H95: +79497243297 | I95: Мариуполь, Митрополитская, 60 | J95: 47.0999, 37.5500 | K95: Руденко Юля | L95: 9497243297
A96: 68e4a9f8d41346b9e28f3a3a | B96: Светлана АТБ | C96: 0 | D96: 68d297f82c15702607657e22 | E96: 0 | F96: 2025-10-07T05:49:44.434Z | G96: 2025-10-07T05:49:44.434Z | H96: +79497318244 | I96: АТБ | J96: 47.133497, 37.566194
A97: 6901c6690024359e2361753a | B97: Светлана ГАИ | C97: 0 | D97: 68d297f82c15702607657e22 | E97: 0 | F97: 2025-10-29T07:46:49.492Z | G97: 2025-10-29T07:46:49.493Z | H97: +79497274199
A98: 6910db1e7ab5058720fad84a | B98: Светлана Драмтеатр | C98: 0 | D98: 68d297f82c15702607657e22 | E98: 0 | F98: 2025-11-09T18:19:10.190Z | G98: 2025-11-09T18:19:10.190Z | H98: +79490040746
A99: 68f8bd366d77f5c8a72f9a8e | B99: Светлана Звенигородская | C99: 0 | D99: 68d297f82c15702607657e22 | E99: 0 | F99: 2025-10-22T11:17:10.244Z | G99: 2025-10-22T11:17:10.244Z | H99: +79497237097
A100: 6916cd907ab5058720fadb2f | B100: Светлана Ильинична Лиходед | C100: 0 | D100: 68d297f82c15702607657e22 | E100: 0 | F100: 2025-11-14T06:34:56.074Z | G100: 2025-11-14T06:34:56.075Z | H100: +7 949 710-40-83
...

Sheet Адреса
A1: Клиент | B1: _id | C1: main | D1: customerId | E1: address | F1: gps | G1: description | H1: __v
A2: =VLOOKUP(ТабАдрес[[#This Row],[customerId]],ТабКлиенты[[#All],[_id]:[name]],2,0) -> Людмила Эдельвейс | B2: 68ee7e5778a38b35c0162bbc | C2: true | D2: 68d297ff2c15702607657f11 | E2: Металлургов 92 | F2: 47.1053, 37.5483 | H2: 0
A3: =VLOOKUP(ТабАдрес[[#This Row],[customerId]],ТабКлиенты[[#All],[_id]:[name]],2,0) -> Наталья Вельвет | B3: 68ee7e5778a38b35c0162bbf | C3: true | D3: 68d297fe2c15702607657ef7 | E3: Шевченко 285А | F3: 47.1169, 37.5258 | H3: 0
A4: =VLOOKUP(ТабАдрес[[#This Row],[customerId]],ТабКлиенты[[#All],[_id]:[name]],2,0) -> Наталья Школа 53 | B4: 68ee7e5778a38b35c0162bc1 | C4: true | D4: 68d297ff2c15702607657f1b | E4: Урицкого 77 | F4: 47.1228, 37.5167 | H4: 0
A5: =VLOOKUP(ТабАдрес[[#This Row],[customerId]],ТабКлиенты[[#All],[_id]:[name]],2,0) -> Наталья Зелинского | B5: 68ee7e5778a38b35c0162bc3 | C5: true | D5: 68d297ff2c15702607657f23 | E5: Зелинского 94 | F5: 47.1008, 37.5167 | H5: 0
A6: =VLOOKUP(ТабАдрес[[#This Row],[customerId]],ТабКлиенты[[#All],[_id]:[name]],2,0) -> Татьяна Торговая 100 | B6: 68ee7e5778a38b35c0162bba | C6: true | D6: 68d297ff2c15702607657f09 | E6: Торговая 100 | F6: 47.1034, 37.5633 | G6: Духи | H6: 0
A7: =VLOOKUP(ТабАдрес[[#This Row],[customerId]],ТабКлиенты[[#All],[_id]:[name]],2,0) -> Александра 50 лет СССР | B7: 68ee7e5778a38b35c0162bc5 | C7: true | D7: 68d297ff2c15702607657f2b | E7: 50 лет СССР 20 кв 92 | F7: 47.1112, 37.5224 | H7: 0
A8: =VLOOKUP(ТабАдрес[[#This Row],[customerId]],ТабКлиенты[[#All],[_id]:[name]],2,0) -> Наталья 60 лет СССР | B8: 68ee7e5778a38b35c0162bc7 | C8: true | D8: 68d298002c15702607657f2d | E8: 60 лет СССР 2Б | F8: 47.1178, 37.5121 | H8: 0
A9: =VLOOKUP(ТабАдрес[[#This Row],[customerId]],ТабКлиенты[[#All],[_id]:[name]],2,0) -> Валерий СТО ОРИОН | B9: 68ee7e5778a38b35c0162bc9 | C9: true | D9: 68d298002c15702607657f33 | E9: Макара Мазая 41 | H9: 0
A10: =VLOOKUP(ТабАдрес[[#This Row],[customerId]],ТабКлиенты[[#All],[_id]:[name]],2,0) -> Анна соседка | B10: 68ee7e5778a38b35c0162bcb | C10: true | D10: 68d298002c15702607657f39 | E10: Казанцева 31 | F10: 47.1070, 37.5475 | H10: 0
A11: =VLOOKUP(ТабАдрес[[#This Row],[customerId]],ТабКлиенты[[#All],[_id]:[name]],2,0) -> Даша Калифорния | B11: 68ee7e5778a38b35c0162bcd | C11: true | D11: 68d298002c15702607657f35 | E11: Шевченко 274 | F11: 47.1149, 37.5127 | H11: 0
A12: =VLOOKUP(ТабАдрес[[#This Row],[customerId]],ТабКлиенты[[#All],[_id]:[name]],2,0) -> Константин СТО Оптима | B12: 68ee7e5778a38b35c0162bcf | C12: true | D12: 68d298002c15702607657f3b | E12: Макара Мазая 41 | F12: 47.1361, 37.5817 | H12: 0
A13: =VLOOKUP(ТабАдрес[[#This Row],[customerId]],ТабКлиенты[[#All],[_id]:[name]],2,0) -> Татьяна Олимпийская 65 | B13: 68ee7e5778a38b35c0162bd1 | C13: true | D13: 68d297ff2c15702607657f25 | E13: Олимпийская 65, кв 28 | F13: 47.1086, 37.6706 | H13: 0
A14: =VLOOKUP(ТабАдрес[[#This Row],[customerId]],ТабКлиенты[[#All],[_id]:[name]],2,0) -> Лида корма | B14: 68ee7e5778a38b35c0162bd3 | C14: true | D14: 68d298002c15702607657f41 | E14: Шевченко 289А | F14: 47.1168, 37.5229 | H14: 0
A15: =VLOOKUP(ТабАдрес[[#This Row],[customerId]],ТабКлиенты[[#All],[_id]:[name]],2,0) -> Татьяна Леонидовна | B15: 68ee7e5778a38b35c0162bdb | C15: true | D15: 68d298002c15702607657f5b | E15: Шевченко 270 | F15: 47.1157, 37.5138 | H15: 0
A16: =VLOOKUP(ТабАдрес[[#This Row],[customerId]],ТабКлиенты[[#All],[_id]:[name]],2,0) -> Лакарова Татьяна | B16: 68ee7e5778a38b35c0162bdd | C16: true | D16: 68d298002c15702607657f5d | E16: Энгельса 28А | F16: 47.0964, 37.5459 | H16: 0
A17: =VLOOKUP(ТабАдрес[[#This Row],[customerId]],ТабКлиенты[[#All],[_id]:[name]],2,0) -> Любовь Виталий | B17: 68ee7e5778a38b35c0162bd9 | C17: true | D17: 68d298002c15702607657f53 | E17: Шевченко 325 | F17: 47.1193, 37.5172 | H17: 0
A18: =VLOOKUP(ТабАдрес[[#This Row],[customerId]],ТабКлиенты[[#All],[_id]:[name]],2,0) -> Светлана Федоровна | B18: 68ee7e5778a38b35c0162be1 | C18: true | D18: 68d298012c15702607657f67 | E18: Шопена 92 | F18: 47.1582, 37.6032 | H18: 0
A19: =VLOOKUP(ТабАдрес[[#This Row],[customerId]],ТабКлиенты[[#All],[_id]:[name]],2,0) -> Александр Радин | B19: 68ee7e5778a38b35c0162be5 | C19: true | D19: 68d297ff2c15702607657f13 | E19: Артема 132 | F19: 47.1085, 37.5599 | H19: 0
A20: =VLOOKUP(ТабАдрес[[#This Row],[customerId]],ТабКлиенты[[#All],[_id]:[name]],2,0) -> Лариса Терраспорт | B20: 68ee7e5778a38b35c0162be7 | C20: true | D20: 68d298012c15702607657f87 | E20: пер. Новгородский 41 | F20: 47.1100, 37.5242 | H20: 0
A21: =VLOOKUP(ТабАдрес[[#This Row],[customerId]],ТабКлиенты[[#All],[_id]:[name]],2,0) -> Лидия Живописная | B21: 68ee7e5778a38b35c0162be9 | C21: true | D21: 68d298012c15702607657f7b | E21: Живописная 7 зеленая крыша | F21: 47.1237, 37.5313 | H21: 0
... A72: =VLOOKUP(ТабАдрес[[#This Row],[customerId]],ТабКлиенты[[#All],[_id]:[name]],2,0) -> Олеся | B72: 68ee7e5778a38b35c0162c5c | C72: true | D72: 68e25c3bb38906efee33859d | E72: Урицкого, 107, подъезд 2 | F72: 47.124663, 37.508768 | H72: 0
A73: =VLOOKUP(ТабАдрес[[#This Row],[customerId]],ТабКлиенты[[#All],[_id]:[name]],2,0) -> Виталий Черемушки | B73: 68ee7e5778a38b35c0162c5a | C73: true | D73: 68e5ff5fd41346b9e28f3d04 | E73: Цибулько, 37 | H73: 0
A74: =VLOOKUP(ТабАдрес[[#This Row],[customerId]],ТабКлиенты[[#All],[_id]:[name]],2,0) -> Ольга Электромех. Колледж | B74: 68ee7e5778a38b35c0162c5e | C74: true | D74: 68e7a7f684f8b0568963190a | E74: Зелинского, 11 | F74: 47.089456, 37.516851 | H74: 0
A75: =VLOOKUP(ТабАдрес[[#This Row],[customerId]],ТабКлиенты[[#All],[_id]:[name]],2,0) -> Олеся Пугачева 23 | B75: 68ee7e5778a38b35c0162c60 | C75: true | D75: 68d298042c15702607657ff3 | E75: Пугачева 23 | F75: 47.1190, 37.5327 | H75: 0
A76: =VLOOKUP(ТабАдрес[[#This Row],[customerId]],ТабКлиенты[[#All],[_id]:[name]],2,0) -> Евгения | B76: 68ee7e5778a38b35c0162c64 | C76: true | D76: 68ecf0d5a46150fa4106fcf4 | E76: Металлургов 127 А | F76: 47.111534, 37.558841 | H76: 0
A77: =VLOOKUP(ТабАдрес[[#This Row],[customerId]],ТабКлиенты[[#All],[_id]:[name]],2,0) -> Софи | B77: 68ee7e5778a38b35c0162c66 | C77: true | D77: 68e802f184f8b05689631b30 | E77: пр. Строителей, 125 Обжора | F77: 47.099672, 37.524508 | H77: 0
A78: =VLOOKUP(ТабАдрес[[#This Row],[customerId]],ТабКлиенты[[#All],[_id]:[name]],2,0) -> Татьяна Константинова | B78: 68ee7e5778a38b35c0162c6e | C78: true | D78: 68e7ad8c84f8b05689631a5e | E78: рынок Калифорния | F78: 47.105156, 37.539071 | H78: 0
A79: =VLOOKUP(ТабАдрес[[#This Row],[customerId]],ТабКлиенты[[#All],[_id]:[name]],2,0) -> Татьяна Куприна 13 | B79: 68ee7e5778a38b35c0162c6c | C79: true | D79: 68d298032c15702607657ff1 | E79: Куприна 13 | F79: 47.1026, 37.5111 | H79: 0
A80: =VLOOKUP(ТабАдрес[[#This Row],[customerId]],ТабКлиенты[[#All],[_id]:[name]],2,0) -> Валерий Фагот | B80: 68ee7e5778a38b35c0162bff | C80: true | D80: 68d298022c15702607657fa3 | E80: Краснофлотская 132 | F80: 47.0917, 37.4968 | H80: 0
A81: =VLOOKUP(ТабАдрес[[#This Row],[customerId]],ТабКлиенты[[#All],[_id]:[name]],2,0) -> Ольга ЖД больница | B81: 68ee7e5778a38b35c0162c15 | C81: true | D81: 68d298032c15702607657fd7 | E81: Новороссийская 28, ЖД Больница | F81: 47.0718, 37.4881 | H81: 0
A82: =VLOOKUP(ТабАдрес[[#This Row],[customerId]],ТабКлиенты[[#All],[_id]:[name]],2,0) -> Руденко Юля | B82: 68f473d1bfaac217810d635c | C82: false | D82: 68d297fe2c15702607657edd | E82: Шевченко, 309 | H82: 0
A83: =VLOOKUP(ТабАдрес[[#This Row],[customerId]],ТабКлиенты[[#All],[_id]:[name]],2,0) -> Руденко Юля | B83: 68ee7e5778a38b35c0162bb8 | C83: true | D83: 68d297fe2c15702607657edd | E83: Мариуполь, Митрополитская, 60 | F83: 47.0999, 37.5500 | H83: 0
A84: =VLOOKUP(ТабАдрес[[#This Row],[customerId]],ТабКлиенты[[#All],[_id]:[name]],2,0) -> Оксана 17 Цветы | B84: 68ee7e5778a38b35c0162be3 | C84: true | D84: 68d298012c15702607657f63 | E84: Троицкая 46 | F84: 47.1119, 37.5147 | H84: 0
A85: =VLOOKUP(ТабАдрес[[#This Row],[customerId]],ТабКлиенты[[#All],[_id]:[name]],2,0) -> Оксана 17 Цветы | B85: 68f48d1308b99d02255ce3e1 | C85: false | D85: 68d298012c15702607657f63 | E85: Шевченко, 295 | F85: 47.116923, 37.522235 | G85: Киоск Цветы | H85: 0
A86: =VLOOKUP(ТабАдрес[[#This Row],[customerId]],ТабКлиенты[[#All],[_id]:[name]],2,0) -> Татьяна Индол | B86: 68f618f9adc63884d7a59be3 | C86: true | D86: 68f618f8adc63884d7a59be1 | E86: Энгельса, 53 | H86: 0
A87: =VLOOKUP(ТабАдрес[[#This Row],[customerId]],ТабКлиенты[[#All],[_id]:[name]],2,0) -> Светлана Кулаки | B87: 68ee7e5778a38b35c0162bef | C87: true | D87: 68d298012c15702607657f8b | E87: Ткаченко Петренко 3 | F87: 47.0853, 37.5071 | H87: 0
A88: =VLOOKUP(ТабАдрес[[#This Row],[customerId]],ТабКлиенты[[#All],[_id]:[name]],2,0) -> Светлана Кулаки | B88: 68f7801aadc63884d7a59d78 | C88: false | D88: 68d298012c15702607657f8b | E88: Лавицкого, 7 | F88: 47.087776, 37.522944 | G88: Школа №60 | H88: 0
A89: =VLOOKUP(ТабАдрес[[#This Row],[customerId]],ТабКлиенты[[#All],[_id]:[name]],2,0) -> Надежда Витамины | B89: 68f78087adc63884d7a59dd9 | C89: false | D89: 68d298002c15702607657f47 | E89: Строителей, 102 | F89: 47.100776, 37.522477 | G89: дет. сад. №125 | H89: 0
A90: =VLOOKUP(ТабАдрес[[#This Row],[customerId]],ТабКлиенты[[#All],[_id]:[name]],2,0) -> Надежда Витамины | B90: 68ee7e5778a38b35c0162bd5 | C90: true | D90: 68d298002c15702607657f47 | E90: пер. Ейский 9 | F90: 47.0898, 37.5062 | H90: 0
A91: =VLOOKUP(ТабАдрес[[#This Row],[customerId]],ТабКлиенты[[#All],[_id]:[name]],2,0) -> Алена Бахчик | B91: 68f781c7adc63884d7a59e1e | C91: true | D91: 68f781c7adc63884d7a59e1c | E91: Строителей, 60 | F91: 47.091097, 37.521829 | G91: Иваныч фастфуд | H91: 0
A92: =VLOOKUP(ТабАдрес[[#This Row],[customerId]],ТабКлиенты[[#All],[_id]:[name]],2,0) -> Полина Цветы | B92: 68f78107adc63884d7a59e08 | C92: true | D92: 68f78107adc63884d7a59e06 | E92: Шевченко, 295 | F92: 47.116917, 37.521872 | G92: Цветы | H92: 0
A93: =VLOOKUP(ТабАдрес[[#This Row],[customerId]],ТабКлиенты[[#All],[_id]:[name]],2,0) -> Алёна Чайка | B93: 68f783a8adc63884d7a59eb3 | C93: true | D93: 68f783a8adc63884d7a59eb1 | E93: Металлургов, 81а | F93: 47.104947, 37.551863 | H93: 0
A94: =VLOOKUP(ТабАдрес[[#This Row],[customerId]],ТабКлиенты[[#All],[_id]:[name]],2,0) -> Наталья магазин (Удалить) | B94: 68ee7e5778a38b35c0162beb | C94: true | D94: 68d298012c15702607657f83 | E94: Грушевского 2б | F94: 47.1178, 37.5121 | H94: 0
A95: =VLOOKUP(ТабАдрес[[#This Row],[customerId]],ТабКлиенты[[#All],[_id]:[name]],2,0) -> Аня Мирный | B95: 68ee7e5778a38b35c0162bdf | C95: true | D95: 68d298012c15702607657f65 | E95: пер Станционный 8 | F95: 47.1640, 37.5780 | H95: 0
A96: =VLOOKUP(ТабАдрес[[#This Row],[customerId]],ТабКлиенты[[#All],[_id]:[name]],2,0) -> Аня Мирный | B96: 68f8b8836d77f5c8a72f993e | C96: false | D96: 68d298012c15702607657f65 | E96: Доменная, 42 | F96: 47.137861, 37.592241 | G96: Проходные | H96: 0
A97: =VLOOKUP(ТабАдрес[[#This Row],[customerId]],ТабКлиенты[[#All],[_id]:[name]],2,0) -> Татьяна Бригантина | B97: 68ee7e5778a38b35c0162bd7 | C97: true | D97: 68d298002c15702607657f51 | E97: Бригантина 152 | F97: 47.0779, 37.4879 | H97: 0
A98: =VLOOKUP(ТабАдрес[[#This Row],[customerId]],ТабКлиенты[[#All],[_id]:[name]],2,0) -> Татьяна Бригантина | B98: 68f8b8dc6d77f5c8a72f9990 | C98: false | D98: 68d298002c15702607657f51 | E98: 50 лет СССР, 48 | F98: 47.111025, 37.512829 | G98: Больница. Отделение Эндоскопии | H98: 0
A99: =VLOOKUP(ТабАдрес[[#This Row],[customerId]],ТабКлиенты[[#All],[_id]:[name]],2,0) -> Римма Омск | B99: 68f8b99a6d77f5c8a72f99b3 | C99: true | D99: 68f8b99a6d77f5c8a72f99b1 | E99: Омск, Енисейская 1Д | F99: 54.974153, 73.342727 | G99: Отделение КИТ | H99: 0
A100: =VLOOKUP(ТабАдрес[[#This Row],[customerId]],ТабКлиенты[[#All],[_id]:[name]],2,0) -> Римма Омск | B100: 68f8b99a6d77f5c8a72f99b5 | C100: false | D100: 68f8b99a6d77f5c8a72f99b1 | E100: 644521, Омский район, село Троицкое, ул. Степная, 27 | F100: 54.884218, 73.309408 | H100: 0
A101: =VLOOKUP(ТабАдрес[[#This Row],[customerId]],ТабКлиенты[[#All],[_id]:[name]],2,0) -> Валентина Кострова | B101: 68f8ba0d6d77f5c8a72f99d8 | C101: true | D101: 68f8ba0d6d77f5c8a72f99d6 | E101: Энгельса, 53 | F101: 47.099518, 37.549309 | G101: Склад | H101: 0
A102: =VLOOKUP(ТабАдрес[[#This Row],[customerId]],ТабКлиенты[[#All],[_id]:[name]],2,0) -> Олег Алешин | B102: 68f8bab16d77f5c8a72f99f2 | C102: true | D102: 68f8bab16d77f5c8a72f99f0 | E102: Мариуполь, пер. Целинный, 22 | F102: 47.102818, 37.662461 | H102: 0
A103: =VLOOKUP(ТабАдрес[[#This Row],[customerId]],ТабКлиенты[[#All],[_id]:[name]],2,0) -> Олег Алешин | B103: 68f8bab16d77f5c8a72f99f4 | C103: false | D103: 68f8bab16d77f5c8a72f99f0 | E103: Мариуполь, Ленина, 80 | F103: 47.097046, 37.536338 | H103: 0
A104: =VLOOKUP(ТабАдрес[[#This Row],[customerId]],ТабКлиенты[[#All],[_id]:[name]],2,0) -> Антонина Космос | B104: 68f8bc256d77f5c8a72f9a16 | C104: true | D104: 68f8bc256d77f5c8a72f9a14 | E104: Мариуполь, б. Шевченко, 295А | F104: 47.116991, 37.521160 | G104: Р. Космос, маг. Меланж | H104: 0
A105: =VLOOKUP(ТабАдрес[[#This Row],[customerId]],ТабКлиенты[[#All],[_id]:[name]],2,0) -> Виктория БСМП | B105: 68ee7e5778a38b35c0162c1f | C105: true | D105: 68d298012c15702607657f89 | E105: Бахмутская 20 | F105: 47.1157, 37.5479 | H105: 0
A106: =VLOOKUP(ТабАдрес[[#This Row],[customerId]],ТабКлиенты[[#All],[_id]:[name]],2,0) -> Светлана Звенигородская | B106: 68f8bd366d77f5c8a72f9a90 | C106: true | D106: 68f8bd366d77f5c8a72f9a8e | E106: Мариуполь, Звенигородская, 91 | F106: 47.124859, 37.673933 | H106: 0
A107: =VLOOKUP(ТабАдрес[[#This Row],[customerId]],ТабКлиенты[[#All],[_id]:[name]],2,0) -> Юлиана Афонина | B107: 68f8bdd06d77f5c8a72f9aa8 | C107: true | D107: 68f8bdd06d77f5c8a72f9aa6 | E107: Мариуполь, 50 лет СССР, 46 | F107: 47.111853, 37.515308 | G107: маг. Цветы | H107: 0
A108: =VLOOKUP(ТабАдрес[[#This Row],[customerId]],ТабКлиенты[[#All],[_id]:[name]],2,0) -> Юлиана Афонина | B108: 68f8bdd06d77f5c8a72f9aaa | C108: false | D108: 68f8bdd06d77f5c8a72f9aa6 | E108: Мариуполь, б. Шевченко, 295А | F108: 47.116900, 37.521949 | G108: маг. Цветы | H108: 0
A109: =VLOOKUP(ТабАдрес[[#This Row],[customerId]],ТабКлиенты[[#All],[_id]:[name]],2,0) -> Наталья магазин | B109: 68ee7e5778a38b35c0162c68 | C109: true | D109: 68ed1a0aa46150fa4106fd24 | E109: Апатова, 125 | F109: 47.094114, 37.535889 | G109: Магазин чёрный | H109: 0
A110: =VLOOKUP(ТабАдрес[[#This Row],[customerId]],ТабКлиенты[[#All],[_id]:[name]],2,0) -> Наталья магазин | B110: 68f7bacbadc63884d7a5a13c | C110: false | D110: 68ed1a0aa46150fa4106fd24 | E110: Грушевского 2б | F110: 47.1178, 37.5121 | H110: 0
A111: =VLOOKUP(ТабАдрес[[#This Row],[customerId]],ТабКлиенты[[#All],[_id]:[name]],2,0) -> Виталий Тополиная, 12А | B111: 68fca01e0024359e23617286 | C111: true | D111: 68fca01e0024359e23617284 | E111: Тополиная, 12А | F111: 47.134337, 37.534047 | H111: 0
A112: =VLOOKUP(ТабАдрес[[#This Row],[customerId]],ТабКлиенты[[#All],[_id]:[name]],2,0) -> Светлана ГАИ | B112: 6901c6d40024359e2361754e | C112: true | D112: 6901c6690024359e2361753a | E112: б. Приморский, 9 | F112: 47.082438, 37.537185 | H112: 0
A113: =VLOOKUP(ТабАдрес[[#This Row],[customerId]],ТабКлиенты[[#All],[_id]:[name]],2,0) -> Виктория Бахчиванджи | B113: 6904df630024359e23617ad9 | C113: true | D113: 6904df630024359e23617ad7 | E113: пр. Строителей, 60 | F113: 47.091120, 37.520662 | G113: Снежнянская колбасная фабрика | H113: 0
A114: =VLOOKUP(ТабАдрес[[#This Row],[customerId]],ТабКлиенты[[#All],[_id]:[name]],2,0) -> Лариса Западный | B114: 68ee7e5778a38b35c0162c36 | C114: true | D114: 68d298052c15702607658027 | E114: Урицкого, 118/16 | F114: 47.1223, 37.5125 | H114: 0
A115: =VLOOKUP(ТабАдрес[[#This Row],[customerId]],ТабКлиенты[[#All],[_id]:[name]],2,0) -> Лариса Западный | B115: 690f670a7ab5058720fad5fa | C115: false | D115: 68d298052c15702607658027 | E115: Писарева, 28 | F115: 47.106578, 37.547899 | H115: 0
A116: =VLOOKUP(ТабАдрес[[#This Row],[customerId]],ТабКлиенты[[#All],[_id]:[name]],2,0) -> Юлия рынок на Нептуне | B116: 691043487ab5058720fad6a0 | C116: false | D116: 68ee73e3a46150fa4106ff04 | E116: Металлургов, 211, Рынок | F116: 47.130100, 37.566450 | H116: 0
A117: =VLOOKUP(ТабАдрес[[#This Row],[customerId]],ТабКлиенты[[#All],[_id]:[name]],2,0) -> Юлия рынок на Нептуне | B117: 68ee7e5778a38b35c0162c6a | C117: true | D117: 68ee73e3a46150fa4106ff04 | E117: Сеченова, 49 | F117: 47.133908, 37.562227 | H117: 0
A118: =VLOOKUP(ТабАдрес[[#This Row],[customerId]],ТабКлиенты[[#All],[_id]:[name]],2,0) -> Светлана Драмтеатр | B118: 6910db1e7ab5058720fad84c | C118: true | D118: 6910db1e7ab5058720fad84a | E118: Драмтеатр | F118: 47.096310, 37.547860 | H118: 0
A119: =VLOOKUP(ТабАдрес[[#This Row],[customerId]],ТабКлиенты[[#All],[_id]:[name]],2,0) -> Светлана Ильинична Лиходед | B119: 6916cd907ab5058720fadb31 | C119: true | D119: 6916cd907ab5058720fadb2f | E119: Казанцева 31 | F119: 47.107026, 37.547586 | H119: 0
A120: =VLOOKUP(ТабАдрес[[#This Row],[customerId]],ТабКлиенты[[#All],[_id]:[name]],2,0) -> Наталья Балабан | B120: 691847157ab5058720fadcc9 | C120: true | D120: 691847157ab5058720fadcc7 | E120: Митрополитская, 51 | F120: 47.100674, 37.548795 | H120: 0
A121: =VLOOKUP(ТабАдрес[[#This Row],[customerId]],ТабКлиенты[[#All],[_id]:[name]],2,0) -> Ольга Лавицкого, 17 | B121: 691885527ab5058720fadd0f | C121: true | D121: 691885527ab5058720fadd0d | E121: Лавицкого, 17, подъезд 2, кв. 56, этаж 5 | F121: 47.089911, 37.518821 | H121: 0
A122: =VLOOKUP(ТабАдрес[[#This Row],[customerId]],ТабКлиенты[[#All],[_id]:[name]],2,0) -> Анна Володарское шоссе | B122: 691c38ab7ab5058720fadf5c | C122: true | D122: 691c38ab7ab5058720fadf5a | E122: Володарское шоссе, 8 | F122: 47.119153, 37.505877 | G122: М. Базар, склады | H122: 0
A123: =VLOOKUP(ТабАдрес[[#This Row],[customerId]],ТабКлиенты[[#All],[_id]:[name]],2,0) -> Виктория Башня/Энгельса | B123: 691c42717ab5058720fadfc3 | C123: true | D123: 691c42717ab5058720fadfc1 | E123: Энгельса, 36 | F123: 47.097705, 37.547111 | H123: 0
A124: =VLOOKUP(ТабАдрес[[#This Row],[customerId]],ТабКлиенты[[#All],[_id]:[name]],2,0) -> Надежда Sumbucol | B124: 691ef910fcbe9ecfd25ad4ec | C124: true | D124: 691ef8c07ab5058720faea1f | E124: пер. Звенигородский, 21/32 | F124: 47.120465, 37.670966 | H124: 0
A125: =VLOOKUP(ТабАдрес[[#This Row],[customerId]],ТабКлиенты[[#All],[_id]:[name]],2,0) -> Алина стоматология Лекарь | B125: 6922f1c27ab5058720faed8c | C125: true | D125: 6922f1c27ab5058720faed8a | E125: Ленина, 104 | F125: 47.098383, 37.522532 | G125: Стоматология Лекарь | H125: 0
A126: =VLOOKUP(ТабАдрес[[#This Row],[customerId]],ТабКлиенты[[#All],[_id]:[name]],2,0) -> Татьяна от Елены б-р Шевченко | B126: 68f7b259adc63884d7a59eff | C126: true | D126: 68f7b259adc63884d7a59efd | E126: Шевченко, 160 | F126: 47.112856, 37.540032 | H126: 0
A127: =VLOOKUP(ТабАдрес[[#This Row],[customerId]],ТабКлиенты[[#All],[_id]:[name]],2,0) -> Елена казначейство | B127: 692943757ab5058720faf3b4 | C127: true | D127: 692943757ab5058720faf3b2 | E127: Казанцева 22а | F127: 47.098525, 37.538948 | G127: Казначейство | H127: 0
A128: =VLOOKUP(ТабАдрес[[#This Row],[customerId]],ТабКлиенты[[#All],[_id]:[name]],2,0) -> Лев | B128: 692981467ab5058720faf45e | C128: true | D128: 692981467ab5058720faf45c | E128: Металлургов, 89 | F128: 47.100559, 37.546649 | H128: 0
A129: =VLOOKUP(ТабАдрес[[#This Row],[customerId]],ТабКлиенты[[#All],[_id]:[name]],2,0) -> Светлана от Надежды | B129: 69298f3310a385bba3c04860 | C129: true | D129: 69298f3210a385bba3c0485e | E129: 9-й Авиадивизии, 10, подъезд, 2 | F129: 47.119790, 37.518888 | H129: 0
A130: =VLOOKUP(ТабАдрес[[#This Row],[customerId]],ТабКлиенты[[#All],[_id]:[name]],2,0) -> Алёна Шевченко, 295 | B130: 692ab7e17ab5058720faf6ed | C130: true | D130: 692ab7e17ab5058720faf6eb | E130: Шевченко, 295, подъезд 3 | F130: 47.117985, 37.521758 | H130: 0
A131: =VLOOKUP(ТабАдрес[[#This Row],[customerId]],ТабКлиенты[[#All],[_id]:[name]],2,0) -> Елена Строителей, 35 | B131: 6932e810e0056d8926405bd9 | C131: false | D131: 68d297fb2c15702607657e53 | E131: Лавицкого, 16, 16 | F131: 47.087079, 37.519275 | G131: адрес сестры | H131: 0
A132: =VLOOKUP(ТабАдрес[[#This Row],[customerId]],ТабКлиенты[[#All],[_id]:[name]],2,0) -> Елена Строителей, 35 | B132: 690f206f0024359e23618449 | C132: true | D132: 68d297fb2c15702607657e53 | E132: Строителей, 35 | F132: 47.084475, 37.516449 | H132: 0

Sheet Карта ESSENS
A1: Сайт ESSENS | G1: Остатки
A2: Женские | C2: Мужские | Q2: ESSENS, NOIR by ESSENS Lost Cherry 50мл, 1233346389
A3: Парфюм | B3: Пробник | C3: Парфюм | D3: Пробник | G3: Женские | H3: Мужские | I3: Презентер1 | J3: Презентер2 | K3: Пробники | Q3: ESSENS, Noir Духи - №2, 0004eln02s
A4: w102 | B4: Unique 06 | C4: m001 | D4: Petronas | G4: NOIR by ESSENS Lost Cherry 50мл | H4: m003 | I4: m003 | J4: m003 | K4: m041 | Q4: ESSENS, Духи для женщин w111, 000w11150
A5: w104 | B5: Unique eu05 | C5: m003 | D5: m001 | G5: Noir Духи - №2 | H5: m007 | I5: m007 | J5: m007 | K5: m042 | Q5: ESSENS, Духи для женщин w114, 000w11450
A6: w105 | B6: w101 | C6: m007 | D6: m003 | G6: w102 | H6: m008 | I6: m008 | J6: m008 | K6: m043 | Q6: ESSENS, Духи для женщин w116, 000w11650
A7: w106 | B7: w102 | C7: m008 | D7: m007 | G7: w107 | H7: m015 | I7: m014 | J7: m014 | K7: m044 | Q7: ESSENS, Духи для женщин w124, 000w12450
A8: w107 | B8: w104 | C8: m013 | D8: m008 | G8: w111 | H8: m024 | I8: m015 | J8: m015 | K8: m045 | Q8: ESSENS, Духи для женщин w142, 000w14250
A9: w111 | B9: w105 | C9: m014 | D9: m013 | G9: w114 | H9: m025 | I9: m016 | J9: m016 | K9: m901 | Q9: ESSENS, Духи для женщин w144, 000w14450
A10: w113 | B10: w106 | C10: m015 | D10: m014 | G10: w116 | H10: m029 | I10: m017 | J10: m017 | K10: w191 | Q10: ESSENS, Духи для женщин w150, 000w15050
A11: w114 | B11: w107 | C11: m016 | D11: m015 | G11: w124 | H11: m035 | I11: m018 | J11: m018 | K11: w192 | Q11: ESSENS, Духи для женщин w151, 000w15150
A12: w115 | B12: w110 | C12: m017 | D12: m016 | G12: w137 | H12: m037 | I12: m024 | J12: m024 | K12: w183 | Q12: ESSENS, Духи для женщин w156, 000w15650
A13: w116 | B13: w111 | C13: m018 | D13: m017 | G13: w141 | H13: m038 | I13: m025 | J13: m025 | K13: w193 | Q13: ESSENS, Духи для женщин w159n, 000w15950n
A14: w117 | B14: w112 | C14: m022 | D14: m018 | G14: w142 | H14: m043 | I14: m027 | J14: m027 | K14: w903 | Q14: ESSENS, Духи для женщин w162, 000w16250
... A16: w124 | B16: w114 | C16: m025 | D16: m020 | G16: w148 | H16: m901 | I16: m029 | J16: m029 | K16: w184 | Q16: ESSENS, Духи для женщин w172, 000w17250
A17: w127 | B17: w116 | C17: m027 | D17: m021 | G17: w150 | I17: m034 | J17: m034 | K17: w185 | Q17: ESSENS, Духи для женщин w173, 000w17350
A18: w130 | B18: w117 | C18: m028 | D18: m022 | G18: w151 | I18: m035 | J18: m035 | K18: w189 | Q18: ESSENS, Духи для женщин w176, 000w17650
A19: w137 | B19: w118 | C19: m029 | D19: m023 | G19: w156 | I19: m036 | J19: m036 | K19: w902 | Q19: ESSENS, Духи для женщин w177, 000w17750
A20: w141 | B20: w124 | C20: m034 | D20: m024 | G20: w159n | I20: m037 | J20: m037 | K20: w186 | Q20: ESSENS, Духи для женщин w179, 000w17950
A21: w142 | B21: w126 | C21: m035 | D21: m025 | G21: w162 | I21: m038 | J21: m038 | K21: w194 | Q21: ESSENS, Духи для женщин w180, 000w18050
A22: w144 | B22: w127 | C22: m036 | D22: m026 | G22: w171 | I22: m039 | J22: m039 | K22: w187 | Q22: ESSENS, Духи для женщин w182, 000w18250
A23: w148 | B23: w130 | C23: m037 | D23: m027 | G23: w172 | I23: m040 | J23: m040 | K23: w162 | Q23: ESSENS, Духи для женщин w183, 000w18350
A24: w150 | B24: w132 | C24: m038 | D24: m028 | G24: w173 | I24: w102 | J24: w102 | K24: w002 | Q24: ESSENS, Духи для женщин w185, 000w18550
A25: w151 | B25: w137 | C25: m039 | D25: m029 | G25: w176 | I25: w104 | J25: w104 | K25: w006 | Q25: ESSENS, Духи для женщин w186, 000w18650
A26: w153 | B26: w141 | C26: m040 | D26: m030 | G26: w177 | I26: w105 | J26: w105 | Q26: ESSENS, Духи для женщин w188, 000w18850
A27: w155 | B27: w142 | C27: m041 | D27: m031 | G27: w179 | I27: w106 | J27: w106 | Q27: ESSENS, Духи для женщин w190, 000w19050
A28: w156 | B28: w144 | C28: m042 | D28: m032 | G28: w180 | I28: w107 | J28: w107 | Q28: ESSENS, Духи для женщин w191, 000w19150
A29: w157 | B29: w146 | C29: m043 | D29: m033 | G29: w182 | I29: w111 | J29: w111 | Q29: ESSENS, Духи для женщин w192, 000w19250
A30: w158 | B30: w147 | C30: m044 | D30: m034 | G30: w183 | I30: w114 | J30: w114 | Q30: ESSENS, Духи для женщин w193, 000w19350
A31: w159n | B31: w148 | C31: m045 | D31: m035 | G31: w185 | I31: w116 | J31: w116 | Q31: ESSENS, Духи для мужчин m007, 000m00750
A32: w163 | B32: w149 | C32: m901 | D32: m036 | G32: w186 | I32: w117 | J32: w117 | Q32: ESSENS, Духи для мужчин m008, 000m00850
A33: w166 | B33: w150 | C33: m902 | D33: m037 | G33: w188 | I33: w118 | J33: w118 | Q33: ESSENS, Духи для мужчин m015, 000m01550
A34: w171 | B34: w151 | D34: m038 | G34: w190 | I34: w124 | J34: w124 | Q34: ESSENS, Духи для мужчин m029, 000m02950
A35: w173 | B35: w152 | D35: m039 | G35: w191 | I35: w127 | J35: w127 | Q35: ESSENS, Духи для мужчин m035, 000m03550
A36: w178 | B36: w153 | D36: m040 | G36: w192 | I36: w130 | J36: w130 | Q36: ESSENS, Духи для мужчин m037, 000m03750
A37: w179 | B37: w154 | D37: m041 | G37: w193 | I37: w137 | J37: w137 | Q37: ESSENS, Духи для мужчин m038, 000m03850
A38: w181 | B38: w155 | D38: m042 | G38: w902 | I38: w141 | J38: w141 | Q38: ESSENS, Духи для мужчин m043, 000m04350
A39: w182 | B39: w156 | D39: m043 | G39: w903 | I39: w142 | J39: w142 | Q39: ESSENS, Духи для мужчин m044, 000m04450
A40: w183 | B40: w157 | D40: m044 | I40: w144 | J40: w144 | Q40: ESSENS, Набор парфюмерный женский Chance Eau Tendre №182, 1395837779
A41: w184 | B41: w158 | D41: m045 | I41: w148 | J41: w148 | Q41: ESSENS, Набор парфюмерный женский по мотивам J'adore №118, 1271446882
A42: w185 | B42: w159 | D42: m901 | I42: w150 | J42: w150 | Q42: ESSENS, парфюмированный гель для душа w179, 0000w179ng
A43: w186 | B43: w159n | D43: Unique eu03 | I43: w151 | J43: w151 | Q43: ESSENS, Пробник Niche Ultramarine Blue, 0000nc06s
A44: w187 | B44: w160 | D44: Unique 08 | I44: w153 | J44: w153 | Q44: ESSENS, Пробник w162, 000w16201
A45: w188 | B45: w161 | I45: w156 | J45: w156 | Q45: ESSENS, Пробник w185, 000w18501
A46: w189 | B46: w162 | I46: w158 | J46: w158 | Q46: ESSENS, Пробник w187, 000w18701
A47: w190 | B47: w163 | I47: w159 | J47: w159 | Q47: Духи для женщин w107
A48: w191 | B48: w164 | I48: w160 | J48: w160 | Q48: Духи для женщин w137
A49: w192 | B49: w165 | I49: w164 | J49: w165 | Q49: Духи для женщин w141
A50: w193 | B50: w166 | I50: w166 | J50: w166 | Q50: Духи для женщин w148
A51: w194 | B51: w167 | I51: w168 | J51: w168 | Q51: Духи для женщин w184
A52: w901 | B52: w168 | I52: w171 | J52: w171 | Q52: Духи для женщин w187
A53: w902 | B53: w169 | I53: w172 | J53: w172 | Q53: Духи для женщин w189
A54: w903 | B54: w170 | I54: w173 | J54: w173 | Q54: Духи для женщин w194
A55: w904 | B55: w171 | I55: w174 | J55: w174 | Q55: Духи для женщин w902
B56: w172 | I56: w175 | J56: w175 | Q56: Духи для женщин w903
B57: w173 | I57: w176 | J57: w176 | Q57: Духи для мужчин m024
B58: w174 | I58: w177 | J58: w177 | Q58: Духи для мужчин m025
B59: w175 | I59: w178 | J59: w178 | Q59: Духи для мужчин m041
B60: w176 | I60: w179 | J60: w179 | Q60: Духи для мужчин m901
B61: w177 | I61: w180 | J61: w180 | Q61: Пробник Noir Духи -№6
B62: w178 | I62: w181 | J62: w181 | Q62: Пробник w188
B63: w179 | I63: w182 | J63: w182 | Q63: Пробник w901
B64: w180 | Q64: Пробник w902
B65: w181 | Q65: Пробник w903
B66: w182
B67: w183
B68: w184
B69: w185
B70: w186
B71: w187
B72: w188
B73: w189
B74: w190
B75: w191
B76: w192
B77: w193
... B82: w904

Sheet СводнаяДоходы
A2: Остатки | C2: В пути
A3: Витамины | B3: =SUMIFS(Journal!$U:$U,Journal!$T:$T,"",Journal!$G:$G,A3) -> -503103.25 | C3: =SUMIFS(Journal!$U:$U,Journal!$T:$T,"",Journal!$G:$G,$A3,Journal!$D:$D,"<>Доставлен") -> -118761.36
A4: Спортпит | B4: =SUMIFS(Journal!$U:$U,Journal!$T:$T,"",Journal!$G:$G,A4) -> -33152.913 | C4: =SUMIFS(Journal!$U:$U,Journal!$T:$T,"",Journal!$G:$G,$A4,Journal!$D:$D,"<>Доставлен") -> 0
A5: Косметика | B5: =SUMIFS(Journal!$U:$U,Journal!$T:$T,"",Journal!$G:$G,A5) -> -139327.62 | C5: =SUMIFS(Journal!$U:$U,Journal!$T:$T,"",Journal!$G:$G,$A5,Journal!$D:$D,"<>Доставлен") -> -7656.3671
A6: Парфюм | B6: =SUMIFS(Journal!$U:$U,Journal!$T:$T,"",Journal!$G:$G,A6) -> -94394.21 | C6: =SUMIFS(Journal!$U:$U,Journal!$T:$T,"",Journal!$G:$G,$A6,Journal!$D:$D,"<>Доставлен") -> 0
A7: Итого: | B7: =SUM(B3:B6) -> -769977.99 | C7: =SUM(C3:C6) -> -126417.73
D9: Итого доход | H9: Наценка
A10: Названия строк | B10: Итого затрат RUB | C10: Итого продаж | D10: Витамины | E10: Спортпит | F10: Косметика | G10: Парфюм | I10: Всего
A11: 2022 07 | B11: 12475.57 | C11: =SUMIF(Journal!$T:$T,A11,Journal!$Q:$Q) -> 0 | D11: =SUMIFS(Journal!$U:$U,Journal!$T:$T,$A11,Journal!$G:$G,$D$10) -> 0 | E11: =SUMIFS(Journal!$U:$U,Journal!$T:$T,$A11,Journal!$G:$G,$E$10) -> 0 | F11: =SUMIFS(Journal!$U:$U,Journal!$T:$T,$A11,Journal!$G:$G,$F$10) -> 0 | I11: =SUM(D11:F11) -> 0
A12: 2022 08 | B12: 36480.995 | C12: =SUMIF(Journal!$T:$T,A12,Journal!$Q:$Q) -> 21400 | D12: =SUMIFS(Journal!$U:$U,Journal!$T:$T,$A12,Journal!$G:$G,$D$10) -> 8820.1844 | E12: =SUMIFS(Journal!$U:$U,Journal!$T:$T,$A12,Journal!$G:$G,$E$10) -> 0 | F12: =SUMIFS(Journal!$U:$U,Journal!$T:$T,$A12,Journal!$G:$G,$F$10) -> 546.73282 | G12: =SUMIFS(Journal!$U:$U,Journal!$T:$T,$A12,Journal!$G:$G,$G$10) -> 0 | H12: =I12/(C12-I12) -> 0.77843038 | I12: =SUM(D12:G12) -> 9366.9172
A13: 2022 09 | B13: 23308.388 | C13: =SUMIF(Journal!$T:$T,A13,Journal!$Q:$Q) -> 50902.59 | D13: =SUMIFS(Journal!$U:$U,Journal!$T:$T,$A13,Journal!$G:$G,$D$10) -> 20454.989 | E13: =SUMIFS(Journal!$U:$U,Journal!$T:$T,$A13,Journal!$G:$G,$E$10) -> 4536 | F13: =SUMIFS(Journal!$U:$U,Journal!$T:$T,$A13,Journal!$G:$G,$F$10) -> 495.37889 | G13: =SUMIFS(Journal!$U:$U,Journal!$T:$T,$A13,Journal!$G:$G,$G$10) -> 0 | H13: =I13/(C13-I13) -> 1.0027599 | I13: =SUM(D13:G13) -> 25486.368
A14: 2022 10 | B14: 56582.405 | C14: =SUMIF(Journal!$T:$T,A14,Journal!$Q:$Q) -> 53127.22 | D14: =SUMIFS(Journal!$U:$U,Journal!$T:$T,$A14,Journal!$G:$G,$D$10) -> 27582.366 | E14: =SUMIFS(Journal!$U:$U,Journal!$T:$T,$A14,Journal!$G:$G,$E$10) -> 1343.2794 | F14: =SUMIFS(Journal!$U:$U,Journal!$T:$T,$A14,Journal!$G:$G,$F$10) -> 131.15024 | G14: =SUMIFS(Journal!$U:$U,Journal!$T:$T,$A14,Journal!$G:$G,$G$10) -> 0 | H14: =I14/(C14-I14) -> 1.2071576 | I14: =SUM(D14:G14) -> 29056.795
A15: 2022 11 | B15: 203204.95 | C15: =SUMIF(Journal!$T:$T,A15,Journal!$Q:$Q) -> 136450 | D15: =SUMIFS(Journal!$U:$U,Journal!$T:$T,$A15,Journal!$G:$G,$D$10) -> 63310.407 | E15: =SUMIFS(Journal!$U:$U,Journal!$T:$T,$A15,Journal!$G:$G,$E$10) -> 4271.2409 | F15: =SUMIFS(Journal!$U:$U,Journal!$T:$T,$A15,Journal!$G:$G,$F$10) -> 4328.7095 | G15: =SUMIFS(Journal!$U:$U,Journal!$T:$T,$A15,Journal!$G:$G,$G$10) -> 0 | H15: =I15/(C15-I15) -> 1.1142045 | I15: =SUM(D15:G15) -> 71910.358
A16: 2022 12 | B16: 137714.47 | C16: =SUMIF(Journal!$T:$T,A16,Journal!$Q:$Q) -> 129424.33 | D16: =SUMIFS(Journal!$U:$U,Journal!$T:$T,$A16,Journal!$G:$G,$D$10) -> 47648.29 | E16: =SUMIFS(Journal!$U:$U,Journal!$T:$T,$A16,Journal!$G:$G,$E$10) -> 1709.216 | F16: =SUMIFS(Journal!$U:$U,Journal!$T:$T,$A16,Journal!$G:$G,$F$10) -> 2311.3849 | G16: =SUMIFS(Journal!$U:$U,Journal!$T:$T,$A16,Journal!$G:$G,$G$10) -> 0 | H16: =I16/(C16-I16) -> 0.66450514 | I16: =SUM(D16:G16) -> 51668.891
A17: 2023 01 | B17: 218003.17 | C17: =SUMIF(Journal!$T:$T,A17,Journal!$Q:$Q) -> 258998.14 | D17: =SUMIFS(Journal!$U:$U,Journal!$T:$T,$A17,Journal!$G:$G,$D$10) -> 85277.333 | E17: =SUMIFS(Journal!$U:$U,Journal!$T:$T,$A17,Journal!$G:$G,$E$10) -> 25338.22 | F17: =SUMIFS(Journal!$U:$U,Journal!$T:$T,$A17,Journal!$G:$G,$F$10) -> 6806.7827 | G17: =SUMIFS(Journal!$U:$U,Journal!$T:$T,$A17,Journal!$G:$G,$G$10) -> 0 | H17: =I17/(C17-I17) -> 0.82939552 | I17: =SUM(D17:G17) -> 117422.34
A18: 2023 02 | B18: 250819.23 | C18: =SUMIF(Journal!$T:$T,A18,Journal!$Q:$Q) -> 244757.31 | D18: =SUMIFS(Journal!$U:$U,Journal!$T:$T,$A18,Journal!$G:$G,$D$10) -> 77435.301 | E18: =SUMIFS(Journal!$U:$U,Journal!$T:$T,$A18,Journal!$G:$G,$E$10) -> 24839.476 | F18: =SUMIFS(Journal!$U:$U,Journal!$T:$T,$A18,Journal!$G:$G,$F$10) -> 3137.0332 | G18: =SUMIFS(Journal!$U:$U,Journal!$T:$T,$A18,Journal!$G:$G,$G$10) -> 0 | H18: =I18/(C18-I18) -> 0.75647804 | I18: =SUM(D18:G18) -> 105411.81
A19: 2023 03 | B19: 211470.11 | C19: =SUMIF(Journal!$T:$T,A19,Journal!$Q:$Q) -> 397722.32 | D19: =SUMIFS(Journal!$U:$U,Journal!$T:$T,$A19,Journal!$G:$G,$D$10) -> 147314.43 | E19: =SUMIFS(Journal!$U:$U,Journal!$T:$T,$A19,Journal!$G:$G,$E$10) -> 18476.175 | F19: =SUMIFS(Journal!$U:$U,Journal!$T:$T,$A19,Journal!$G:$G,$F$10) -> 13217.423 | G19: =SUMIFS(Journal!$U:$U,Journal!$T:$T,$A19,Journal!$G:$G,$G$10) -> 0 | H19: =I19/(C19-I19) -> 0.818456 | I19: =SUM(D19:G19) -> 179008.03
A20: 2023 04 | B20: 201384.13 | C20: =SUMIF(Journal!$T:$T,A20,Journal!$Q:$Q) -> 218200.4 | D20: =SUMIFS(Journal!$U:$U,Journal!$T:$T,$A20,Journal!$G:$G,$D$10) -> 58999.878 | E20: =SUMIFS(Journal!$U:$U,Journal!$T:$T,$A20,Journal!$G:$G,$E$10) -> 28237.463 | F20: =SUMIFS(Journal!$U:$U,Journal!$T:$T,$A20,Journal!$G:$G,$F$10) -> 4980.6627 | G20: =SUMIFS(Journal!$U:$U,Journal!$T:$T,$A20,Journal!$G:$G,$G$10) -> 0 | H20: =I20/(C20-I20) -> 0.73199119 | I20: =SUM(D20:G20) -> 92218.004
A21: 2023 05 | B21: 202220.42 | C21: =SUMIF(Journal!$T:$T,A21,Journal!$Q:$Q) -> 187411.49 | D21: =SUMIFS(Journal!$U:$U,Journal!$T:$T,$A21,Journal!$G:$G,$D$10) -> 55273.41 | E21: =SUMIFS(Journal!$U:$U,Journal!$T:$T,$A21,Journal!$G:$G,$E$10) -> 15291.584 | F21: =SUMIFS(Journal!$U:$U,Journal!$T:$T,$A21,Journal!$G:$G,$F$10) -> 1458.2754 | G21: =SUMIFS(Journal!$U:$U,Journal!$T:$T,$A21,Journal!$G:$G,$G$10) -> 0 | H21: =I21/(C21-I21) -> 0.62418217 | I21: =SUM(D21:G21) -> 72023.269
A22: 2023 06 | B22: 175586.89 | C22: =SUMIF(Journal!$T:$T,A22,Journal!$Q:$Q) -> 244424.19 | D22: =SUMIFS(Journal!$U:$U,Journal!$T:$T,$A22,Journal!$G:$G,$D$10) -> 65617.326 | E22: =SUMIFS(Journal!$U:$U,Journal!$T:$T,$A22,Journal!$G:$G,$E$10) -> 11996.515 | F22: =SUMIFS(Journal!$U:$U,Journal!$T:$T,$A22,Journal!$G:$G,$F$10) -> 3431.8755 | G22: =SUMIFS(Journal!$U:$U,Journal!$T:$T,$A22,Journal!$G:$G,$G$10) -> 0 | H22: =I22/(C22-I22) -> 0.49606117 | I22: =SUM(D22:G22) -> 81045.716
A23: 2023 07 | B23: 138647.7 | C23: =SUMIF(Journal!$T:$T,A23,Journal!$Q:$Q) -> 264715.82 | D23: =SUMIFS(Journal!$U:$U,Journal!$T:$T,$A23,Journal!$G:$G,$D$10) -> 59673.983 | E23: =SUMIFS(Journal!$U:$U,Journal!$T:$T,$A23,Journal!$G:$G,$E$10) -> 27240.619 | F23: =SUMIFS(Journal!$U:$U,Journal!$T:$T,$A23,Journal!$G:$G,$F$10) -> 861.54395 | G23: =SUMIFS(Journal!$U:$U,Journal!$T:$T,$A23,Journal!$G:$G,$G$10) -> 0 | H23: =I23/(C23-I23) -> 0.49607951 | I23: =SUM(D23:G23) -> 87776.146
... A57: 2026 05 | B57: 2056 | C57: =SUMIF(Journal!$T:$T,A57,Journal!$Q:$Q) -> 255350 | D57: =SUMIFS(Journal!$U:$U,Journal!$T:$T,$A57,Journal!$G:$G,$D$10) -> 89358.925 | E57: =SUMIFS(Journal!$U:$U,Journal!$T:$T,$A57,Journal!$G:$G,$E$10) -> 2457 | F57: =SUMIFS(Journal!$U:$U,Journal!$T:$T,$A57,Journal!$G:$G,$F$10) -> 847.85517 | G57: =SUMIFS(Journal!$U:$U,Journal!$T:$T,$A57,Journal!$G:$G,$G$10) -> 0 | H57: =I57/(C57-I57) -> 0.56958592 | I57: =SUM(D57:G57) -> 92663.78
A58: Общий итог | B58: 7924994.5 | C58: =SUM(C$11:C57) -> 11703078 | D58: =SUM(D$11:D57) -> 3842276.3 | E58: =SUM(E$11:E57) -> 471502.37 | F58: =SUM(F$11:F57) -> 107498.43 | G58: =SUM(G$11:G57) -> 56879.019 | H58: =I58/(C58-I58) -> 0.61982069 | I58: =SUM(I$11:I57) -> 4478156.2

Sheet Лист1
A1: Бренд | B1: ESSENS
A2: ДатаП | B2: (пусто)
A4: Названия строк | B4: Количество по полю Наименование
A5: Aloe Vera Зубная паста | B5: 1
A6: Noir Парфюм - № 6 | B6: 1
A7: Noir Парфюм - №2 | B7: 1
A8: Дкхи для женщин w117 | B8: 1
A9: Духи для женщин w111 | B9: 1
A10: Духи для женщин w114 | B10: 1
A11: Духи для женщин w116 | B11: 1
A12: Духи для женщин w124 | B12: 1
A13: Духи для женщин w130 | B13: 1
A14: Духи для женщин w137 | B14: 1
A15: Духи для женщин w141 | B15: 1
A16: Духи для женщин w142 | B16: 1
... A85: Общий итог | B85: 86

Sheet Лист2
A1: Названия строк | B1: Остаток | D1: Названия строк | E1: Остаток
A2: Aloe Vera Зубная паста | B2: 1 | D2: Духи для женщин w193 | E2: 1
A3: Noir Парфюм - № 6 | B3: 1 | D3: Духи для женщин w194 | E3: 1
A4: Noir Парфюм - №2 | B4: 1 | D4: Духи для женщин w195 | E4: 1
A5: Дкхи для женщин w117 | B5: 1 | D5: Духи для женщин w198 | E5: 1
A6: Духи для женщин w111 | B6: 1 | D6: Духи для женщин w199 | E6: 1
A7: Духи для женщин w114 | B7: 1 | D7: Духи для женщин w202 | E7: 1
A8: Духи для женщин w116 | B8: 1 | D8: Духи для женщин w902 | E8: 1
A9: Духи для женщин w124 | B9: 1 | D9: Духи для женщин w903 | E9: 1
A10: Духи для женщин w130 | B10: 1 | D10: Духи для мужчин m007 | E10: 1
A11: Духи для женщин w137 | B11: 1 | D11: Духи для мужчин m008 | E11: 1
A12: Духи для женщин w141 | B12: 1 | D12: Духи для мужчин m015 | E12: 1
A13: Духи для женщин w142 | B13: 1 | D13: Духи для мужчин m024 | E13: 1
... A39: Духи для женщин w192 | B39: 2 | D39: Пробник w902 | E39: 1
D40: Пробник w903 | E40: 1

Sheet Journal
A1: № заказа | B1: № отслеживания | C1: Поставщик | D1: Статус | E1: ДатаЗ | F1: МесяцЗ | G1: Группа | H1: Артикул | I1: Бренд | J1: Наименование | K1: Цена закупки | L1: Bonus | M1: Вознаграждение | N1: Разница в оплате | O1: Логистика | P1: Итоговая цена RUB | Q1: Продажа RUB | R1: ДатаП | S1: Клиент | T1: МесяцП | U1: Чистая прибыль RUB | V1: % наценки | Y1: Остатки
K2: =SUBTOTAL(3,K$3:K$6343) -> 5935 | L2: =SUBTOTAL(9,L$3:L$6343) -> -105536.64 | M2: =SUBTOTAL(9,M$3:M$6343) -> -39087.917 | N2: =SUBTOTAL(9,N$3:N$6343) -> -1012.383 | O2: =SUBTOTAL(9,O$3:O$6343) -> 139361.5 | P2: =SUBTOTAL(9,P$3:P$6343) -> 8064317.5 | Q2: =SUBTOTAL(9,Q$3:Q$6343) -> 11773268 | R2: =SUBTOTAL(3,R$3:R$6343) -> 5176 | T2: =SUBTOTAL(2,T$3:T$6343) -> 0 | U2: =SUBTOTAL(9,U$3:U$6343) -> 3708950.2 | V2: =SUBTOTAL(1,V$3:V$6343) -> 0.81620417 | Y2: Витамины | Z2: =SUMIFS($U:$U,$T:$T,"",$G:$G,Y2) -> -503103.25 | AA2: Спортпит | AB2: =SUMIFS($U:$U,$T:$T,"",$G:$G,AA2) -> -33152.913 | AC2: Косметика | AD2: =SUMIFS($U:$U,$T:$T,"",$G:$G,AC2) -> -139327.62 | AE2: Парфюм | AF2: =SUMIFS($U:$U,$T:$T,"",$G:$G,AE2) -> -94394.21
A3: 920195273 | B3: =IFERROR(VLOOKUP($A3,HeadJournal!$A$1:$NTR$890,COLUMN(HeadJournal!B$1),0),"") -> 1Z095EE70248804009 | C3: =IFERROR(VLOOKUP($A3,HeadJournal!$A$1:$NTR$890,COLUMN(HeadJournal!C$1),0),"") -> iHerb_OA CZN6870 | D3: =IFERROR(VLOOKUP($A3,HeadJournal!$A$1:$NTR$890,COLUMN(HeadJournal!D$1),0),"") -> Доставлен | E3: =IFERROR(VLOOKUP($A3,HeadJournal!$A$1:$NTR$890,COLUMN(HeadJournal!G$1),0),"") -> 44754 | F3: =IFERROR(TEXT(E3, "ГГГГ ММ"),"") -> 2022 07 | G3: Витамины | H3: CGN-01033 | I3: California Gold Nutrition | J3: CollagenUP®, гидролизованные пептиды морского коллагена с гиалуроновой кислотой и витамином C, с нейтральным вкусом, 206 г (7,26 унции) | K3: 534.78 | L3: -106.95667 | M3: =IFERROR(VLOOKUP($A3,HeadJournal!$A$1:$J$890,COLUMN(HeadJournal!I$1),0)*($K3+$L3)/(SUMIF($A:$A,$A3,$K:$K)+SUMIF($A:$A,$A3,$L:$L)),0) -> -70.365272 | N3: =IFERROR((VLOOKUP($A3,HeadJournal!$A$1:$K$890,COLUMN(HeadJournal!K$1),0)-VLOOKUP($A3,HeadJournal!$A$1:$K$890,COLUMN(HeadJournal!J$1),0))*($K3+$L3)/(SUMIF($A:$A,$A3,$K:$K)+SUMIF($A:$A,$A3,$L:$L)),0) -> 66.505573 | O3: =IFERROR((VLOOKUP($A3,HeadJournal!$A$1:$L$890,COLUMN(HeadJournal!L$1),0)*($K3+$L3)/(SUMIF($A:$A,$A3,$K:$K)+SUMIF($A:$A,$A3,$L:$L)))/VLOOKUP($A3,HeadJournal!$A$1:$L$890,COLUMN(HeadJournal!H$1),0),0) -> 237.03697 | P3: =IFERROR(SUM(K3:O3)*VLOOKUP($A3,HeadJournal!$A$1:$L$890,COLUMN(HeadJournal!H$1),0),0) -> 1322.0012 | Q3: 1100 | R3: 44804 | S3: <Клиент не выбран> | T3: =IF(R3="","",TEXT(R3,"ГГГГ ММ")) -> 2022 08 | U3: =Q3-P3 -> -222.00122 | V3: =IF(Q3<>0,IFERROR(U3/P3,""),"") -> -0.16792815
A4: 920195273 | B4: =IFERROR(VLOOKUP($A4,HeadJournal!$A$1:$NTR$890,COLUMN(HeadJournal!B$1),0),"") -> 1Z095EE70248804009 | C4: =IFERROR(VLOOKUP($A4,HeadJournal!$A$1:$NTR$890,COLUMN(HeadJournal!C$1),0),"") -> iHerb_OA CZN6870 | D4: =IFERROR(VLOOKUP($A4,HeadJournal!$A$1:$NTR$890,COLUMN(HeadJournal!D$1),0),"") -> Доставлен | E4: =IFERROR(VLOOKUP($A4,HeadJournal!$A$1:$NTR$890,COLUMN(HeadJournal!G$1),0),"") -> 44754 | F4: =IFERROR(TEXT(E4, "ГГГГ ММ"),"") -> 2022 07 | G4: Витамины | H4: CGN-01033 | I4: California Gold Nutrition | J4: CollagenUP®, гидролизованные пептиды морского коллагена с гиалуроновой кислотой и витамином C, с нейтральным вкусом, 206 г (7,26 унции) | K4: 534.78 | L4: -106.95667 | M4: =IFERROR(VLOOKUP($A4,HeadJournal!$A$1:$J$890,COLUMN(HeadJournal!I$1),0)*($K4+$L4)/(SUMIF($A:$A,$A4,$K:$K)+SUMIF($A:$A,$A4,$L:$L)),0) -> -70.365272 | N4: =IFERROR((VLOOKUP($A4,HeadJournal!$A$1:$K$890,COLUMN(HeadJournal!K$1),0)-VLOOKUP($A4,HeadJournal!$A$1:$K$890,COLUMN(HeadJournal!J$1),0))*($K4+$L4)/(SUMIF($A:$A,$A4,$K:$K)+SUMIF($A:$A,$A4,$L:$L)),0) -> 66.505573 | O4: =IFERROR((VLOOKUP($A4,HeadJournal!$A$1:$L$890,COLUMN(HeadJournal!L$1),0)*($K4+$L4)/(SUMIF($A:$A,$A4,$K:$K)+SUMIF($A:$A,$A4,$L:$L)))/VLOOKUP($A4,HeadJournal!$A$1:$L$890,COLUMN(HeadJournal!H$1),0),0) -> 237.03697 | P4: =IFERROR(SUM(K4:O4)*VLOOKUP($A4,HeadJournal!$A$1:$L$890,COLUMN(HeadJournal!H$1),0),0) -> 1322.0012 | Q4: 1100 | R4: 44804 | S4: <Клиент не выбран> | T4: =IF(R4="","",TEXT(R4,"ГГГГ ММ")) -> 2022 08 | U4: =Q4-P4 -> -222.00122 | V4: =IF(Q4<>0,IFERROR(U4/P4,""),"") -> -0.16792815
A5: 920195273 | B5: =IFERROR(VLOOKUP($A5,HeadJournal!$A$1:$NTR$890,COLUMN(HeadJournal!B$1),0),"") -> 1Z095EE70248804009 | C5: =IFERROR(VLOOKUP($A5,HeadJournal!$A$1:$NTR$890,COLUMN(HeadJournal!C$1),0),"") -> iHerb_OA CZN6870 | D5: =IFERROR(VLOOKUP($A5,HeadJournal!$A$1:$NTR$890,COLUMN(HeadJournal!D$1),0),"") -> Доставлен | E5: =IFERROR(VLOOKUP($A5,HeadJournal!$A$1:$NTR$890,COLUMN(HeadJournal!G$1),0),"") -> 44754 | F5: =IFERROR(TEXT(E5, "ГГГГ ММ"),"") -> 2022 07 | G5: Витамины | H5: CGN-01033 | I5: California Gold Nutrition | J5: CollagenUP®, гидролизованные пептиды морского коллагена с гиалуроновой кислотой и витамином C, с нейтральным вкусом, 206 г (7,26 унции) | K5: 534.78 | L5: -106.95667 | M5: =IFERROR(VLOOKUP($A5,HeadJournal!$A$1:$J$890,COLUMN(HeadJournal!I$1),0)*($K5+$L5)/(SUMIF($A:$A,$A5,$K:$K)+SUMIF($A:$A,$A5,$L:$L)),0) -> -70.365272 | N5: =IFERROR((VLOOKUP($A5,HeadJournal!$A$1:$K$890,COLUMN(HeadJournal!K$1),0)-VLOOKUP($A5,HeadJournal!$A$1:$K$890,COLUMN(HeadJournal!J$1),0))*($K5+$L5)/(SUMIF($A:$A,$A5,$K:$K)+SUMIF($A:$A,$A5,$L:$L)),0) -> 66.505573 | O5: =IFERROR((VLOOKUP($A5,HeadJournal!$A$1:$L$890,COLUMN(HeadJournal!L$1),0)*($K5+$L5)/(SUMIF($A:$A,$A5,$K:$K)+SUMIF($A:$A,$A5,$L:$L)))/VLOOKUP($A5,HeadJournal!$A$1:$L$890,COLUMN(HeadJournal!H$1),0),0) -> 237.03697 | P5: =IFERROR(SUM(K5:O5)*VLOOKUP($A5,HeadJournal!$A$1:$L$890,COLUMN(HeadJournal!H$1),0),0) -> 1322.0012 | Q5: 1800 | R5: 44804 | S5: <Клиент не выбран> | T5: =IF(R5="","",TEXT(R5,"ГГГГ ММ")) -> 2022 08 | U5: =Q5-P5 -> 477.99878 | V5: =IF(Q5<>0,IFERROR(U5/P5,""),"") -> 0.36157212
A6: 920195273 | B6: =IFERROR(VLOOKUP($A6,HeadJournal!$A$1:$NTR$890,COLUMN(HeadJournal!B$1),0),"") -> 1Z095EE70248804009 | C6: =IFERROR(VLOOKUP($A6,HeadJournal!$A$1:$NTR$890,COLUMN(HeadJournal!C$1),0),"") -> iHerb_OA CZN6870 | D6: =IFERROR(VLOOKUP($A6,HeadJournal!$A$1:$NTR$890,COLUMN(HeadJournal!D$1),0),"") -> Доставлен | E6: =IFERROR(VLOOKUP($A6,HeadJournal!$A$1:$NTR$890,COLUMN(HeadJournal!G$1),0),"") -> 44754 | F6: =IFERROR(TEXT(E6, "ГГГГ ММ"),"") -> 2022 07 | G6: Витамины | H6: CEN-22675 | I6: 21st Century | J6: Sentry, для женщин, мультивитаминная и мультиминеральная добавка, 120 таблеток | K6: 248.13 | L6: -24.82 | M6: =IFERROR(VLOOKUP($A6,HeadJournal!$A$1:$J$890,COLUMN(HeadJournal!I$1),0)*($K6+$L6)/(SUMIF($A:$A,$A6,$K:$K)+SUMIF($A:$A,$A6,$L:$L)),0) -> -36.728405 | N6: =IFERROR((VLOOKUP($A6,HeadJournal!$A$1:$K$890,COLUMN(HeadJournal!K$1),0)-VLOOKUP($A6,HeadJournal!$A$1:$K$890,COLUMN(HeadJournal!J$1),0))*($K6+$L6)/(SUMIF($A:$A,$A6,$K:$K)+SUMIF($A:$A,$A6,$L:$L)),0) -> 34.713767 | O6: =IFERROR((VLOOKUP($A6,HeadJournal!$A$1:$L$890,COLUMN(HeadJournal!L$1),0)*($K6+$L6)/(SUMIF($A:$A,$A6,$K:$K)+SUMIF($A:$A,$A6,$L:$L)))/VLOOKUP($A6,HeadJournal!$A$1:$L$890,COLUMN(HeadJournal!H$1),0),0) -> 123.72567 | P6: =IFERROR(SUM(K6:O6)*VLOOKUP($A6,HeadJournal!$A$1:$L$890,COLUMN(HeadJournal!H$1),0),0) -> 690.04205 | Q6: 1500 | R6: 44804 | S6: <Клиент не выбран> | T6: =IF(R6="","",TEXT(R6,"ГГГГ ММ")) -> 2022 08 | U6: =Q6-P6 -> 809.95795 | V6: =IF(Q6<>0,IFERROR(U6/P6,""),"") -> 1.1737806
A7: 920195273 | B7: =IFERROR(VLOOKUP($A7,HeadJournal!$A$1:$NTR$890,COLUMN(HeadJournal!B$1),0),"") -> 1Z095EE70248804009 | C7: =IFERROR(VLOOKUP($A7,HeadJournal!$A$1:$NTR$890,COLUMN(HeadJournal!C$1),0),"") -> iHerb_OA CZN6870 | D7: =IFERROR(VLOOKUP($A7,HeadJournal!$A$1:$NTR$890,COLUMN(HeadJournal!D$1),0),"") -> Доставлен | E7: =IFERROR(VLOOKUP($A7,HeadJournal!$A$1:$NTR$890,COLUMN(HeadJournal!G$1),0),"") -> 44754 | F7: =IFERROR(TEXT(E7, "ГГГГ ММ"),"") -> 2022 07 | G7: Витамины | H7: CEN-22673 | I7: 21st Century | J7: Sentry для мужчин, добавка с комплексом витаминов и микроэлементов, 120 таблеток | K7: 248.89 | L7: -24.89 | M7: =IFERROR(VLOOKUP($A7,HeadJournal!$A$1:$J$890,COLUMN(HeadJournal!I$1),0)*($K7+$L7)/(SUMIF($A:$A,$A7,$K:$K)+SUMIF($A:$A,$A7,$L:$L)),0) -> -36.841892 | N7: =IFERROR((VLOOKUP($A7,HeadJournal!$A$1:$K$890,COLUMN(HeadJournal!K$1),0)-VLOOKUP($A7,HeadJournal!$A$1:$K$890,COLUMN(HeadJournal!J$1),0))*($K7+$L7)/(SUMIF($A:$A,$A7,$K:$K)+SUMIF($A:$A,$A7,$L:$L)),0) -> 34.821028 | O7: =IFERROR((VLOOKUP($A7,HeadJournal!$A$1:$L$890,COLUMN(HeadJournal!L$1),0)*($K7+$L7)/(SUMIF($A:$A,$A7,$K:$K)+SUMIF($A:$A,$A7,$L:$L)))/VLOOKUP($A7,HeadJournal!$A$1:$L$890,COLUMN(HeadJournal!H$1),0),0) -> 124.10796 | P7: =IFERROR(SUM(K7:O7)*VLOOKUP($A7,HeadJournal!$A$1:$L$890,COLUMN(HeadJournal!H$1),0),0) -> 692.1742 | Q7: 1500 | R7: 44804 | S7: <Клиент не выбран> | T7: =IF(R7="","",TEXT(R7,"ГГГГ ММ")) -> 2022 08 | U7: =Q7-P7 -> 807.8258 | V7: =IF(Q7<>0,IFERROR(U7/P7,""),"") -> 1.1670845
A8: 920195273 | B8: =IFERROR(VLOOKUP($A8,HeadJournal!$A$1:$NTR$890,COLUMN(HeadJournal!B$1),0),"") -> 1Z095EE70248804009 | C8: =IFERROR(VLOOKUP($A8,HeadJournal!$A$1:$NTR$890,COLUMN(HeadJournal!C$1),0),"") -> iHerb_OA CZN6870 | D8: =IFERROR(VLOOKUP($A8,HeadJournal!$A$1:$NTR$890,COLUMN(HeadJournal!D$1),0),"") -> Доставлен | E8: =IFERROR(VLOOKUP($A8,HeadJournal!$A$1:$NTR$890,COLUMN(HeadJournal!G$1),0),"") -> 44754 | F8: =IFERROR(TEXT(E8, "ГГГГ ММ"),"") -> 2022 07 | G8: Витамины | H8: =RIGHT(Journal!$J8,9) -> CEN-28026 | I8: =IFERROR(LEFT(J8,FIND(",",J8)-1),"") -> 21st Century | J8: 21st Century, цитрат цинка, 50 мг, 60 таблеток CEN-28026 | K8: 62.92 | L8: -6.29 | M8: =IFERROR(VLOOKUP($A8,HeadJournal!$A$1:$J$890,COLUMN(HeadJournal!I$1),0)*($K8+$L8)/(SUMIF($A:$A,$A8,$K:$K)+SUMIF($A:$A,$A8,$L:$L)),0) -> -9.3140907 | N8: =IFERROR((VLOOKUP($A8,HeadJournal!$A$1:$K$890,COLUMN(HeadJournal!K$1),0)-VLOOKUP($A8,HeadJournal!$A$1:$K$890,COLUMN(HeadJournal!J$1),0))*($K8+$L8)/(SUMIF($A:$A,$A8,$K:$K)+SUMIF($A:$A,$A8,$L:$L)),0) -> 8.8031912 | O8: =IFERROR((VLOOKUP($A8,HeadJournal!$A$1:$L$890,COLUMN(HeadJournal!L$1),0)*($K8+$L8)/(SUMIF($A:$A,$A8,$K:$K)+SUMIF($A:$A,$A8,$L:$L)))/VLOOKUP($A8,HeadJournal!$A$1:$L$890,COLUMN(HeadJournal!H$1),0),0) -> 31.376044 | P8: =IFERROR(SUM(K8:O8)*VLOOKUP($A8,HeadJournal!$A$1:$L$890,COLUMN(HeadJournal!H$1),0),0) -> 174.99029 | Q8: 450 | R8: 44821 | S8: <Клиент не выбран> | T8: =IF(R8="","",TEXT(R8,"ГГГГ ММ")) -> 2022 09 | U8: =Q8-P8 -> 275.00971 | V8: =IF(Q8<>0,IFERROR(U8/P8,""),"") -> 1.5715713
A9: 920195273 | B9: =IFERROR(VLOOKUP($A9,HeadJournal!$A$1:$NTR$890,COLUMN(HeadJournal!B$1),0),"") -> 1Z095EE70248804009 | C9: =IFERROR(VLOOKUP($A9,HeadJournal!$A$1:$NTR$890,COLUMN(HeadJournal!C$1),0),"") -> iHerb_OA CZN6870 | D9: =IFERROR(VLOOKUP($A9,HeadJournal!$A$1:$NTR$890,COLUMN(HeadJournal!D$1),0),"") -> Доставлен | E9: =IFERROR(VLOOKUP($A9,HeadJournal!$A$1:$NTR$890,COLUMN(HeadJournal!G$1),0),"") -> 44754 | F9: =IFERROR(TEXT(E9, "ГГГГ ММ"),"") -> 2022 07 | G9: Витамины | H9: =RIGHT(Journal!$J9,9) -> CEN-27116 | I9: =IFERROR(LEFT(J9,FIND(",",J9)-1),"") -> 21st Century | J9: 21st Century, Биотин, 5000 мкг, 110 капсул CEN-27116 | K9: 186.22 | L9: -18.62 | M9: =IFERROR(VLOOKUP($A9,HeadJournal!$A$1:$J$890,COLUMN(HeadJournal!I$1),0)*($K9+$L9)/(SUMIF($A:$A,$A9,$K:$K)+SUMIF($A:$A,$A9,$L:$L)),0) -> -27.56563 | N9: =IFERROR((VLOOKUP($A9,HeadJournal!$A$1:$K$890,COLUMN(HeadJournal!K$1),0)-VLOOKUP($A9,HeadJournal!$A$1:$K$890,COLUMN(HeadJournal!J$1),0))*($K9+$L9)/(SUMIF($A:$A,$A9,$K:$K)+SUMIF($A:$A,$A9,$L:$L)),0) -> 26.053591 | O9: =IFERROR((VLOOKUP($A9,HeadJournal!$A$1:$L$890,COLUMN(HeadJournal!L$1),0)*($K9+$L9)/(SUMIF($A:$A,$A9,$K:$K)+SUMIF($A:$A,$A9,$L:$L)))/VLOOKUP($A9,HeadJournal!$A$1:$L$890,COLUMN(HeadJournal!H$1),0),0) -> 92.85935 | P9: =IFERROR(SUM(K9:O9)*VLOOKUP($A9,HeadJournal!$A$1:$L$890,COLUMN(HeadJournal!H$1),0),0) -> 517.89462 | Q9: 700 | R9: 44804 | S9: <Клиент не выбран> | T9: =IF(R9="","",TEXT(R9,"ГГГГ ММ")) -> 2022 08 | U9: =Q9-P9 -> 182.10538 | V9: =IF(Q9<>0,IFERROR(U9/P9,""),"") -> 0.35162631
A10: 920195273 | B10: =IFERROR(VLOOKUP($A10,HeadJournal!$A$1:$NTR$890,COLUMN(HeadJournal!B$1),0),"") -> 1Z095EE70248804009 | C10: =IFERROR(VLOOKUP($A10,HeadJournal!$A$1:$NTR$890,COLUMN(HeadJournal!C$1),0),"") -> iHerb_OA CZN6870 | D10: =IFERROR(VLOOKUP($A10,HeadJournal!$A$1:$NTR$890,COLUMN(HeadJournal!D$1),0),"") -> Доставлен | E10: =IFERROR(VLOOKUP($A10,HeadJournal!$A$1:$NTR$890,COLUMN(HeadJournal!G$1),0),"") -> 44754 | F10: =IFERROR(TEXT(E10, "ГГГГ ММ"),"") -> 2022 07 | G10: Витамины | H10: =RIGHT(Journal!$J10,9) -> NOW-01685 | I10: =IFERROR(LEFT(J10,FIND(",",J10)-1),"") -> NOW Foods | J10: NOW Foods, жирные кислоты омега-3 в мини-капсулах, 180 ЭПК / 120 ДГК, 180 капсул NOW-01685 | K10: 378.49 | L10: -56.77 | M10: =IFERROR(VLOOKUP($A10,HeadJournal!$A$1:$J$890,COLUMN(HeadJournal!I$1),0)*($K10+$L10)/(SUMIF($A:$A,$A10,$K:$K)+SUMIF($A:$A,$A10,$L:$L)),0) -> -52.914167 | N10: =IFERROR((VLOOKUP($A10,HeadJournal!$A$1:$K$890,COLUMN(HeadJournal!K$1),0)-VLOOKUP($A10,HeadJournal!$A$1:$K$890,COLUMN(HeadJournal!J$1),0))*($K10+$L10)/(SUMIF($A:$A,$A10,$K:$K)+SUMIF($A:$A,$A10,$L:$L)),0) -> 50.011702 | O10: =IFERROR((VLOOKUP($A10,HeadJournal!$A$1:$L$890,COLUMN(HeadJournal!L$1),0)*($K10+$L10)/(SUMIF($A:$A,$A10,$K:$K)+SUMIF($A:$A,$A10,$L:$L)))/VLOOKUP($A10,HeadJournal!$A$1:$L$890,COLUMN(HeadJournal!H$1),0),0) -> 178.25006 | P10: =IFERROR(SUM(K10:O10)*VLOOKUP($A10,HeadJournal!$A$1:$L$890,COLUMN(HeadJournal!H$1),0),0) -> 994.13519 | Q10: 1400 | R10: 44804 | S10: <Клиент не выбран> | T10: =IF(R10="","",TEXT(R10,"ГГГГ ММ")) -> 2022 08 | U10: =Q10-P10 -> 405.86481 | V10: =IF(Q10<>0,IFERROR(U10/P10,""),"") -> 0.40825917
A11: 920406036 | B11: =IFERROR(VLOOKUP($A11,HeadJournal!$A$1:$NTR$890,COLUMN(HeadJournal!B$1),0),"") -> 1LSCXLZ000YQI0M | C11: =IFERROR(VLOOKUP($A11,HeadJournal!$A$1:$NTR$890,COLUMN(HeadJournal!C$1),0),"") -> iHerb_AV CYG0792 | D11: =IFERROR(VLOOKUP($A11,HeadJournal!$A$1:$NTR$890,COLUMN(HeadJournal!D$1),0),"") -> Доставлен | E11: =IFERROR(VLOOKUP($A11,HeadJournal!$A$1:$NTR$890,COLUMN(HeadJournal!G$1),0),"") -> 44768 | F11: =IFERROR(TEXT(E11, "ГГГГ ММ"),"") -> 2022 07 | G11: Витамины | H11: MLI-00952 | I11: California Gold Nutrition | J11: премиальный рыбий жир с омега-3, 100 капсул из рыбьего желатина (1100 мг в 1 капсуле) | K11: 258.3 | L11: -125.46 | M11: =IFERROR(VLOOKUP($A11,HeadJournal!$A$1:$J$890,COLUMN(HeadJournal!I$1),0)*($K11+$L11)/(SUMIF($A:$A,$A11,$K:$K)+SUMIF($A:$A,$A11,$L:$L)),0) -> -40.852379 | N11: =IFERROR((VLOOKUP($A11,HeadJournal!$A$1:$K$890,COLUMN(HeadJournal!K$1),0)-VLOOKUP($A11,HeadJournal!$A$1:$K$890,COLUMN(HeadJournal!J$1),0))*($K11+$L11)/(SUMIF($A:$A,$A11,$K:$K)+SUMIF($A:$A,$A11,$L:$L)),0) -> 0.00029088558 | O11: =IFERROR((VLOOKUP($A11,HeadJournal!$A$1:$L$890,COLUMN(HeadJournal!L$1),0)*($K11+$L11)/(SUMIF($A:$A,$A11,$K:$K)+SUMIF($A:$A,$A11,$L:$L)))/VLOOKUP($A11,HeadJournal!$A$1:$L$890,COLUMN(HeadJournal!H$1),0),0) -> 66.263445 | P11: =IFERROR(SUM(K11:O11)*VLOOKUP($A11,HeadJournal!$A$1:$L$890,COLUMN(HeadJournal!H$1),0),0) -> 316.50271 | Q11: 1000 | R11: 44880 | S11: <Клиент не выбран> | T11: =IF(R11="","",TEXT(R11,"ГГГГ ММ")) -> 2022 11 | U11: =Q11-P11 -> 683.49729 | V11: =IF(Q11<>0,IFERROR(U11/P11,""),"") -> 2.1595306
A12: 920406036 | B12: =IFERROR(VLOOKUP($A12,HeadJournal!$A$1:$NTR$890,COLUMN(HeadJournal!B$1),0),"") -> 1LSCXLZ000YQI0M | C12: =IFERROR(VLOOKUP($A12,HeadJournal!$A$1:$NTR$890,COLUMN(HeadJournal!C$1),0),"") -> iHerb_AV CYG0792 | D12: =IFERROR(VLOOKUP($A12,HeadJournal!$A$1:$NTR$890,COLUMN(HeadJournal!D$1),0),"") -> Доставлен | E12: =IFERROR(VLOOKUP($A12,HeadJournal!$A$1:$NTR$890,COLUMN(HeadJournal!G$1),0),"") -> 44768 | F12: =IFERROR(TEXT(E12, "ГГГГ ММ"),"") -> 2022 07 | G12: Витамины | H12: MLI-00952 | I12: California Gold Nutrition | J12: премиальный рыбий жир с омега-3, 100 капсул из рыбьего желатина (1100 мг в 1 капсуле) | K12: 258.3 | L12: -125.46 | M12: =IFERROR(VLOOKUP($A12,HeadJournal!$A$1:$J$890,COLUMN(HeadJournal!I$1),0)*($K12+$L12)/(SUMIF($A:$A,$A12,$K:$K)+SUMIF($A:$A,$A12,$L:$L)),0) -> -40.852379 | N12: =IFERROR((VLOOKUP($A12,HeadJournal!$A$1:$K$890,COLUMN(HeadJournal!K$1),0)-VLOOKUP($A12,HeadJournal!$A$1:$K$890,COLUMN(HeadJournal!J$1),0))*($K12+$L12)/(SUMIF($A:$A,$A12,$K:$K)+SUMIF($A:$A,$A12,$L:$L)),0) -> 0.00029088558 | O12: =IFERROR((VLOOKUP($A12,HeadJournal!$A$1:$L$890,COLUMN(HeadJournal!L$1),0)*($K12+$L12)/(SUMIF($A:$A,$A12,$K:$K)+SUMIF($A:$A,$A12,$L:$L)))/VLOOKUP($A12,HeadJournal!$A$1:$L$890,COLUMN(HeadJournal!H$1),0),0) -> 66.263445 | P12: =IFERROR(SUM(K12:O12)*VLOOKUP($A12,HeadJournal!$A$1:$L$890,COLUMN(HeadJournal!H$1),0),0) -> 316.50271 | Q12: 1200 | R12: 44935 | S12: <Клиент не выбран> | T12: =IF(R12="","",TEXT(R12,"ГГГГ ММ")) -> 2023 01 | U12: =Q12-P12 -> 883.49729 | V12: =IF(Q12<>0,IFERROR(U12/P12,""),"") -> 2.7914367
A13: 920406036 | B13: =IFERROR(VLOOKUP($A13,HeadJournal!$A$1:$NTR$890,COLUMN(HeadJournal!B$1),0),"") -> 1LSCXLZ000YQI0M | C13: =IFERROR(VLOOKUP($A13,HeadJournal!$A$1:$NTR$890,COLUMN(HeadJournal!C$1),0),"") -> iHerb_AV CYG0792 | D13: =IFERROR(VLOOKUP($A13,HeadJournal!$A$1:$NTR$890,COLUMN(HeadJournal!D$1),0),"") -> Доставлен | E13: =IFERROR(VLOOKUP($A13,HeadJournal!$A$1:$NTR$890,COLUMN(HeadJournal!G$1),0),"") -> 44768 | F13: =IFERROR(TEXT(E13, "ГГГГ ММ"),"") -> 2022 07 | G13: Витамины | H13: MLI-00952 | I13: California Gold Nutrition | J13: премиальный рыбий жир с омега-3, 100 капсул из рыбьего желатина (1100 мг в 1 капсуле) | K13: 258.3 | L13: -125.46 | M13: =IFERROR(VLOOKUP($A13,HeadJournal!$A$1:$J$890,COLUMN(HeadJournal!I$1),0)*($K13+$L13)/(SUMIF($A:$A,$A13,$K:$K)+SUMIF($A:$A,$A13,$L:$L)),0) -> -40.852379 | N13: =IFERROR((VLOOKUP($A13,HeadJournal!$A$1:$K$890,COLUMN(HeadJournal!K$1),0)-VLOOKUP($A13,HeadJournal!$A$1:$K$890,COLUMN(HeadJournal!J$1),0))*($K13+$L13)/(SUMIF($A:$A,$A13,$K:$K)+SUMIF($A:$A,$A13,$L:$L)),0) -> 0.00029088558 | O13: =IFERROR((VLOOKUP($A13,HeadJournal!$A$1:$L$890,COLUMN(HeadJournal!L$1),0)*($K13+$L13)/(SUMIF($A:$A,$A13,$K:$K)+SUMIF($A:$A,$A13,$L:$L)))/VLOOKUP($A13,HeadJournal!$A$1:$L$890,COLUMN(HeadJournal!H$1),0),0) -> 66.263445 | P13: =IFERROR(SUM(K13:O13)*VLOOKUP($A13,HeadJournal!$A$1:$L$890,COLUMN(HeadJournal!H$1),0),0) -> 316.50271 | Q13: 1100 | R13: 45052 | S13: <Клиент не выбран> | T13: =IF(R13="","",TEXT(R13,"ГГГГ ММ")) -> 2023 05 | U13: =Q13-P13 -> 783.49729 | V13: =IF(Q13<>0,IFERROR(U13/P13,""),"") -> 2.4754836
A14: 920406036 | B14: =IFERROR(VLOOKUP($A14,HeadJournal!$A$1:$NTR$890,COLUMN(HeadJournal!B$1),0),"") -> 1LSCXLZ000YQI0M | C14: =IFERROR(VLOOKUP($A14,HeadJournal!$A$1:$NTR$890,COLUMN(HeadJournal!C$1),0),"") -> iHerb_AV CYG0792 | D14: =IFERROR(VLOOKUP($A14,HeadJournal!$A$1:$NTR$890,COLUMN(HeadJournal!D$1),0),"") -> Доставлен | E14: =IFERROR(VLOOKUP($A14,HeadJournal!$A$1:$NTR$890,COLUMN(HeadJournal!G$1),0),"") -> 44768 | F14: =IFERROR(TEXT(E14, "ГГГГ ММ"),"") -> 2022 07 | G14: Витамины | H14: =RIGHT(Journal!$J14,9) -> MLI-00953 | I14: =IFERROR(LEFT(J14,FIND(",",J14)-1),"") -> California Gold Nutrition | J14: California Gold Nutrition, омега-3, рыбий жир премиального качества, 180 мг ЭПК / 120 мг ДГК, 100 капсул из рыбьего желатина MLI-00953 | K14: 627.3 | L14: -125.46 | M14: =IFERROR(VLOOKUP($A14,HeadJournal!$A$1:$J$890,COLUMN(HeadJournal!I$1),0)*($K14+$L14)/(SUMIF($A:$A,$A14,$K:$K)+SUMIF($A:$A,$A14,$L:$L)),0) -> -154.33121 | N14: =IFERROR((VLOOKUP($A14,HeadJournal!$A$1:$K$890,COLUMN(HeadJournal!K$1),0)-VLOOKUP($A14,HeadJournal!$A$1:$K$890,COLUMN(HeadJournal!J$1),0))*($K14+$L14)/(SUMIF($A:$A,$A14,$K:$K)+SUMIF($A:$A,$A14,$L:$L)),0) -> 0.0010989011 | O14: =IFERROR((VLOOKUP($A14,HeadJournal!$A$1:$L$890,COLUMN(HeadJournal!L$1),0)*($K14+$L14)/(SUMIF($A:$A,$A14,$K:$K)+SUMIF($A:$A,$A14,$L:$L)))/VLOOKUP($A14,HeadJournal!$A$1:$L$890,COLUMN(HeadJournal!H$1),0),0) -> 250.32857 | P14: =IFERROR(SUM(K14:O14)*VLOOKUP($A14,HeadJournal!$A$1:$L$890,COLUMN(HeadJournal!H$1),0),0) -> 1195.6769 | Q14: 2300 | R14: 45072 | S14: <Клиент не выбран> | T14: =IF(R14="","",TEXT(R14,"ГГГГ ММ")) -> 2023 05 | U14: =Q14-P14 -> 1104.3231 | V14: =IF(Q14<>0,IFERROR(U14/P14,""),"") -> 0.92359655
A15: 920406036 | B15: =IFERROR(VLOOKUP($A15,HeadJournal!$A$1:$NTR$890,COLUMN(HeadJournal!B$1),0),"") -> 1LSCXLZ000YQI0M | C15: =IFERROR(VLOOKUP($A15,HeadJournal!$A$1:$NTR$890,COLUMN(HeadJournal!C$1),0),"") -> iHerb_AV CYG0792 | D15: =IFERROR(VLOOKUP($A15,HeadJournal!$A$1:$NTR$890,COLUMN(HeadJournal!D$1),0),"") -> Доставлен | E15: =IFERROR(VLOOKUP($A15,HeadJournal!$A$1:$NTR$890,COLUMN(HeadJournal!G$1),0),"") -> 44768 | F15: =IFERROR(TEXT(E15, "ГГГГ ММ"),"") -> 2022 07 | G15: Витамины | H15: CGN-01033 | I15: California Gold Nutrition | J15: CollagenUP®, гидролизованные пептиды морского коллагена с гиалуроновой кислотой и витамином C, с нейтральным вкусом, 206 г (7,26 унции) | K15: 627.3 | L15: -125.46 | M15: =IFERROR(VLOOKUP($A15,HeadJournal!$A$1:$J$890,COLUMN(HeadJournal!I$1),0)*($K15+$L15)/(SUMIF($A:$A,$A15,$K:$K)+SUMIF($A:$A,$A15,$L:$L)),0) -> -154.33121 | N15: =IFERROR((VLOOKUP($A15,HeadJournal!$A$1:$K$890,COLUMN(HeadJournal!K$1),0)-VLOOKUP($A15,HeadJournal!$A$1:$K$890,COLUMN(HeadJournal!J$1),0))*($K15+$L15)/(SUMIF($A:$A,$A15,$K:$K)+SUMIF($A:$A,$A15,$L:$L)),0) -> 0.0010989011 | O15: =IFERROR((VLOOKUP($A15,HeadJournal!$A$1:$L$890,COLUMN(HeadJournal!L$1),0)*($K15+$L15)/(SUMIF($A:$A,$A15,$K:$K)+SUMIF($A:$A,$A15,$L:$L)))/VLOOKUP($A15,HeadJournal!$A$1:$L$890,COLUMN(HeadJournal!H$1),0),0) -> 250.32857 | P15: =IFERROR(SUM(K15:O15)*VLOOKUP($A15,HeadJournal!$A$1:$L$890,COLUMN(HeadJournal!H$1),0),0) -> 1195.6769 | Q15: 2100 | R15: 45078 | S15: <Клиент не выбран> | T15: =IF(R15="","",TEXT(R15,"ГГГГ ММ")) -> 2023 06 | U15: =Q15-P15 -> 904.32308 | V15: =IF(Q15<>0,IFERROR(U15/P15,""),"") -> 0.75632728
A16: 920406036 | B16: =IFERROR(VLOOKUP($A16,HeadJournal!$A$1:$NTR$890,COLUMN(HeadJournal!B$1),0),"") -> 1LSCXLZ000YQI0M | C16: =IFERROR(VLOOKUP($A16,HeadJournal!$A$1:$NTR$890,COLUMN(HeadJournal!C$1),0),"") -> iHerb_AV CYG0792 | D16: =IFERROR(VLOOKUP($A16,HeadJournal!$A$1:$NTR$890,COLUMN(HeadJournal!D$1),0),"") -> Доставлен | E16: =IFERROR(VLOOKUP($A16,HeadJournal!$A$1:$NTR$890,COLUMN(HeadJournal!G$1),0),"") -> 44768 | F16: =IFERROR(TEXT(E16, "ГГГГ ММ"),"") -> 2022 07 | G16: Витамины | H16: CGN-01033 | I16: California Gold Nutrition | J16: CollagenUP®, гидролизованные пептиды морского коллагена с гиалуроновой кислотой и витамином C, с нейтральным вкусом, 206 г (7,26 унции) | K16: 627.3 | L16: -125.46 | M16: =IFERROR(VLOOKUP($A16,HeadJournal!$A$1:$J$890,COLUMN(HeadJournal!I$1),0)*($K16+$L16)/(SUMIF($A:$A,$A16,$K:$K)+SUMIF($A:$A,$A16,$L:$L)),0) -> -154.33121 | N16: =IFERROR((VLOOKUP($A16,HeadJournal!$A$1:$K$890,COLUMN(HeadJournal!K$1),0)-VLOOKUP($A16,HeadJournal!$A$1:$K$890,COLUMN(HeadJournal!J$1),0))*($K16+$L16)/(SUMIF($A:$A,$A16,$K:$K)+SUMIF($A:$A,$A16,$L:$L)),0) -> 0.0010989011 | O16: =IFERROR((VLOOKUP($A16,HeadJournal!$A$1:$L$890,COLUMN(HeadJournal!L$1),0)*($K16+$L16)/(SUMIF($A:$A,$A16,$K:$K)+SUMIF($A:$A,$A16,$L:$L)))/VLOOKUP($A16,HeadJournal!$A$1:$L$890,COLUMN(HeadJournal!H$1),0),0) -> 250.32857 | P16: =IFERROR(SUM(K16:O16)*VLOOKUP($A16,HeadJournal!$A$1:$L$890,COLUMN(HeadJournal!H$1),0),0) -> 1195.6769 | Q16: 2100 | R16: 45078 | S16: <Клиент не выбран> | T16: =IF(R16="","",TEXT(R16,"ГГГГ ММ")) -> 2023 06 | U16: =Q16-P16 -> 904.32308 | V16: =IF(Q16<>0,IFERROR(U16/P16,""),"") -> 0.75632728
A17: 920406036 | B17: =IFERROR(VLOOKUP($A17,HeadJournal!$A$1:$NTR$890,COLUMN(HeadJournal!B$1),0),"") -> 1LSCXLZ000YQI0M | C17: =IFERROR(VLOOKUP($A17,HeadJournal!$A$1:$NTR$890,COLUMN(HeadJournal!C$1),0),"") -> iHerb_AV CYG0792 | D17: =IFERROR(VLOOKUP($A17,HeadJournal!$A$1:$NTR$890,COLUMN(HeadJournal!D$1),0),"") -> Доставлен | E17: =IFERROR(VLOOKUP($A17,HeadJournal!$A$1:$NTR$890,COLUMN(HeadJournal!G$1),0),"") -> 44768 | F17: =IFERROR(TEXT(E17, "ГГГГ ММ"),"") -> 2022 07 | G17: Витамины | H17: =RIGHT(Journal!$J17,9) -> NOW-01650 | I17: =IFERROR(LEFT(J17,FIND(",",J17)-1),"") -> NOW Foods | J17: NOW Foods, жирные кислоты омега-3, 180 ЭПК / 120 ДГК, 100 капсул NOW-01650 | K17: 244.278 | L17: -34.317 | M17: =IFERROR(VLOOKUP($A17,HeadJournal!$A$1:$J$890,COLUMN(HeadJournal!I$1),0)*($K17+$L17)/(SUMIF($A:$A,$A17,$K:$K)+SUMIF($A:$A,$A17,$L:$L)),0) -> -64.569454 | N17: =IFERROR((VLOOKUP($A17,HeadJournal!$A$1:$K$890,COLUMN(HeadJournal!K$1),0)-VLOOKUP($A17,HeadJournal!$A$1:$K$890,COLUMN(HeadJournal!J$1),0))*($K17+$L17)/(SUMIF($A:$A,$A17,$K:$K)+SUMIF($A:$A,$A17,$L:$L)),0) -> 0.00045976083 | O17: =IFERROR((VLOOKUP($A17,HeadJournal!$A$1:$L$890,COLUMN(HeadJournal!L$1),0)*($K17+$L17)/(SUMIF($A:$A,$A17,$K:$K)+SUMIF($A:$A,$A17,$L:$L)))/VLOOKUP($A17,HeadJournal!$A$1:$L$890,COLUMN(HeadJournal!H$1),0),0) -> 104.73306 | P17: =IFERROR(SUM(K17:O17)*VLOOKUP($A17,HeadJournal!$A$1:$L$890,COLUMN(HeadJournal!H$1),0),0) -> 500.25012 | Q17: 1000 | R17: 44877 | S17: <Клиент не выбран> | T17: =IF(R17="","",TEXT(R17,"ГГГГ ММ")) -> 2022 11 | U17: =Q17-P17 -> 499.74988 | V17: =IF(Q17<>0,IFERROR(U17/P17,""),"") -> 0.999
A18: 920406036 | B18: =IFERROR(VLOOKUP($A18,HeadJournal!$A$1:$NTR$890,COLUMN(HeadJournal!B$1),0),"") -> 1LSCXLZ000YQI0M | C18: =IFERROR(VLOOKUP($A18,HeadJournal!$A$1:$NTR$890,COLUMN(HeadJournal!C$1),0),"") -> iHerb_AV CYG0792 | D18: =IFERROR(VLOOKUP($A18,HeadJournal!$A$1:$NTR$890,COLUMN(HeadJournal!D$1),0),"") -> Доставлен | E18: =IFERROR(VLOOKUP($A18,HeadJournal!$A$1:$NTR$890,COLUMN(HeadJournal!G$1),0),"") -> 44768 | F18: =IFERROR(TEXT(E18, "ГГГГ ММ"),"") -> 2022 07 | G18: Косметика | H18: MAV-14757 | I18: Mason Natural | J18: крем с коллагеном премиального качества, 57 г (2 унции) | K18: 188.19 | L18: -18.819 | M18: =IFERROR(VLOOKUP($A18,HeadJournal!$A$1:$J$890,COLUMN(HeadJournal!I$1),0)*($K18+$L18)/(SUMIF($A:$A,$A18,$K:$K)+SUMIF($A:$A,$A18,$L:$L)),0) -> -52.086783 | N18: =IFERROR((VLOOKUP($A18,HeadJournal!$A$1:$K$890,COLUMN(HeadJournal!K$1),0)-VLOOKUP($A18,HeadJournal!$A$1:$K$890,COLUMN(HeadJournal!J$1),0))*($K18+$L18)/(SUMIF($A:$A,$A18,$K:$K)+SUMIF($A:$A,$A18,$L:$L)),0) -> 0.00037087912 | O18: =IFERROR((VLOOKUP($A18,HeadJournal!$A$1:$L$890,COLUMN(HeadJournal!L$1),0)*($K18+$L18)/(SUMIF($A:$A,$A18,$K:$K)+SUMIF($A:$A,$A18,$L:$L)))/VLOOKUP($A18,HeadJournal!$A$1:$L$890,COLUMN(HeadJournal!H$1),0),0) -> 84.485893 | P18: =IFERROR(SUM(K18:O18)*VLOOKUP($A18,HeadJournal!$A$1:$L$890,COLUMN(HeadJournal!H$1),0),0) -> 403.54096 | Q18: 800 | R18: 44867 | S18: <Клиент не выбран> | T18: =IF(R18="","",TEXT(R18,"ГГГГ ММ")) -> 2022 11 | U18: =Q18-P18 -> 396.45904 | V18: =IF(Q18<>0,IFERROR(U18/P18,""),"") -> 0.98245055
A19: 920538149 | B19: =IFERROR(VLOOKUP($A19,HeadJournal!$A$1:$NTR$890,COLUMN(HeadJournal!B$1),0),"") -> 1LSCXLZ000Z8LTB | C19: =IFERROR(VLOOKUP($A19,HeadJournal!$A$1:$NTR$890,COLUMN(HeadJournal!C$1),0),"") -> iHerb_VP DFD1605 | D19: =IFERROR(VLOOKUP($A19,HeadJournal!$A$1:$NTR$890,COLUMN(HeadJournal!D$1),0),"") -> Доставлен | E19: =IFERROR(VLOOKUP($A19,HeadJournal!$A$1:$NTR$890,COLUMN(HeadJournal!G$1),0),"") -> 44777 | F19: =IFERROR(TEXT(E19, "ГГГГ ММ"),"") -> 2022 08 | G19: Витамины | H19: =RIGHT(Journal!$J19,9) -> CGN-01066 | I19: =IFERROR(LEFT(J19,FIND(",",J19)-1),"") -> California Gold Nutrition | J19: California Gold Nutrition, витамин D3, 125 мкг (5000 МЕ), 360 капсул из рыбьего желатина CGN-01066 | K19: 251.6 | L19: -214.6 | M19: =IFERROR(VLOOKUP($A19,HeadJournal!$A$1:$J$890,COLUMN(HeadJournal!I$1),0)*($K19+$L19)/(SUMIF($A:$A,$A19,$K:$K)+SUMIF($A:$A,$A19,$L:$L)),0) -> -4.2805362 | N19: =IFERROR((VLOOKUP($A19,HeadJournal!$A$1:$K$890,COLUMN(HeadJournal!K$1),0)-VLOOKUP($A19,HeadJournal!$A$1:$K$890,COLUMN(HeadJournal!J$1),0))*($K19+$L19)/(SUMIF($A:$A,$A19,$K:$K)+SUMIF($A:$A,$A19,$L:$L)),0) -> 3.7632187e-15 | O19: =IFERROR((VLOOKUP($A19,HeadJournal!$A$1:$L$890,COLUMN(HeadJournal!L$1),0)*($K19+$L19)/(SUMIF($A:$A,$A19,$K:$K)+SUMIF($A:$A,$A19,$L:$L)))/VLOOKUP($A19,HeadJournal!$A$1:$L$890,COLUMN(HeadJournal!H$1),0),0) -> 25.135055 | P19: =IFERROR(SUM(K19:O19)*VLOOKUP($A19,HeadJournal!$A$1:$L$890,COLUMN(HeadJournal!H$1),0),0) -> 86.781778 | Q19: 1500 | R19: 44869 | S19: <Клиент не выбран> | T19: =IF(R19="","",TEXT(R19,"ГГГГ ММ")) -> 2022 11 | U19: =Q19-P19 -> 1413.2182 | V19: =IF(Q19<>0,IFERROR(U19/P19,""),"") -> 16.284735
A20: 920538149 | B20: =IFERROR(VLOOKUP($A20,HeadJournal!$A$1:$NTR$890,COLUMN(HeadJournal!B$1),0),"") -> 1LSCXLZ000Z8LTB | C20: =IFERROR(VLOOKUP($A20,HeadJournal!$A$1:$NTR$890,COLUMN(HeadJournal!C$1),0),"") -> iHerb_VP DFD1605 | D20: =IFERROR(VLOOKUP($A20,HeadJournal!$A$1:$NTR$890,COLUMN(HeadJournal!D$1),0),"") -> Доставлен | E20: =IFERROR(VLOOKUP($A20,HeadJournal!$A$1:$NTR$890,COLUMN(HeadJournal!G$1),0),"") -> 44777 | F20: =IFERROR(TEXT(E20, "ГГГГ ММ"),"") -> 2022 08 | G20: Витамины | H20: CGN-01033 | I20: California Gold Nutrition | J20: CollagenUP®, гидролизованные пептиды морского коллагена с гиалуроновой кислотой и витамином C, с нейтральным вкусом, 206 г (7,26 унции) | K20: 629 | L20: -125.8 | M20: =IFERROR(VLOOKUP($A20,HeadJournal!$A$1:$J$890,COLUMN(HeadJournal!I$1),0)*($K20+$L20)/(SUMIF($A:$A,$A20,$K:$K)+SUMIF($A:$A,$A20,$L:$L)),0) -> -58.215293 | N20: =IFERROR((VLOOKUP($A20,HeadJournal!$A$1:$K$890,COLUMN(HeadJournal!K$1),0)-VLOOKUP($A20,HeadJournal!$A$1:$K$890,COLUMN(HeadJournal!J$1),0))*($K20+$L20)/(SUMIF($A:$A,$A20,$K:$K)+SUMIF($A:$A,$A20,$L:$L)),0) -> 5.1179775e-14 | O20: =IFERROR((VLOOKUP($A20,HeadJournal!$A$1:$L$890,COLUMN(HeadJournal!L$1),0)*($K20+$L20)/(SUMIF($A:$A,$A20,$K:$K)+SUMIF($A:$A,$A20,$L:$L)))/VLOOKUP($A20,HeadJournal!$A$1:$L$890,COLUMN(HeadJournal!H$1),0),0) -> 341.83674 | P20: =IFERROR(SUM(K20:O20)*VLOOKUP($A20,HeadJournal!$A$1:$L$890,COLUMN(HeadJournal!H$1),0),0) -> 1180.2322 | Q20: 2100 | R20: 45113 | S20: <Клиент не выбран> | T20: =IF(R20="","",TEXT(R20,"ГГГГ ММ")) -> 2023 07 | U20: =Q20-P20 -> 919.76783 | V20: =IF(Q20<>0,IFERROR(U20/P20,""),"") -> 0.77931092
A21: 920538149 | B21: =IFERROR(VLOOKUP($A21,HeadJournal!$A$1:$NTR$890,COLUMN(HeadJournal!B$1),0),"") -> 1LSCXLZ000Z8LTB | C21: =IFERROR(VLOOKUP($A21,HeadJournal!$A$1:$NTR$890,COLUMN(HeadJournal!C$1),0),"") -> iHerb_VP DFD1605 | D21: =IFERROR(VLOOKUP($A21,HeadJournal!$A$1:$NTR$890,COLUMN(HeadJournal!D$1),0),"") -> Доставлен | E21: =IFERROR(VLOOKUP($A21,HeadJournal!$A$1:$NTR$890,COLUMN(HeadJournal!G$1),0),"") -> 44777 | F21: =IFERROR(TEXT(E21, "ГГГГ ММ"),"") -> 2022 08 | G21: Витамины | H21: CGN-01033 | I21: California Gold Nutrition | J21: CollagenUP®, гидролизованные пептиды морского коллагена с гиалуроновой кислотой и витамином C, с нейтральным вкусом, 206 г (7,26 унции) | K21: 629 | L21: -125.8 | M21: =IFERROR(VLOOKUP($A21,HeadJournal!$A$1:$J$890,COLUMN(HeadJournal!I$1),0)*($K21+$L21)/(SUMIF($A:$A,$A21,$K:$K)+SUMIF($A:$A,$A21,$L:$L)),0) -> -58.215293 | N21: =IFERROR((VLOOKUP($A21,HeadJournal!$A$1:$K$890,COLUMN(HeadJournal!K$1),0)-VLOOKUP($A21,HeadJournal!$A$1:$K$890,COLUMN(HeadJournal!J$1),0))*($K21+$L21)/(SUMIF($A:$A,$A21,$K:$K)+SUMIF($A:$A,$A21,$L:$L)),0) -> 5.1179775e-14 | O21: =IFERROR((VLOOKUP($A21,HeadJournal!$A$1:$L$890,COLUMN(HeadJournal!L$1),0)*($K21+$L21)/(SUMIF($A:$A,$A21,$K:$K)+SUMIF($A:$A,$A21,$L:$L)))/VLOOKUP($A21,HeadJournal!$A$1:$L$890,COLUMN(HeadJournal!H$1),0),0) -> 341.83674 | P21: =IFERROR(SUM(K21:O21)*VLOOKUP($A21,HeadJournal!$A$1:$L$890,COLUMN(HeadJournal!H$1),0),0) -> 1180.2322 | Q21: 2100 | R21: 45139 | S21: <Клиент не выбран> | T21: =IF(R21="","",TEXT(R21,"ГГГГ ММ")) -> 2023 08 | U21: =Q21-P21 -> 919.76783 | V21: =IF(Q21<>0,IFERROR(U21/P21,""),"") -> 0.77931092
A22: 920538149 | B22: =IFERROR(VLOOKUP($A22,HeadJournal!$A$1:$NTR$890,COLUMN(HeadJournal!B$1),0),"") -> 1LSCXLZ000Z8LTB | C22: =IFERROR(VLOOKUP($A22,HeadJournal!$A$1:$NTR$890,COLUMN(HeadJournal!C$1),0),"") -> iHerb_VP DFD1605 | D22: =IFERROR(VLOOKUP($A22,HeadJournal!$A$1:$NTR$890,COLUMN(HeadJournal!D$1),0),"") -> Доставлен | E22: =IFERROR(VLOOKUP($A22,HeadJournal!$A$1:$NTR$890,COLUMN(HeadJournal!G$1),0),"") -> 44777 | F22: =IFERROR(TEXT(E22, "ГГГГ ММ"),"") -> 2022 08 | G22: Витамины | H22: MLI-00952 | I22: California Gold Nutrition | J22: премиальный рыбий жир с омега-3, 100 капсул из рыбьего желатина (1100 мг в 1 капсуле) | K22: 259 | L22: -125.985 | M22: =IFERROR(VLOOKUP($A22,HeadJournal!$A$1:$J$890,COLUMN(HeadJournal!I$1),0)*($K22+$L22)/(SUMIF($A:$A,$A22,$K:$K)+SUMIF($A:$A,$A22,$L:$L)),0) -> -15.388528 | N22: =IFERROR((VLOOKUP($A22,HeadJournal!$A$1:$K$890,COLUMN(HeadJournal!K$1),0)-VLOOKUP($A22,HeadJournal!$A$1:$K$890,COLUMN(HeadJournal!J$1),0))*($K22+$L22)/(SUMIF($A:$A,$A22,$K:$K)+SUMIF($A:$A,$A22,$L:$L)),0) -> 1.3528771e-14 | O22: =IFERROR((VLOOKUP($A22,HeadJournal!$A$1:$L$890,COLUMN(HeadJournal!L$1),0)*($K22+$L22)/(SUMIF($A:$A,$A22,$K:$K)+SUMIF($A:$A,$A22,$L:$L)))/VLOOKUP($A22,HeadJournal!$A$1:$L$890,COLUMN(HeadJournal!H$1),0),0) -> 90.360521 | P22: =IFERROR(SUM(K22:O22)*VLOOKUP($A22,HeadJournal!$A$1:$L$890,COLUMN(HeadJournal!H$1),0),0) -> 311.98049 | Q22: 1000 | R22: 45054 | S22: <Клиент не выбран> | T22: =IF(R22="","",TEXT(R22,"ГГГГ ММ")) -> 2023 05 | U22: =Q22-P22 -> 688.01951 | V22: =IF(Q22<>0,IFERROR(U22/P22,""),"") -> 2.2053286
A23: 920538149 | B23: =IFERROR(VLOOKUP($A23,HeadJournal!$A$1:$NTR$890,COLUMN(HeadJournal!B$1),0),"") -> 1LSCXLZ000Z8LTB | C23: =IFERROR(VLOOKUP($A23,HeadJournal!$A$1:$NTR$890,COLUMN(HeadJournal!C$1),0),"") -> iHerb_VP DFD1605 | D23: =IFERROR(VLOOKUP($A23,HeadJournal!$A$1:$NTR$890,COLUMN(HeadJournal!D$1),0),"") -> Доставлен | E23: =IFERROR(VLOOKUP($A23,HeadJournal!$A$1:$NTR$890,COLUMN(HeadJournal!G$1),0),"") -> 44777 | F23: =IFERROR(TEXT(E23, "ГГГГ ММ"),"") -> 2022 08 | G23: Витамины | H23: MLI-00952 | I23: California Gold Nutrition | J23: премиальный рыбий жир с омега-3, 100 капсул из рыбьего желатина (1100 мг в 1 капсуле) | K23: 259 | L23: -125.985 | M23: =IFERROR(VLOOKUP($A23,HeadJournal!$A$1:$J$890,COLUMN(HeadJournal!I$1),0)*($K23+$L23)/(SUMIF($A:$A,$A23,$K:$K)+SUMIF($A:$A,$A23,$L:$L)),0) -> -15.388528 | N23: =IFERROR((VLOOKUP($A23,HeadJournal!$A$1:$K$890,COLUMN(HeadJournal!K$1),0)-VLOOKUP($A23,HeadJournal!$A$1:$K$890,COLUMN(HeadJournal!J$1),0))*($K23+$L23)/(SUMIF($A:$A,$A23,$K:$K)+SUMIF($A:$A,$A23,$L:$L)),0) -> 1.3528771e-14 | O23: =IFERROR((VLOOKUP($A23,HeadJournal!$A$1:$L$890,COLUMN(HeadJournal!L$1),0)*($K23+$L23)/(SUMIF($A:$A,$A23,$K:$K)+SUMIF($A:$A,$A23,$L:$L)))/VLOOKUP($A23,HeadJournal!$A$1:$L$890,COLUMN(HeadJournal!H$1),0),0) -> 90.360521 | P23: =IFERROR(SUM(K23:O23)*VLOOKUP($A23,HeadJournal!$A$1:$L$890,COLUMN(HeadJournal!H$1),0),0) -> 311.98049 | Q23: 1000 | R23: 45054 | S23: <Клиент не выбран> | T23: =IF(R23="","",TEXT(R23,"ГГГГ ММ")) -> 2023 05 | U23: =Q23-P23 -> 688.01951 | V23: =IF(Q23<>0,IFERROR(U23/P23,""),"") -> 2.2053286
A24: 920538149 | B24: =IFERROR(VLOOKUP($A24,HeadJournal!$A$1:$NTR$890,COLUMN(HeadJournal!B$1),0),"") -> 1LSCXLZ000Z8LTB | C24: =IFERROR(VLOOKUP($A24,HeadJournal!$A$1:$NTR$890,COLUMN(HeadJournal!C$1),0),"") -> iHerb_VP DFD1605 | D24: =IFERROR(VLOOKUP($A24,HeadJournal!$A$1:$NTR$890,COLUMN(HeadJournal!D$1),0),"") -> Доставлен | E24: =IFERROR(VLOOKUP($A24,HeadJournal!$A$1:$NTR$890,COLUMN(HeadJournal!G$1),0),"") -> 44777 | F24: =IFERROR(TEXT(E24, "ГГГГ ММ"),"") -> 2022 08 | G24: Косметика | H24: =RIGHT(Journal!$J24,9) -> SKE-99153 | I24: =IFERROR(LEFT(J24,FIND(",",J24)-1),"") -> Secret Key | J24: Secret Key, Освежающий успокаивающий тоник Tea Tree, 248 мл (8,38 жидк. Унции) SKE-99153 | K24: 310.8 | L24: -59.2 | M24: =IFERROR(VLOOKUP($A24,HeadJournal!$A$1:$J$890,COLUMN(HeadJournal!I$1),0)*($K24+$L24)/(SUMIF($A:$A,$A24,$K:$K)+SUMIF($A:$A,$A24,$L:$L)),0) -> -29.107646 | N24: =IFERROR((VLOOKUP($A24,HeadJournal!$A$1:$K$890,COLUMN(HeadJournal!K$1),0)-VLOOKUP($A24,HeadJournal!$A$1:$K$890,COLUMN(HeadJournal!J$1),0))*($K24+$L24)/(SUMIF($A:$A,$A24,$K:$K)+SUMIF($A:$A,$A24,$L:$L)),0) -> 2.5589887e-14 | O24: =IFERROR((VLOOKUP($A24,HeadJournal!$A$1:$L$890,COLUMN(HeadJournal!L$1),0)*($K24+$L24)/(SUMIF($A:$A,$A24,$K:$K)+SUMIF($A:$A,$A24,$L:$L)))/VLOOKUP($A24,HeadJournal!$A$1:$L$890,COLUMN(HeadJournal!H$1),0),0) -> 170.91837 | P24: =IFERROR(SUM(K24:O24)*VLOOKUP($A24,HeadJournal!$A$1:$L$890,COLUMN(HeadJournal!H$1),0),0) -> 590.11609 | Q24: 900 | R24: 44868 | S24: <Клиент не выбран> | T24: =IF(R24="","",TEXT(R24,"ГГГГ ММ")) -> 2022 11 | U24: =Q24-P24 -> 309.88391 | V24: =IF(Q24<>0,IFERROR(U24/P24,""),"") -> 0.52512365
A25: 920538149 | B25: =IFERROR(VLOOKUP($A25,HeadJournal!$A$1:$NTR$890,COLUMN(HeadJournal!B$1),0),"") -> 1LSCXLZ000Z8LTB | C25: =IFERROR(VLOOKUP($A25,HeadJournal!$A$1:$NTR$890,COLUMN(HeadJournal!C$1),0),"") -> iHerb_VP DFD1605 | D25: =IFERROR(VLOOKUP($A25,HeadJournal!$A$1:$NTR$890,COLUMN(HeadJournal!D$1),0),"") -> Доставлен | E25: =IFERROR(VLOOKUP($A25,HeadJournal!$A$1:$NTR$890,COLUMN(HeadJournal!G$1),0),"") -> 44777 | F25: =IFERROR(TEXT(E25, "ГГГГ ММ"),"") -> 2022 08 | G25: Витамины | H25: NOW-00372 | I25: NOW Foods | J25: витамин D3, высокоактивный, 125 мкг (5000 МЕ), 120 мягких таблеток | K25: 213.86 | L25: -42.92 | M25: =IFERROR(VLOOKUP($A25,HeadJournal!$A$1:$J$890,COLUMN(HeadJournal!I$1),0)*($K25+$L25)/(SUMIF($A:$A,$A25,$K:$K)+SUMIF($A:$A,$A25,$L:$L)),0) -> -19.776077 | N25: =IFERROR((VLOOKUP($A25,HeadJournal!$A$1:$K$890,COLUMN(HeadJournal!K$1),0)-VLOOKUP($A25,HeadJournal!$A$1:$K$890,COLUMN(HeadJournal!J$1),0))*($K25+$L25)/(SUMIF($A:$A,$A25,$K:$K)+SUMIF($A:$A,$A25,$L:$L)),0) -> 1.7386071e-14 | O25: =IFERROR((VLOOKUP($A25,HeadJournal!$A$1:$L$890,COLUMN(HeadJournal!L$1),0)*($K25+$L25)/(SUMIF($A:$A,$A25,$K:$K)+SUMIF($A:$A,$A25,$L:$L)))/VLOOKUP($A25,HeadJournal!$A$1:$L$890,COLUMN(HeadJournal!H$1),0),0) -> 116.12395 | P25: =IFERROR(SUM(K25:O25)*VLOOKUP($A25,HeadJournal!$A$1:$L$890,COLUMN(HeadJournal!H$1),0),0) -> 400.93181 | Q25: 1000 | R25: 44869 | S25: <Клиент не выбран> | T25: =IF(R25="","",TEXT(R25,"ГГГГ ММ")) -> 2022 11 | U25: =Q25-P25 -> 599.06819 | V25: =IF(Q25<>0,IFERROR(U25/P25,""),"") -> 1.4941897
A26: 920538149 | B26: =IFERROR(VLOOKUP($A26,HeadJournal!$A$1:$NTR$890,COLUMN(HeadJournal!B$1),0),"") -> 1LSCXLZ000Z8LTB | C26: =IFERROR(VLOOKUP($A26,HeadJournal!$A$1:$NTR$890,COLUMN(HeadJournal!C$1),0),"") -> iHerb_VP DFD1605 | D26: =IFERROR(VLOOKUP($A26,HeadJournal!$A$1:$NTR$890,COLUMN(HeadJournal!D$1),0),"") -> Доставлен | E26: =IFERROR(VLOOKUP($A26,HeadJournal!$A$1:$NTR$890,COLUMN(HeadJournal!G$1),0),"") -> 44777 | F26: =IFERROR(TEXT(E26, "ГГГГ ММ"),"") -> 2022 08 | G26: Витамины | H26: CGN-01065 | I26: California Gold Nutrition | J26: витамин D3, 125 мкг (5000 МЕ), 90 капсул из рыбьего желатина | K26: 222 | L26: -111 | M26: =IFERROR(VLOOKUP($A26,HeadJournal!$A$1:$J$890,COLUMN(HeadJournal!I$1),0)*($K26+$L26)/(SUMIF($A:$A,$A26,$K:$K)+SUMIF($A:$A,$A26,$L:$L)),0) -> -12.841609 | N26: =IFERROR((VLOOKUP($A26,HeadJournal!$A$1:$K$890,COLUMN(HeadJournal!K$1),0)-VLOOKUP($A26,HeadJournal!$A$1:$K$890,COLUMN(HeadJournal!J$1),0))*($K26+$L26)/(SUMIF($A:$A,$A26,$K:$K)+SUMIF($A:$A,$A26,$L:$L)),0) -> 1.1289656e-14 | O26: =IFERROR((VLOOKUP($A26,HeadJournal!$A$1:$L$890,COLUMN(HeadJournal!L$1),0)*($K26+$L26)/(SUMIF($A:$A,$A26,$K:$K)+SUMIF($A:$A,$A26,$L:$L)))/VLOOKUP($A26,HeadJournal!$A$1:$L$890,COLUMN(HeadJournal!H$1),0),0) -> 75.405164 | P26: =IFERROR(SUM(K26:O26)*VLOOKUP($A26,HeadJournal!$A$1:$L$890,COLUMN(HeadJournal!H$1),0),0) -> 260.34533 | Q26: 700 | R26: 44871 | S26: <Клиент не выбран> | T26: =IF(R26="","",TEXT(R26,"ГГГГ ММ")) -> 2022 11 | U26: =Q26-P26 -> 439.65467 | V26: =IF(Q26<>0,IFERROR(U26/P26,""),"") -> 1.6887365
A27: 920538149 | B27: =IFERROR(VLOOKUP($A27,HeadJournal!$A$1:$NTR$890,COLUMN(HeadJournal!B$1),0),"") -> 1LSCXLZ000Z8LTB | C27: =IFERROR(VLOOKUP($A27,HeadJournal!$A$1:$NTR$890,COLUMN(HeadJournal!C$1),0),"") -> iHerb_VP DFD1605 | D27: =IFERROR(VLOOKUP($A27,HeadJournal!$A$1:$NTR$890,COLUMN(HeadJournal!D$1),0),"") -> Доставлен | E27: =IFERROR(VLOOKUP($A27,HeadJournal!$A$1:$NTR$890,COLUMN(HeadJournal!G$1),0),"") -> 44777 | F27: =IFERROR(TEXT(E27, "ГГГГ ММ"),"") -> 2022 08 | G27: Витамины | H27: =RIGHT(Journal!$J27,9) -> CEN-22713 | I27: =IFERROR(LEFT(J27,FIND(",",J27)-1),"") -> 21st Century | J27: 21st Century, магний, 250 мг, 110 таблеток CEN-22713 | K27: 103.6 | L27: -10.36 | M27: =IFERROR(VLOOKUP($A27,HeadJournal!$A$1:$J$890,COLUMN(HeadJournal!I$1),0)*($K27+$L27)/(SUMIF($A:$A,$A27,$K:$K)+SUMIF($A:$A,$A27,$L:$L)),0) -> -10.786951 | N27: =IFERROR((VLOOKUP($A27,HeadJournal!$A$1:$K$890,COLUMN(HeadJournal!K$1),0)-VLOOKUP($A27,HeadJournal!$A$1:$K$890,COLUMN(HeadJournal!J$1),0))*($K27+$L27)/(SUMIF($A:$A,$A27,$K:$K)+SUMIF($A:$A,$A27,$L:$L)),0) -> 9.4833112e-15 | O27: =IFERROR((VLOOKUP($A27,HeadJournal!$A$1:$L$890,COLUMN(HeadJournal!L$1),0)*($K27+$L27)/(SUMIF($A:$A,$A27,$K:$K)+SUMIF($A:$A,$A27,$L:$L)))/VLOOKUP($A27,HeadJournal!$A$1:$L$890,COLUMN(HeadJournal!H$1),0),0) -> 63.340338 | P27: =IFERROR(SUM(K27:O27)*VLOOKUP($A27,HeadJournal!$A$1:$L$890,COLUMN(HeadJournal!H$1),0),0) -> 218.69008 | Q27: 1200 | R27: 44871 | S27: <Клиент не выбран> | T27: =IF(R27="","",TEXT(R27,"ГГГГ ММ")) -> 2022 11 | U27: =Q27-P27 -> 981.30992 | V27: =IF(Q27<>0,IFERROR(U27/P27,""),"") -> 4.4872174
A28: 920538149 | B28: =IFERROR(VLOOKUP($A28,HeadJournal!$A$1:$NTR$890,COLUMN(HeadJournal!B$1),0),"") -> 1LSCXLZ000Z8LTB | C28: =IFERROR(VLOOKUP($A28,HeadJournal!$A$1:$NTR$890,COLUMN(HeadJournal!C$1),0),"") -> iHerb_VP DFD1605 | D28: =IFERROR(VLOOKUP($A28,HeadJournal!$A$1:$NTR$890,COLUMN(HeadJournal!D$1),0),"") -> Доставлен | E28: =IFERROR(VLOOKUP($A28,HeadJournal!$A$1:$NTR$890,COLUMN(HeadJournal!G$1),0),"") -> 44777 | F28: =IFERROR(TEXT(E28, "ГГГГ ММ"),"") -> 2022 08 | G28: Витамины | H28: DRB-00091 | I28: Doctor's Best | J28: гинкго с повышенной силой действия, 120 мг, 120 вегетарианских капсул | K28: 332.26 | L28: -32.93 | M28: =IFERROR(VLOOKUP($A28,HeadJournal!$A$1:$J$890,COLUMN(HeadJournal!I$1),0)*($K28+$L28)/(SUMIF($A:$A,$A28,$K:$K)+SUMIF($A:$A,$A28,$L:$L)),0) -> -34.629538 | N28: =IFERROR((VLOOKUP($A28,HeadJournal!$A$1:$K$890,COLUMN(HeadJournal!K$1),0)-VLOOKUP($A28,HeadJournal!$A$1:$K$890,COLUMN(HeadJournal!J$1),0))*($K28+$L28)/(SUMIF($A:$A,$A28,$K:$K)+SUMIF($A:$A,$A28,$L:$L)),0) -> 3.0444439e-14 | O28: =IFERROR((VLOOKUP($A28,HeadJournal!$A$1:$L$890,COLUMN(HeadJournal!L$1),0)*($K28+$L28)/(SUMIF($A:$A,$A28,$K:$K)+SUMIF($A:$A,$A28,$L:$L)))/VLOOKUP($A28,HeadJournal!$A$1:$L$890,COLUMN(HeadJournal!H$1),0),0) -> 203.34259 | P28: =IFERROR(SUM(K28:O28)*VLOOKUP($A28,HeadJournal!$A$1:$L$890,COLUMN(HeadJournal!H$1),0),0) -> 702.06458 | Q28: 1500 | R28: 44894 | S28: <Клиент не выбран> | T28: =IF(R28="","",TEXT(R28,"ГГГГ ММ")) -> 2022 11 | U28: =Q28-P28 -> 797.93542 | V28: =IF(Q28<>0,IFERROR(U28/P28,""),"") -> 1.1365556
A29: 920706319 | B29: =IFERROR(VLOOKUP($A29,HeadJournal!$A$1:$NTR$890,COLUMN(HeadJournal!B$1),0),"") -> IHORD0000446652NPG | C29: =IFERROR(VLOOKUP($A29,HeadJournal!$A$1:$NTR$890,COLUMN(HeadJournal!C$1),0),"") -> iHerb_MH DLE7202 | D29: =IFERROR(VLOOKUP($A29,HeadJournal!$A$1:$NTR$890,COLUMN(HeadJournal!D$1),0),"") -> Доставлен | E29: =IFERROR(VLOOKUP($A29,HeadJournal!$A$1:$NTR$890,COLUMN(HeadJournal!G$1),0),"") -> 44788 | F29: =IFERROR(TEXT(E29, "ГГГГ ММ"),"") -> 2022 08 | G29: Витамины | H29: LEX-23151 | I29: Life Extension | J29: Мультивитамины для двух приемов в день, 120 таблеток | K29: 713.84 | L29: -71.38 | M29: =IFERROR(VLOOKUP($A29,HeadJournal!$A$1:$J$890,COLUMN(HeadJournal!I$1),0)*($K29+$L29)/(SUMIF($A:$A,$A29,$K:$K)+SUMIF($A:$A,$A29,$L:$L)),0) -> -101.40832 | N29: =IFERROR((VLOOKUP($A29,HeadJournal!$A$1:$K$890,COLUMN(HeadJournal!K$1),0)-VLOOKUP($A29,HeadJournal!$A$1:$K$890,COLUMN(HeadJournal!J$1),0))*($K29+$L29)/(SUMIF($A:$A,$A29,$K:$K)+SUMIF($A:$A,$A29,$L:$L)),0) -> 13.755906 | O29: =IFERROR((VLOOKUP($A29,HeadJournal!$A$1:$L$890,COLUMN(HeadJournal!L$1),0)*($K29+$L29)/(SUMIF($A:$A,$A29,$K:$K)+SUMIF($A:$A,$A29,$L:$L)))/VLOOKUP($A29,HeadJournal!$A$1:$L$890,COLUMN(HeadJournal!H$1),0),0) -> 99.658812 | P29: =IFERROR(SUM(K29:O29)*VLOOKUP($A29,HeadJournal!$A$1:$L$890,COLUMN(HeadJournal!H$1),0),0) -> 981.69959 | Q29: 2200 | R29: 44821 | S29: <Клиент не выбран> | T29: =IF(R29="","",TEXT(R29,"ГГГГ ММ")) -> 2022 09 | U29: =Q29-P29 -> 1218.3004 | V29: =IF(Q29<>0,IFERROR(U29/P29,""),"") -> 1.2410114
A30: 920706319 | B30: =IFERROR(VLOOKUP($A30,HeadJournal!$A$1:$NTR$890,COLUMN(HeadJournal!B$1),0),"") -> IHORD0000446652NPG | C30: =IFERROR(VLOOKUP($A30,HeadJournal!$A$1:$NTR$890,COLUMN(HeadJournal!C$1),0),"") -> iHerb_MH DLE7202 | D30: =IFERROR(VLOOKUP($A30,HeadJournal!$A$1:$NTR$890,COLUMN(HeadJournal!D$1),0),"") -> Доставлен | E30: =IFERROR(VLOOKUP($A30,HeadJournal!$A$1:$NTR$890,COLUMN(HeadJournal!G$1),0),"") -> 44788 | F30: =IFERROR(TEXT(E30, "ГГГГ ММ"),"") -> 2022 08 | G30: Витамины | H30: =RIGHT(Journal!$J30,9) -> LEX-23166 | I30: =IFERROR(LEFT(J30,FIND(",",J30)-1),"") -> Life Extension | J30: Life Extension, таблетки для приема дважды в день, 60 таблеток LEX-23166 | K30: 387.16 | L30: -38.74 | M30: =IFERROR(VLOOKUP($A30,HeadJournal!$A$1:$J$890,COLUMN(HeadJournal!I$1),0)*($K30+$L30)/(SUMIF($A:$A,$A30,$K:$K)+SUMIF($A:$A,$A30,$L:$L)),0) -> -54.995934 | N30: =IFERROR((VLOOKUP($A30,HeadJournal!$A$1:$K$890,COLUMN(HeadJournal!K$1),0)-VLOOKUP($A30,HeadJournal!$A$1:$K$890,COLUMN(HeadJournal!J$1),0))*($K30+$L30)/(SUMIF($A:$A,$A30,$K:$K)+SUMIF($A:$A,$A30,$L:$L)),0) -> 7.4601263 | O30: =IFERROR((VLOOKUP($A30,HeadJournal!$A$1:$L$890,COLUMN(HeadJournal!L$1),0)*($K30+$L30)/(SUMIF($A:$A,$A30,$K:$K)+SUMIF($A:$A,$A30,$L:$L)))/VLOOKUP($A30,HeadJournal!$A$1:$L$890,COLUMN(HeadJournal!H$1),0),0) -> 54.047137 | P30: =IFERROR(SUM(K30:O30)*VLOOKUP($A30,HeadJournal!$A$1:$L$890,COLUMN(HeadJournal!H$1),0),0) -> 532.39699 | Q30: 1500 | R30: 44821 | S30: <Клиент не выбран> | T30: =IF(R30="","",TEXT(R30,"ГГГГ ММ")) -> 2022 09 | U30: =Q30-P30 -> 967.60301 | V30: =IF(Q30<>0,IFERROR(U30/P30,""),"") -> 1.8174464
A31: 920706319 | B31: =IFERROR(VLOOKUP($A31,HeadJournal!$A$1:$NTR$890,COLUMN(HeadJournal!B$1),0),"") -> IHORD0000446652NPG | C31: =IFERROR(VLOOKUP($A31,HeadJournal!$A$1:$NTR$890,COLUMN(HeadJournal!C$1),0),"") -> iHerb_MH DLE7202 | D31: =IFERROR(VLOOKUP($A31,HeadJournal!$A$1:$NTR$890,COLUMN(HeadJournal!D$1),0),"") -> Доставлен | E31: =IFERROR(VLOOKUP($A31,HeadJournal!$A$1:$NTR$890,COLUMN(HeadJournal!G$1),0),"") -> 44788 | F31: =IFERROR(TEXT(E31, "ГГГГ ММ"),"") -> 2022 08 | G31: Витамины | H31: NBC-00450 | I31: NutriBiotic | J31: Immunity, аскорбат натрия, кристаллический порошок, 227 г (8 унций) | K31: 389.25 | L31: -38.925 | M31: =IFERROR(VLOOKUP($A31,HeadJournal!$A$1:$J$890,COLUMN(HeadJournal!I$1),0)*($K31+$L31)/(SUMIF($A:$A,$A31,$K:$K)+SUMIF($A:$A,$A31,$L:$L)),0) -> -55.296626 | N31: =IFERROR((VLOOKUP($A31,HeadJournal!$A$1:$K$890,COLUMN(HeadJournal!K$1),0)-VLOOKUP($A31,HeadJournal!$A$1:$K$890,COLUMN(HeadJournal!J$1),0))*($K31+$L31)/(SUMIF($A:$A,$A31,$K:$K)+SUMIF($A:$A,$A31,$L:$L)),0) -> 7.5009148 | O31: =IFERROR((VLOOKUP($A31,HeadJournal!$A$1:$L$890,COLUMN(HeadJournal!L$1),0)*($K31+$L31)/(SUMIF($A:$A,$A31,$K:$K)+SUMIF($A:$A,$A31,$L:$L)))/VLOOKUP($A31,HeadJournal!$A$1:$L$890,COLUMN(HeadJournal!H$1),0),0) -> 54.342641 | P31: =IFERROR(SUM(K31:O31)*VLOOKUP($A31,HeadJournal!$A$1:$L$890,COLUMN(HeadJournal!H$1),0),0) -> 535.30789 | Q31: 1700 | R31: 44804 | S31: <Клиент не выбран> | T31: =IF(R31="","",TEXT(R31,"ГГГГ ММ")) -> 2022 08 | U31: =Q31-P31 -> 1164.6921 | V31: =IF(Q31<>0,IFERROR(U31/P31,""),"") -> 2.1757424
A32: 920706319 | B32: =IFERROR(VLOOKUP($A32,HeadJournal!$A$1:$NTR$890,COLUMN(HeadJournal!B$1),0),"") -> IHORD0000446652NPG | C32: =IFERROR(VLOOKUP($A32,HeadJournal!$A$1:$NTR$890,COLUMN(HeadJournal!C$1),0),"") -> iHerb_MH DLE7202 | D32: =IFERROR(VLOOKUP($A32,HeadJournal!$A$1:$NTR$890,COLUMN(HeadJournal!D$1),0),"") -> Доставлен | E32: =IFERROR(VLOOKUP($A32,HeadJournal!$A$1:$NTR$890,COLUMN(HeadJournal!G$1),0),"") -> 44788 | F32: =IFERROR(TEXT(E32, "ГГГГ ММ"),"") -> 2022 08 | G32: Витамины | H32: NBC-00450 | I32: NutriBiotic | J32: Immunity, аскорбат натрия, кристаллический порошок, 227 г (8 унций) | K32: 389.25 | L32: -38.925 | M32: =IFERROR(VLOOKUP($A32,HeadJournal!$A$1:$J$890,COLUMN(HeadJournal!I$1),0)*($K32+$L32)/(SUMIF($A:$A,$A32,$K:$K)+SUMIF($A:$A,$A32,$L:$L)),0) -> -55.296626 | N32: =IFERROR((VLOOKUP($A32,HeadJournal!$A$1:$K$890,COLUMN(HeadJournal!K$1),0)-VLOOKUP($A32,HeadJournal!$A$1:$K$890,COLUMN(HeadJournal!J$1),0))*($K32+$L32)/(SUMIF($A:$A,$A32,$K:$K)+SUMIF($A:$A,$A32,$L:$L)),0) -> 7.5009148 | O32: =IFERROR((VLOOKUP($A32,HeadJournal!$A$1:$L$890,COLUMN(HeadJournal!L$1),0)*($K32+$L32)/(SUMIF($A:$A,$A32,$K:$K)+SUMIF($A:$A,$A32,$L:$L)))/VLOOKUP($A32,HeadJournal!$A$1:$L$890,COLUMN(HeadJournal!H$1),0),0) -> 54.342641 | P32: =IFERROR(SUM(K32:O32)*VLOOKUP($A32,HeadJournal!$A$1:$L$890,COLUMN(HeadJournal!H$1),0),0) -> 535.30789 | Q32: 1700 | R32: 44804 | S32: <Клиент не выбран> | T32: =IF(R32="","",TEXT(R32,"ГГГГ ММ")) -> 2022 08 | U32: =Q32-P32 -> 1164.6921 | V32: =IF(Q32<>0,IFERROR(U32/P32,""),"") -> 2.1757424
A33: 920706319 | B33: =IFERROR(VLOOKUP($A33,HeadJournal!$A$1:$NTR$890,COLUMN(HeadJournal!B$1),0),"") -> IHORD0000446652NPG | C33: =IFERROR(VLOOKUP($A33,HeadJournal!$A$1:$NTR$890,COLUMN(HeadJournal!C$1),0),"") -> iHerb_MH DLE7202 | D33: =IFERROR(VLOOKUP($A33,HeadJournal!$A$1:$NTR$890,COLUMN(HeadJournal!D$1),0),"") -> Доставлен | E33: =IFERROR(VLOOKUP($A33,HeadJournal!$A$1:$NTR$890,COLUMN(HeadJournal!G$1),0),"") -> 44788 | F33: =IFERROR(TEXT(E33, "ГГГГ ММ"),"") -> 2022 08 | G33: Витамины | H33: NOR-56780 | I33: Nordic Naturals | J33: Children's DHA, ДГК для детей от 1 до 6 лет, со вкусом клубники, 530 мг, 119 мл (4 жидк. унции) (530 мг в 1/2 ч. л.) | K33: 567.03 | L33: -56.7 | M33: =IFERROR(VLOOKUP($A33,HeadJournal!$A$1:$J$890,COLUMN(HeadJournal!I$1),0)*($K33+$L33)/(SUMIF($A:$A,$A33,$K:$K)+SUMIF($A:$A,$A33,$L:$L)),0) -> -80.552422 | N33: =IFERROR((VLOOKUP($A33,HeadJournal!$A$1:$K$890,COLUMN(HeadJournal!K$1),0)-VLOOKUP($A33,HeadJournal!$A$1:$K$890,COLUMN(HeadJournal!J$1),0))*($K33+$L33)/(SUMIF($A:$A,$A33,$K:$K)+SUMIF($A:$A,$A33,$L:$L)),0) -> 10.92683 | O33: =IFERROR((VLOOKUP($A33,HeadJournal!$A$1:$L$890,COLUMN(HeadJournal!L$1),0)*($K33+$L33)/(SUMIF($A:$A,$A33,$K:$K)+SUMIF($A:$A,$A33,$L:$L)))/VLOOKUP($A33,HeadJournal!$A$1:$L$890,COLUMN(HeadJournal!H$1),0),0) -> 79.162721 | P33: =IFERROR(SUM(K33:O33)*VLOOKUP($A33,HeadJournal!$A$1:$L$890,COLUMN(HeadJournal!H$1),0),0) -> 779.80069 | Q33: 2100 | R33: 44804 | S33: <Клиент не выбран> | T33: =IF(R33="","",TEXT(R33,"ГГГГ ММ")) -> 2022 08 | U33: =Q33-P33 -> 1320.1993 | V33: =IF(Q33<>0,IFERROR(U33/P33,""),"") -> 1.6929958
A34: 920706319 | B34: =IFERROR(VLOOKUP($A34,HeadJournal!$A$1:$NTR$890,COLUMN(HeadJournal!B$1),0),"") -> IHORD0000446652NPG | C34: =IFERROR(VLOOKUP($A34,HeadJournal!$A$1:$NTR$890,COLUMN(HeadJournal!C$1),0),"") -> iHerb_MH DLE7202 | D34: =IFERROR(VLOOKUP($A34,HeadJournal!$A$1:$NTR$890,COLUMN(HeadJournal!D$1),0),"") -> Доставлен | E34: =IFERROR(VLOOKUP($A34,HeadJournal!$A$1:$NTR$890,COLUMN(HeadJournal!G$1),0),"") -> 44788 | F34: =IFERROR(TEXT(E34, "ГГГГ ММ"),"") -> 2022 08 | G34: Витамины | H34: NOW-02644 | I34: NOW Foods | J34: жидкий хлорофилл, аромат натуральной мяты, 473 мл (16 жидк. унций) | K34: 641.03 | L34: -64.1 | M34: =IFERROR(VLOOKUP($A34,HeadJournal!$A$1:$J$890,COLUMN(HeadJournal!I$1),0)*($K34+$L34)/(SUMIF($A:$A,$A34,$K:$K)+SUMIF($A:$A,$A34,$L:$L)),0) -> -91.064819 | N34: =IFERROR((VLOOKUP($A34,HeadJournal!$A$1:$K$890,COLUMN(HeadJournal!K$1),0)-VLOOKUP($A34,HeadJournal!$A$1:$K$890,COLUMN(HeadJournal!J$1),0))*($K34+$L34)/(SUMIF($A:$A,$A34,$K:$K)+SUMIF($A:$A,$A34,$L:$L)),0) -> 12.352823 | O34: =IFERROR((VLOOKUP($A34,HeadJournal!$A$1:$L$890,COLUMN(HeadJournal!L$1),0)*($K34+$L34)/(SUMIF($A:$A,$A34,$K:$K)+SUMIF($A:$A,$A34,$L:$L)))/VLOOKUP($A34,HeadJournal!$A$1:$L$890,COLUMN(HeadJournal!H$1),0),0) -> 89.493756 | P34: =IFERROR(SUM(K34:O34)*VLOOKUP($A34,HeadJournal!$A$1:$L$890,COLUMN(HeadJournal!H$1),0),0) -> 881.56764 | Q34: 881.57 | R34: 44805 | S34: <Клиент не выбран> | T34: =IF(R34="","",TEXT(R34,"ГГГГ ММ")) -> 2022 09 | U34: =Q34-P34 -> 0.0023596178 | V34: =IF(Q34<>0,IFERROR(U34/P34,""),"") -> 2.6766157e-06
A35: 920706319 | B35: =IFERROR(VLOOKUP($A35,HeadJournal!$A$1:$NTR$890,COLUMN(HeadJournal!B$1),0),"") -> IHORD0000446652NPG | C35: =IFERROR(VLOOKUP($A35,HeadJournal!$A$1:$NTR$890,COLUMN(HeadJournal!C$1),0),"") -> iHerb_MH DLE7202 | D35: =IFERROR(VLOOKUP($A35,HeadJournal!$A$1:$NTR$890,COLUMN(HeadJournal!D$1),0),"") -> Доставлен | E35: =IFERROR(VLOOKUP($A35,HeadJournal!$A$1:$NTR$890,COLUMN(HeadJournal!G$1),0),"") -> 44788 | F35: =IFERROR(TEXT(E35, "ГГГГ ММ"),"") -> 2022 08 | G35: Витамины | H35: MLI-00952 | I35: California Gold Nutrition | J35: премиальный рыбий жир с омега-3, 100 капсул из рыбьего желатина (1100 мг в 1 капсуле) | K35: 269.72 | L35: -131.01 | M35: =IFERROR(VLOOKUP($A35,HeadJournal!$A$1:$J$890,COLUMN(HeadJournal!I$1),0)*($K35+$L35)/(SUMIF($A:$A,$A35,$K:$K)+SUMIF($A:$A,$A35,$L:$L)),0) -> -21.894512 | N35: =IFERROR((VLOOKUP($A35,HeadJournal!$A$1:$K$890,COLUMN(HeadJournal!K$1),0)-VLOOKUP($A35,HeadJournal!$A$1:$K$890,COLUMN(HeadJournal!J$1),0))*($K35+$L35)/(SUMIF($A:$A,$A35,$K:$K)+SUMIF($A:$A,$A35,$L:$L)),0) -> 2.9699619 | O35: =IFERROR((VLOOKUP($A35,HeadJournal!$A$1:$L$890,COLUMN(HeadJournal!L$1),0)*($K35+$L35)/(SUMIF($A:$A,$A35,$K:$K)+SUMIF($A:$A,$A35,$L:$L)))/VLOOKUP($A35,HeadJournal!$A$1:$L$890,COLUMN(HeadJournal!H$1),0),0) -> 21.516785 | P35: =IFERROR(SUM(K35:O35)*VLOOKUP($A35,HeadJournal!$A$1:$L$890,COLUMN(HeadJournal!H$1),0),0) -> 211.95335 | Q35: 900 | R35: 44821 | S35: <Клиент не выбран> | T35: =IF(R35="","",TEXT(R35,"ГГГГ ММ")) -> 2022 09 | U35: =Q35-P35 -> 688.04665 | V35: =IF(Q35<>0,IFERROR(U35/P35,""),"") -> 3.2462173
A36: 920706319 | B36: =IFERROR(VLOOKUP($A36,HeadJournal!$A$1:$NTR$890,COLUMN(HeadJournal!B$1),0),"") -> IHORD0000446652NPG | C36: =IFERROR(VLOOKUP($A36,HeadJournal!$A$1:$NTR$890,COLUMN(HeadJournal!C$1),0),"") -> iHerb_MH DLE7202 | D36: =IFERROR(VLOOKUP($A36,HeadJournal!$A$1:$NTR$890,COLUMN(HeadJournal!D$1),0),"") -> Доставлен | E36: =IFERROR(VLOOKUP($A36,HeadJournal!$A$1:$NTR$890,COLUMN(HeadJournal!G$1),0),"") -> 44788 | F36: =IFERROR(TEXT(E36, "ГГГГ ММ"),"") -> 2022 08 | G36: Витамины | H36: MLI-00952 | I36: California Gold Nutrition | J36: премиальный рыбий жир с омега-3, 100 капсул из рыбьего желатина (1100 мг в 1 капсуле) | K36: 269.72 | L36: -131.01 | M36: =IFERROR(VLOOKUP($A36,HeadJournal!$A$1:$J$890,COLUMN(HeadJournal!I$1),0)*($K36+$L36)/(SUMIF($A:$A,$A36,$K:$K)+SUMIF($A:$A,$A36,$L:$L)),0) -> -21.894512 | N36: =IFERROR((VLOOKUP($A36,HeadJournal!$A$1:$K$890,COLUMN(HeadJournal!K$1),0)-VLOOKUP($A36,HeadJournal!$A$1:$K$890,COLUMN(HeadJournal!J$1),0))*($K36+$L36)/(SUMIF($A:$A,$A36,$K:$K)+SUMIF($A:$A,$A36,$L:$L)),0) -> 2.9699619 | O36: =IFERROR((VLOOKUP($A36,HeadJournal!$A$1:$L$890,COLUMN(HeadJournal!L$1),0)*($K36+$L36)/(SUMIF($A:$A,$A36,$K:$K)+SUMIF($A:$A,$A36,$L:$L)))/VLOOKUP($A36,HeadJournal!$A$1:$L$890,COLUMN(HeadJournal!H$1),0),0) -> 21.516785 | P36: =IFERROR(SUM(K36:O36)*VLOOKUP($A36,HeadJournal!$A$1:$L$890,COLUMN(HeadJournal!H$1),0),0) -> 211.95335 | Q36: 900 | R36: 44821 | S36: <Клиент не выбран> | T36: =IF(R36="","",TEXT(R36,"ГГГГ ММ")) -> 2022 09 | U36: =Q36-P36 -> 688.04665 | V36: =IF(Q36<>0,IFERROR(U36/P36,""),"") -> 3.2462173
A37: 920706319 | B37: =IFERROR(VLOOKUP($A37,HeadJournal!$A$1:$NTR$890,COLUMN(HeadJournal!B$1),0),"") -> IHORD0000446652NPG | C37: =IFERROR(VLOOKUP($A37,HeadJournal!$A$1:$NTR$890,COLUMN(HeadJournal!C$1),0),"") -> iHerb_MH DLE7202 | D37: =IFERROR(VLOOKUP($A37,HeadJournal!$A$1:$NTR$890,COLUMN(HeadJournal!D$1),0),"") -> Доставлен | E37: =IFERROR(VLOOKUP($A37,HeadJournal!$A$1:$NTR$890,COLUMN(HeadJournal!G$1),0),"") -> 44788 | F37: =IFERROR(TEXT(E37, "ГГГГ ММ"),"") -> 2022 08 | G37: Витамины | H37: =RIGHT(Journal!$J37,9) -> SOR-45931 | I37: =IFERROR(LEFT(J37,FIND(",",J37)-1),"") -> Solaray | J37: Solaray, Медь, 2&nbsp;мг, 100&nbsp;вегетарианских капсул SOR-45931 | K37: 180.27 | L37: -18.02 | M37: =IFERROR(VLOOKUP($A37,HeadJournal!$A$1:$J$890,COLUMN(HeadJournal!I$1),0)*($K37+$L37)/(SUMIF($A:$A,$A37,$K:$K)+SUMIF($A:$A,$A37,$L:$L)),0) -> -25.610155 | N37: =IFERROR((VLOOKUP($A37,HeadJournal!$A$1:$K$890,COLUMN(HeadJournal!K$1),0)-VLOOKUP($A37,HeadJournal!$A$1:$K$890,COLUMN(HeadJournal!J$1),0))*($K37+$L37)/(SUMIF($A:$A,$A37,$K:$K)+SUMIF($A:$A,$A37,$L:$L)),0) -> 3.4739839 | O37: =IFERROR((VLOOKUP($A37,HeadJournal!$A$1:$L$890,COLUMN(HeadJournal!L$1),0)*($K37+$L37)/(SUMIF($A:$A,$A37,$K:$K)+SUMIF($A:$A,$A37,$L:$L)))/VLOOKUP($A37,HeadJournal!$A$1:$L$890,COLUMN(HeadJournal!H$1),0),0) -> 25.168325 | P37: =IFERROR(SUM(K37:O37)*VLOOKUP($A37,HeadJournal!$A$1:$L$890,COLUMN(HeadJournal!H$1),0),0) -> 247.92323 | Q37: 900 | R37: 44804 | S37: <Клиент не выбран> | T37: =IF(R37="","",TEXT(R37,"ГГГГ ММ")) -> 2022 08 | U37: =Q37-P37 -> 652.07677 | V37: =IF(Q37<>0,IFERROR(U37/P37,""),"") -> 2.630156
A38: 920706319 | B38: =IFERROR(VLOOKUP($A38,HeadJournal!$A$1:$NTR$890,COLUMN(HeadJournal!B$1),0),"") -> IHORD0000446652NPG | C38: =IFERROR(VLOOKUP($A38,HeadJournal!$A$1:$NTR$890,COLUMN(HeadJournal!C$1),0),"") -> iHerb_MH DLE7202 | D38: =IFERROR(VLOOKUP($A38,HeadJournal!$A$1:$NTR$890,COLUMN(HeadJournal!D$1),0),"") -> Доставлен | E38: =IFERROR(VLOOKUP($A38,HeadJournal!$A$1:$NTR$890,COLUMN(HeadJournal!G$1),0),"") -> 44788 | F38: =IFERROR(TEXT(E38, "ГГГГ ММ"),"") -> 2022 08 | G38: Витамины | H38: CEN-27387 | I38: 21st Century | J38: глюкозамин, хондроитин, гиалуроновая кислота и МСМ, 120 таблеток | K38: 808.85 | L38: -80.88 | M38: =IFERROR(VLOOKUP($A38,HeadJournal!$A$1:$J$890,COLUMN(HeadJournal!I$1),0)*($K38+$L38)/(SUMIF($A:$A,$A38,$K:$K)+SUMIF($A:$A,$A38,$L:$L)),0) -> -114.90555 | N38: =IFERROR((VLOOKUP($A38,HeadJournal!$A$1:$K$890,COLUMN(HeadJournal!K$1),0)-VLOOKUP($A38,HeadJournal!$A$1:$K$890,COLUMN(HeadJournal!J$1),0))*($K38+$L38)/(SUMIF($A:$A,$A38,$K:$K)+SUMIF($A:$A,$A38,$L:$L)),0) -> 15.586786 | O38: =IFERROR((VLOOKUP($A38,HeadJournal!$A$1:$L$890,COLUMN(HeadJournal!L$1),0)*($K38+$L38)/(SUMIF($A:$A,$A38,$K:$K)+SUMIF($A:$A,$A38,$L:$L)))/VLOOKUP($A38,HeadJournal!$A$1:$L$890,COLUMN(HeadJournal!H$1),0),0) -> 112.92318 | P38: =IFERROR(SUM(K38:O38)*VLOOKUP($A38,HeadJournal!$A$1:$L$890,COLUMN(HeadJournal!H$1),0),0) -> 1112.3616 | Q38: 2500 | R38: 44804 | S38: <Клиент не выбран> | T38: =IF(R38="","",TEXT(R38,"ГГГГ ММ")) -> 2022 08 | U38: =Q38-P38 -> 1387.6384 | V38: =IF(Q38<>0,IFERROR(U38/P38,""),"") -> 1.2474705
A39: 920706319 | B39: =IFERROR(VLOOKUP($A39,HeadJournal!$A$1:$NTR$890,COLUMN(HeadJournal!B$1),0),"") -> IHORD0000446652NPG | C39: =IFERROR(VLOOKUP($A39,HeadJournal!$A$1:$NTR$890,COLUMN(HeadJournal!C$1),0),"") -> iHerb_MH DLE7202 | D39: =IFERROR(VLOOKUP($A39,HeadJournal!$A$1:$NTR$890,COLUMN(HeadJournal!D$1),0),"") -> Доставлен | E39: =IFERROR(VLOOKUP($A39,HeadJournal!$A$1:$NTR$890,COLUMN(HeadJournal!G$1),0),"") -> 44788 | F39: =IFERROR(TEXT(E39, "ГГГГ ММ"),"") -> 2022 08 | G39: Витамины | H39: CGN-00931 | I39: California Gold Nutrition | J39: Gold C™, витамин C класса USP, 1000 мг, 60 растительных капсул | K39: 192.66 | L39: -154.13 | M39: =IFERROR(VLOOKUP($A39,HeadJournal!$A$1:$J$890,COLUMN(HeadJournal!I$1),0)*($K39+$L39)/(SUMIF($A:$A,$A39,$K:$K)+SUMIF($A:$A,$A39,$L:$L)),0) -> -6.0817213 | N39: =IFERROR((VLOOKUP($A39,HeadJournal!$A$1:$K$890,COLUMN(HeadJournal!K$1),0)-VLOOKUP($A39,HeadJournal!$A$1:$K$890,COLUMN(HeadJournal!J$1),0))*($K39+$L39)/(SUMIF($A:$A,$A39,$K:$K)+SUMIF($A:$A,$A39,$L:$L)),0) -> 0.82497751 | O39: =IFERROR((VLOOKUP($A39,HeadJournal!$A$1:$L$890,COLUMN(HeadJournal!L$1),0)*($K39+$L39)/(SUMIF($A:$A,$A39,$K:$K)+SUMIF($A:$A,$A39,$L:$L)))/VLOOKUP($A39,HeadJournal!$A$1:$L$890,COLUMN(HeadJournal!H$1),0),0) -> 5.9767986 | P39: =IFERROR(SUM(K39:O39)*VLOOKUP($A39,HeadJournal!$A$1:$L$890,COLUMN(HeadJournal!H$1),0),0) -> 58.875082 | Q39: 600 | R39: 44828 | S39: <Клиент не выбран> | T39: =IF(R39="","",TEXT(R39,"ГГГГ ММ")) -> 2022 09 | U39: =Q39-P39 -> 541.12492 | V39: =IF(Q39<>0,IFERROR(U39/P39,""),"") -> 9.1910686
A40: 920706319 | B40: =IFERROR(VLOOKUP($A40,HeadJournal!$A$1:$NTR$890,COLUMN(HeadJournal!B$1),0),"") -> IHORD0000446652NPG | C40: =IFERROR(VLOOKUP($A40,HeadJournal!$A$1:$NTR$890,COLUMN(HeadJournal!C$1),0),"") -> iHerb_MH DLE7202 | D40: =IFERROR(VLOOKUP($A40,HeadJournal!$A$1:$NTR$890,COLUMN(HeadJournal!D$1),0),"") -> Доставлен | E40: =IFERROR(VLOOKUP($A40,HeadJournal!$A$1:$NTR$890,COLUMN(HeadJournal!G$1),0),"") -> 44788 | F40: =IFERROR(TEXT(E40, "ГГГГ ММ"),"") -> 2022 08 | G40: Витамины | H40: =RIGHT(Journal!$J40,9) -> NAP-03770 | I40: =IFERROR(LEFT(J40,FIND(",",J40)-1),"") -> NaturesPlus | J40: NaturesPlus, Hema-Plex, 30 таблеток с длительным высвобождением NAP-03770 | K40: 347.52 | L40: -34.75 | M40: =IFERROR(VLOOKUP($A40,HeadJournal!$A$1:$J$890,COLUMN(HeadJournal!I$1),0)*($K40+$L40)/(SUMIF($A:$A,$A40,$K:$K)+SUMIF($A:$A,$A40,$L:$L)),0) -> -49.368803 | N40: =IFERROR((VLOOKUP($A40,HeadJournal!$A$1:$K$890,COLUMN(HeadJournal!K$1),0)-VLOOKUP($A40,HeadJournal!$A$1:$K$890,COLUMN(HeadJournal!J$1),0))*($K40+$L40)/(SUMIF($A:$A,$A40,$K:$K)+SUMIF($A:$A,$A40,$L:$L)),0) -> 6.6968133 | O40: =IFERROR((VLOOKUP($A40,HeadJournal!$A$1:$L$890,COLUMN(HeadJournal!L$1),0)*($K40+$L40)/(SUMIF($A:$A,$A40,$K:$K)+SUMIF($A:$A,$A40,$L:$L)))/VLOOKUP($A40,HeadJournal!$A$1:$L$890,COLUMN(HeadJournal!H$1),0),0) -> 48.517085 | P40: =IFERROR(SUM(K40:O40)*VLOOKUP($A40,HeadJournal!$A$1:$L$890,COLUMN(HeadJournal!H$1),0),0) -> 477.92264 | Q40: 1000 | R40: 44804 | S40: <Клиент не выбран> | T40: =IF(R40="","",TEXT(R40,"ГГГГ ММ")) -> 2022 08 | U40: =Q40-P40 -> 522.07736 | V40: =IF(Q40<>0,IFERROR(U40/P40,""),"") -> 1.0923888
A41: 513638852 | B41: =IFERROR(VLOOKUP($A41,HeadJournal!$A$1:$NTR$890,COLUMN(HeadJournal!B$1),0),"") -> IHORD0000452586NPG | C41: =IFERROR(VLOOKUP($A41,HeadJournal!$A$1:$NTR$890,COLUMN(HeadJournal!C$1),0),"") -> iHerb_OA CZN6870 | D41: =IFERROR(VLOOKUP($A41,HeadJournal!$A$1:$NTR$890,COLUMN(HeadJournal!D$1),0),"") -> Доставлен | E41: =IFERROR(VLOOKUP($A41,HeadJournal!$A$1:$NTR$890,COLUMN(HeadJournal!G$1),0),"") -> 44793 | F41: =IFERROR(TEXT(E41, "ГГГГ ММ"),"") -> 2022 08 | G41: Витамины | H41: SBL-00121 | I41: Sambucol | J41: Сироп из черной бузины, для детей, ягодный аромат, 230 мл (7,8 жидк, унции) | K41: 892.38 | L41: -89.26 | M41: =IFERROR(VLOOKUP($A41,HeadJournal!$A$1:$J$890,COLUMN(HeadJournal!I$1),0)*($K41+$L41)/(SUMIF($A:$A,$A41,$K:$K)+SUMIF($A:$A,$A41,$L:$L)),0) -> -0.85966256 | N41: =IFERROR((VLOOKUP($A41,HeadJournal!$A$1:$K$890,COLUMN(HeadJournal!K$1),0)-VLOOKUP($A41,HeadJournal!$A$1:$K$890,COLUMN(HeadJournal!J$1),0))*($K41+$L41)/(SUMIF($A:$A,$A41,$K:$K)+SUMIF($A:$A,$A41,$L:$L)),0) -> 20.401884 | O41: =IFERROR((VLOOKUP($A41,HeadJournal!$A$1:$L$890,COLUMN(HeadJournal!L$1),0)*($K41+$L41)/(SUMIF($A:$A,$A41,$K:$K)+SUMIF($A:$A,$A41,$L:$L)))/VLOOKUP($A41,HeadJournal!$A$1:$L$890,COLUMN(HeadJournal!H$1),0),0) -> 154.89416 | P41: =IFERROR(SUM(K41:O41)*VLOOKUP($A41,HeadJournal!$A$1:$L$890,COLUMN(HeadJournal!H$1),0),0) -> 1466.3346 | Q41: 2600 | R41: 44828 | S41: <Клиент не выбран> | T41: =IF(R41="","",TEXT(R41,"ГГГГ ММ")) -> 2022 09 | U41: =Q41-P41 -> 1133.6654 | V41: =IF(Q41<>0,IFERROR(U41/P41,""),"") -> 0.77312877
A42: 513638852 | B42: =IFERROR(VLOOKUP($A42,HeadJournal!$A$1:$NTR$890,COLUMN(HeadJournal!B$1),0),"") -> IHORD0000452586NPG | C42: =IFERROR(VLOOKUP($A42,HeadJournal!$A$1:$NTR$890,COLUMN(HeadJournal!C$1),0),"") -> iHerb_OA CZN6870 | D42: =IFERROR(VLOOKUP($A42,HeadJournal!$A$1:$NTR$890,COLUMN(HeadJournal!D$1),0),"") -> Доставлен | E42: =IFERROR(VLOOKUP($A42,HeadJournal!$A$1:$NTR$890,COLUMN(HeadJournal!G$1),0),"") -> 44793 | F42: =IFERROR(TEXT(E42, "ГГГГ ММ"),"") -> 2022 08 | G42: Витамины | H42: =RIGHT(Journal!$J42,9) -> NOW-02120 | I42: =IFERROR(LEFT(J42,FIND(",",J42)-1),"") -> NOW Foods | J42: NOW Foods, МСМ, метил-сульфонил-метан, 1000 мг, 120 капсул в растительной оболочке NOW-02120 | K42: 327.73 | L42: -32.77 | M42: =IFERROR(VLOOKUP($A42,HeadJournal!$A$1:$J$890,COLUMN(HeadJournal!I$1),0)*($K42+$L42)/(SUMIF($A:$A,$A42,$K:$K)+SUMIF($A:$A,$A42,$L:$L)),0) -> -0.31572625 | N42: =IFERROR((VLOOKUP($A42,HeadJournal!$A$1:$K$890,COLUMN(HeadJournal!K$1),0)-VLOOKUP($A42,HeadJournal!$A$1:$K$890,COLUMN(HeadJournal!J$1),0))*($K42+$L42)/(SUMIF($A:$A,$A42,$K:$K)+SUMIF($A:$A,$A42,$L:$L)),0) -> 7.492952 | O42: =IFERROR((VLOOKUP($A42,HeadJournal!$A$1:$L$890,COLUMN(HeadJournal!L$1),0)*($K42+$L42)/(SUMIF($A:$A,$A42,$K:$K)+SUMIF($A:$A,$A42,$L:$L)))/VLOOKUP($A42,HeadJournal!$A$1:$L$890,COLUMN(HeadJournal!H$1),0),0) -> 56.887613 | P42: =IFERROR(SUM(K42:O42)*VLOOKUP($A42,HeadJournal!$A$1:$L$890,COLUMN(HeadJournal!H$1),0),0) -> 538.53726 | Q42: 905 | R42: 44821 | S42: <Клиент не выбран> | T42: =IF(R42="","",TEXT(R42,"ГГГГ ММ")) -> 2022 09 | U42: =Q42-P42 -> 366.46274 | V42: =IF(Q42<>0,IFERROR(U42/P42,""),"") -> 0.68047797
A43: 513638852 | B43: =IFERROR(VLOOKUP($A43,HeadJournal!$A$1:$NTR$890,COLUMN(HeadJournal!B$1),0),"") -> IHORD0000452586NPG | C43: =IFERROR(VLOOKUP($A43,HeadJournal!$A$1:$NTR$890,COLUMN(HeadJournal!C$1),0),"") -> iHerb_OA CZN6870 | D43: =IFERROR(VLOOKUP($A43,HeadJournal!$A$1:$NTR$890,COLUMN(HeadJournal!D$1),0),"") -> Доставлен | E43: =IFERROR(VLOOKUP($A43,HeadJournal!$A$1:$NTR$890,COLUMN(HeadJournal!G$1),0),"") -> 44793 | F43: =IFERROR(TEXT(E43, "ГГГГ ММ"),"") -> 2022 08 | G43: Витамины | H43: MLI-00952 | I43: California Gold Nutrition | J43: премиальный рыбий жир с омега-3, 100 капсул из рыбьего желатина (1100 мг в 1 капсуле) | K43: 269.72 | L43: -131.01 | M43: =IFERROR(VLOOKUP($A43,HeadJournal!$A$1:$J$890,COLUMN(HeadJournal!I$1),0)*($K43+$L43)/(SUMIF($A:$A,$A43,$K:$K)+SUMIF($A:$A,$A43,$L:$L)),0) -> -0.14847569 | N43: =IFERROR((VLOOKUP($A43,HeadJournal!$A$1:$K$890,COLUMN(HeadJournal!K$1),0)-VLOOKUP($A43,HeadJournal!$A$1:$K$890,COLUMN(HeadJournal!J$1),0))*($K43+$L43)/(SUMIF($A:$A,$A43,$K:$K)+SUMIF($A:$A,$A43,$L:$L)),0) -> 3.5236892 | O43: =IFERROR((VLOOKUP($A43,HeadJournal!$A$1:$L$890,COLUMN(HeadJournal!L$1),0)*($K43+$L43)/(SUMIF($A:$A,$A43,$K:$K)+SUMIF($A:$A,$A43,$L:$L)))/VLOOKUP($A43,HeadJournal!$A$1:$L$890,COLUMN(HeadJournal!H$1),0),0) -> 26.752376 | P43: =IFERROR(SUM(K43:O43)*VLOOKUP($A43,HeadJournal!$A$1:$L$890,COLUMN(HeadJournal!H$1),0),0) -> 253.25638 | Q43: 900 | R43: 44825 | S43: <Клиент не выбран> | T43: =IF(R43="","",TEXT(R43,"ГГГГ ММ")) -> 2022 09 | U43: =Q43-P43 -> 646.74362 | V43: =IF(Q43<>0,IFERROR(U43/P43,""),"") -> 2.553711
